Workbook
Name base: [1]Feuil2!$B$4:$M$37

Sheet 👥 Personnel
A1: LISTE DU PERSONNEL - Saisir ici vos salariés
A3: ID | B3: Fonction à supprimer | C3: Nom | D3: Prénom | E3: Site | F3: Fonction | G3: Type de contrat | H3: Catégorie | I3: Coef | J3: Sexe | K3: Date Entree | L3: Date d'anc. | M3: Date de naissance | N3: Salaire Brut Mensuel (Base brut CP) | O3: Salaire Brut annuel | P3: Nb CP Acquis | Q3: Date de sortie théorique | R3: Salaire Brut de référence | S3: Provision CP | T3: Ancienneté (ans) réelle | U3: Age | V3: Salaire Annuel Total | W3: Préavis (mois) | X3: Ancienneté (ans) à la date théorique de sortie | Y3: Salarié Protégé | Z3: Situation familiale | AA3: Nb d'enfants | AB3: Charge de famille | AC3: Difficulté de reclassement | AD3: Nb de points | AE3: Commentaires | AF3: CSP (contrat de sécurisation professionnel) | AG3: INDEM LÉGALE | AH3: INDEM CONV. | AI3: COMPARAISON | AJ3: INDEM RETENUE | AK3: Majoration PSE | AL3: TOTAL INDEM | AM3: Préavis Calc (mois) | AN3: Indem Préavis Brut | AO3: CP Calc (jrs) | AP3: Indem CP | AQ3: COÛT Charges Patronales | AR3: COÛT TOTAL
A4: 3 | B4: Non | C4: BASTARD | D4: Gilles | E4: PUSIGNAN | F4: Manutentionnaire | G4: CDI | H4: Ouvrier | I4: 138M | J4: H | K4: 39153 | L4: 39153 | M4: 25026 | N4: 2320.54 | P4: 30.58 | Q4: =IF(UPPER(B4)="OUI",'📈 Dashboard'!$B$37,"") | R4: =MAX(N4,O4/12) -> 2320.54 | S4: 3223.72 | T4: =IF(L4="",(TODAY()-K4)/365.25,MAX((TODAY()-K4)/365.25,(TODAY()-L4)/365.25)) -> 19.011636 | U4: =IF(M4="","",(TODAY()-M4)/365.25) -> 57.689254 | V4: =N4*12 -> 27846.48 | W4: =IF(H4="Cadre",3,IF(H4="Haute maitrise",2,IF(OR(H4="Agent Maitrise",H4="Agent de maitrise"),IF(T4<2/12,0,IF(T4<2,1,2)),IF(OR(H4="Ouvrier"),IF(T4<6/12,1/4,IF(T4<2,1,2)),IF(OR(H4="Employe",H4="Employé"),IF(T4<1/12,0,IF(T4<2,1,2)),2))))) -> 2 | X4: =IF(Q4="",T4,(Q4-K4)/365.25) -> 19.011636 | AG4: =IF(TPersonnel[[#This Row],[Fonction à supprimer]]="NON",0,IF(TPersonnel[[#This Row],[Ancienneté (ans) à la date théorique de sortie]]<0.67,0,IF(TPersonnel[[#This Row],[Ancienneté (ans) à la date théorique de sortie]]<=10,TPersonnel[[#This Row],[Ancienneté (ans) à la date théorique de sortie]]*TPersonnel[[#This Row],[Salaire Brut de référence]]/4,(10*TPersonnel[[#This Row],[Salaire Brut de référence]]/4+(TPersonnel[[#This Row],[Ancienneté (ans) à la date théorique de sortie]]-10)*TPersonnel[[#This Row],[Salaire Brut de référence]]/3)))) -> 0 | AH4: =IF(UPPER(TPersonnel[[#This Row],[Fonction à supprimer]])="NON",0,IF(TPersonnel[[#This Row],[Ancienneté (ans) à la date théorique de sortie]]<1,0,IF(OR(TPersonnel[[#This Row],[Catégorie]]="Ouvrier",TPersonnel[[#This Row],[Catégorie]]="Employe",TPersonnel[[#This Row],[Catégorie]]="Employé"),IF(TPersonnel[[#This Row],[Ancienneté (ans) à la date théorique de sortie]]<3,TPersonnel[[#This Row],[Ancienneté (ans) à la date théorique de sortie]]*TPersonnel[[#This Row],[Salaire Brut de référence]]/10,TPersonnel[[#This Row],[Ancienneté (ans) à la date théorique de sortie]]*TPersonnel[[#This Row],[Salaire Brut de référence]]*2/10),IF(OR(TPersonnel[[#This Row],[Catégorie]]="Agent Maitrise",TPersonnel[[#This Row],[Catégorie]]="Agent de maitrise",TPersonnel[[#This Row],[Catégorie]]="Haute maitrise"),IF(TPersonnel[[#This Row],[Ancienneté (ans) à la date théorique de sortie]]<3,TPersonnel[[#This Row],[Ancienneté (ans) à la date théorique de sortie]]*TPersonnel[[#This Row],[Salaire Brut de référence]]/10,TPersonnel[[#This Row],[Ancienneté (ans) à la date théorique de sortie]]*TPersonnel[[#This Row],[Salaire Brut de référence]]*3/10),IF(TPersonnel[[#This Row],[Catégorie]]="Cadre",IF(TPersonnel[[#This Row],[Ancienneté (ans) à la date théorique de sortie]]<3,0,TPersonnel[[#This Row],[Ancienneté (ans) à la date théorique de sortie]]*TPersonnel[[#This Row],[Salaire Brut de référence]]*4/10),0))))) -> 0 | AI4: =IF(TPersonnel[[#This Row],[INDEM LÉGALE]]=0,"",IF(TPersonnel[[#This Row],[INDEM LÉGALE]]>TPersonnel[[#This Row],[INDEM CONV.]],"LEGAL","CONVENTIONNEL")) | AJ4: =MAX(TPersonnel[[#This Row],[INDEM LÉGALE]],TPersonnel[[#This Row],[INDEM CONV.]]) -> 0 | AK4: =TPersonnel[[#This Row],[INDEM RETENUE]]*'⚙️ Parametres'!$B$5 -> 0 | AL4: =TPersonnel[[#This Row],[INDEM RETENUE]]+TPersonnel[[#This Row],[Majoration PSE]] -> 0 | AM4: =IF(UPPER(TPersonnel[[#This Row],[Fonction à supprimer]])="NON",0,IF(OR(TPersonnel[[#This Row],[Catégorie]]="Cadre"),3,IF(TPersonnel[[#This Row],[Catégorie]]="Haute maitrise",2,IF(OR(TPersonnel[[#This Row],[Catégorie]]="Agent Maitrise",TPersonnel[[#This Row],[Catégorie]]="Agent de maitrise"),IF(TPersonnel[[#This Row],[Ancienneté (ans) à la date théorique de sortie]]<2/12,0,IF(TPersonnel[[#This Row],[Ancienneté (ans) à la date théorique de sortie]]<2,1,2)),IF(OR(TPersonnel[[#This Row],[Catégorie]]="Ouvrier",TPersonnel[[#This Row],[Catégorie]]="Employe",TPersonnel[[#This Row],[Catégorie]]="Employé"),IF(TPersonnel[[#This Row],[Ancienneté (ans) à la date théorique de sortie]]<6/12,IF(TPersonnel[[#This Row],[Catégorie]]="Ouvrier",1/4,IF(TPersonnel[[#This Row],[Ancienneté (ans) à la date théorique de sortie]]<1/12,0,1)),IF(TPersonnel[[#This Row],[Ancienneté (ans) à la date théorique de sortie]]<2,1,2)),2))))) -> 0 | AN4: =IF(UPPER(TPersonnel[[#This Row],[Fonction à supprimer]])="NON",0,TPersonnel[[#This Row],[Préavis Calc (mois)]]*TPersonnel[[#This Row],[Salaire Brut de référence]]) -> 0 | AO4: =IF(TPersonnel[[#This Row],[Fonction à supprimer]]="NON",0,TPersonnel[[#This Row],[Nb CP Acquis]]+TPersonnel[[#This Row],[Préavis Calc (mois)]]*2.08) -> 0 | AP4: =TPersonnel[[#This Row],[CP Calc (jrs)]]*TPersonnel[[#This Row],[Salaire Brut de référence]]/21.67 -> 0 | AQ4: =IF(UPPER(TPersonnel[[#This Row],[Fonction à supprimer]])="NON",0,_xlfn.LET(_xlpm.taux,IF(TPersonnel[[#This Row],[Catégorie]]="Ouvrier",'📈 Dashboard'!$B$32,IF(TPersonnel[[#This Row],[Catégorie]]="Cadre",'📈 Dashboard'!$B$34,'📈 Dashboard'!$B$33)),_xlpm.csp,UPPER(TPersonnel[[#This Row],[CSP (contrat de sécurisation professionnel)]])="OUI",IF(AND(_xlpm.csp,TPersonnel[[#This Row],[Ancienneté (ans) à la date théorique de sortie]]>=1),MIN(TPersonnel[[#This Row],[Préavis Calc (mois)]],3)*TPersonnel[[#This Row],[Salaire Brut de référence]]*(_xlpm.taux+'⚙️ Parametres'!$B$11)+IF(TPersonnel[[#This Row],[Préavis Calc (mois)]]>3,(TPersonnel[[#This Row],[Préavis Calc (mois)]]-3)*TPersonnel[[#This Row],[Salaire Brut de référence]]*_xlpm.taux,0)+TPersonnel[[#This Row],[Indem CP]]*_xlpm.taux,IF(_xlpm.csp,TPersonnel[[#This Row],[Indem CP]]*_xlpm.taux,(TPersonnel[[#This Row],[Indem Préavis Brut]]+TPersonnel[[#This Row],[Indem CP]])*_xlpm.taux)))) -> 0 | AR4: =TPersonnel[[#This Row],[TOTAL INDEM]]+TPersonnel[[#This Row],[Indem Préavis Brut]]+TPersonnel[[#This Row],[Indem CP]]+TPersonnel[[#This Row],[COÛT Charges Patronales]] -> 0
A5: 8 | B5: Non | C5: GERARD | D5: Bruno | E5: VALENCE | F5: Chauffeur PL | G5: CDI | H5: Ouvrier | I5: 138M | J5: H | K5: 35128 | L5: 35128 | M5: 27781 | N5: 2635.89 | P5: 27.08 | Q5: =IF(UPPER(B5)="OUI",'📈 Dashboard'!$B$37,"") | R5: =MAX(N5,O5/12) -> 2635.89 | S5: 3664.22 | T5: =IF(L5="",(TODAY()-K5)/365.25,MAX((TODAY()-K5)/365.25,(TODAY()-L5)/365.25)) -> 30.031485 | U5: =IF(M5="","",(TODAY()-M5)/365.25) -> 50.146475 | V5: =N5*12 -> 31630.68 | W5: =IF(H5="Cadre",3,IF(H5="Haute maitrise",2,IF(OR(H5="Agent Maitrise",H5="Agent de maitrise"),IF(T5<2/12,0,IF(T5<2,1,2)),IF(OR(H5="Ouvrier"),IF(T5<6/12,1/4,IF(T5<2,1,2)),IF(OR(H5="Employe",H5="Employé"),IF(T5<1/12,0,IF(T5<2,1,2)),2))))) -> 2 | X5: =IF(Q5="",T5,(Q5-K5)/365.25) -> 30.031485 | AG5: =IF(TPersonnel[[#This Row],[Fonction à supprimer]]="NON",0,IF(TPersonnel[[#This Row],[Ancienneté (ans) à la date théorique de sortie]]<0.67,0,IF(TPersonnel[[#This Row],[Ancienneté (ans) à la date théorique de sortie]]<=10,TPersonnel[[#This Row],[Ancienneté (ans) à la date théorique de sortie]]*TPersonnel[[#This Row],[Salaire Brut de référence]]/4,(10*TPersonnel[[#This Row],[Salaire Brut de référence]]/4+(TPersonnel[[#This Row],[Ancienneté (ans) à la date théorique de sortie]]-10)*TPersonnel[[#This Row],[Salaire Brut de référence]]/3)))) -> 0 | AH5: =IF(UPPER(TPersonnel[[#This Row],[Fonction à supprimer]])="NON",0,IF(TPersonnel[[#This Row],[Ancienneté (ans) à la date théorique de sortie]]<1,0,IF(OR(TPersonnel[[#This Row],[Catégorie]]="Ouvrier",TPersonnel[[#This Row],[Catégorie]]="Employe",TPersonnel[[#This Row],[Catégorie]]="Employé"),IF(TPersonnel[[#This Row],[Ancienneté (ans) à la date théorique de sortie]]<3,TPersonnel[[#This Row],[Ancienneté (ans) à la date théorique de sortie]]*TPersonnel[[#This Row],[Salaire Brut de référence]]/10,TPersonnel[[#This Row],[Ancienneté (ans) à la date théorique de sortie]]*TPersonnel[[#This Row],[Salaire Brut de référence]]*2/10),IF(OR(TPersonnel[[#This Row],[Catégorie]]="Agent Maitrise",TPersonnel[[#This Row],[Catégorie]]="Agent de maitrise",TPersonnel[[#This Row],[Catégorie]]="Haute maitrise"),IF(TPersonnel[[#This Row],[Ancienneté (ans) à la date théorique de sortie]]<3,TPersonnel[[#This Row],[Ancienneté (ans) à la date théorique de sortie]]*TPersonnel[[#This Row],[Salaire Brut de référence]]/10,TPersonnel[[#This Row],[Ancienneté (ans) à la date théorique de sortie]]*TPersonnel[[#This Row],[Salaire Brut de référence]]*3/10),IF(TPersonnel[[#This Row],[Catégorie]]="Cadre",IF(TPersonnel[[#This Row],[Ancienneté (ans) à la date théorique de sortie]]<3,0,TPersonnel[[#This Row],[Ancienneté (ans) à la date théorique de sortie]]*TPersonnel[[#This Row],[Salaire Brut de référence]]*4/10),0))))) -> 0 | AI5: =IF(TPersonnel[[#This Row],[INDEM LÉGALE]]=0,"",IF(TPersonnel[[#This Row],[INDEM LÉGALE]]>TPersonnel[[#This Row],[INDEM CONV.]],"LEGAL","CONVENTIONNEL")) | AJ5: =MAX(TPersonnel[[#This Row],[INDEM LÉGALE]],TPersonnel[[#This Row],[INDEM CONV.]]) -> 0 | AK5: =TPersonnel[[#This Row],[INDEM RETENUE]]*'⚙️ Parametres'!$B$5 -> 0 | AL5: =TPersonnel[[#This Row],[INDEM RETENUE]]+TPersonnel[[#This Row],[Majoration PSE]] -> 0 | AM5: =IF(UPPER(TPersonnel[[#This Row],[Fonction à supprimer]])="NON",0,IF(OR(TPersonnel[[#This Row],[Catégorie]]="Cadre"),3,IF(TPersonnel[[#This Row],[Catégorie]]="Haute maitrise",2,IF(OR(TPersonnel[[#This Row],[Catégorie]]="Agent Maitrise",TPersonnel[[#This Row],[Catégorie]]="Agent de maitrise"),IF(TPersonnel[[#This Row],[Ancienneté (ans) à la date théorique de sortie]]<2/12,0,IF(TPersonnel[[#This Row],[Ancienneté (ans) à la date théorique de sortie]]<2,1,2)),IF(OR(TPersonnel[[#This Row],[Catégorie]]="Ouvrier",TPersonnel[[#This Row],[Catégorie]]="Employe",TPersonnel[[#This Row],[Catégorie]]="Employé"),IF(TPersonnel[[#This Row],[Ancienneté (ans) à la date théorique de sortie]]<6/12,IF(TPersonnel[[#This Row],[Catégorie]]="Ouvrier",1/4,IF(TPersonnel[[#This Row],[Ancienneté (ans) à la date théorique de sortie]]<1/12,0,1)),IF(TPersonnel[[#This Row],[Ancienneté (ans) à la date théorique de sortie]]<2,1,2)),2))))) -> 0 | AN5: =IF(UPPER(TPersonnel[[#This Row],[Fonction à supprimer]])="NON",0,TPersonnel[[#This Row],[Préavis Calc (mois)]]*TPersonnel[[#This Row],[Salaire Brut de référence]]) -> 0 | AO5: =IF(TPersonnel[[#This Row],[Fonction à supprimer]]="NON",0,TPersonnel[[#This Row],[Nb CP Acquis]]+TPersonnel[[#This Row],[Préavis Calc (mois)]]*2.08) -> 0 | AP5: =TPersonnel[[#This Row],[CP Calc (jrs)]]*TPersonnel[[#This Row],[Salaire Brut de référence]]/21.67 -> 0 | AQ5: =IF(UPPER(TPersonnel[[#This Row],[Fonction à supprimer]])="NON",0,_xlfn.LET(_xlpm.taux,IF(TPersonnel[[#This Row],[Catégorie]]="Ouvrier",'📈 Dashboard'!$B$32,IF(TPersonnel[[#This Row],[Catégorie]]="Cadre",'📈 Dashboard'!$B$34,'📈 Dashboard'!$B$33)),_xlpm.csp,UPPER(TPersonnel[[#This Row],[CSP (contrat de sécurisation professionnel)]])="OUI",IF(AND(_xlpm.csp,TPersonnel[[#This Row],[Ancienneté (ans) à la date théorique de sortie]]>=1),MIN(TPersonnel[[#This Row],[Préavis Calc (mois)]],3)*TPersonnel[[#This Row],[Salaire Brut de référence]]*(_xlpm.taux+'⚙️ Parametres'!$B$11)+IF(TPersonnel[[#This Row],[Préavis Calc (mois)]]>3,(TPersonnel[[#This Row],[Préavis Calc (mois)]]-3)*TPersonnel[[#This Row],[Salaire Brut de référence]]*_xlpm.taux,0)+TPersonnel[[#This Row],[Indem CP]]*_xlpm.taux,IF(_xlpm.csp,TPersonnel[[#This Row],[Indem CP]]*_xlpm.taux,(TPersonnel[[#This Row],[Indem Préavis Brut]]+TPersonnel[[#This Row],[Indem CP]])*_xlpm.taux)))) -> 0 | AR5: =TPersonnel[[#This Row],[TOTAL INDEM]]+TPersonnel[[#This Row],[Indem Préavis Brut]]+TPersonnel[[#This Row],[Indem CP]]+TPersonnel[[#This Row],[COÛT Charges Patronales]] -> 0
A6: 9 | B6: Non | C6: GERARD | D6: Pascal | E6: PUSIGNAN | F6: Chef de Quai Temp | G6: CDI | H6: Ouvrier | I6: 150M | J6: H | K6: 35541 | L6: 35541 | M6: 28477 | N6: 2687.99 | P6: 57.08 | Q6: =IF(UPPER(B6)="OUI",'📈 Dashboard'!$B$37,"") | R6: =MAX(N6,O6/12) -> 2687.99 | S6: 7424.6 | T6: =IF(L6="",(TODAY()-K6)/365.25,MAX((TODAY()-K6)/365.25,(TODAY()-L6)/365.25)) -> 28.900753 | U6: =IF(M6="","",(TODAY()-M6)/365.25) -> 48.240931 | V6: =N6*12 -> 32255.88 | W6: =IF(H6="Cadre",3,IF(H6="Haute maitrise",2,IF(OR(H6="Agent Maitrise",H6="Agent de maitrise"),IF(T6<2/12,0,IF(T6<2,1,2)),IF(OR(H6="Ouvrier"),IF(T6<6/12,1/4,IF(T6<2,1,2)),IF(OR(H6="Employe",H6="Employé"),IF(T6<1/12,0,IF(T6<2,1,2)),2))))) -> 2 | X6: =IF(Q6="",T6,(Q6-K6)/365.25) -> 28.900753 | AG6: =IF(TPersonnel[[#This Row],[Fonction à supprimer]]="NON",0,IF(TPersonnel[[#This Row],[Ancienneté (ans) à la date théorique de sortie]]<0.67,0,IF(TPersonnel[[#This Row],[Ancienneté (ans) à la date théorique de sortie]]<=10,TPersonnel[[#This Row],[Ancienneté (ans) à la date théorique de sortie]]*TPersonnel[[#This Row],[Salaire Brut de référence]]/4,(10*TPersonnel[[#This Row],[Salaire Brut de référence]]/4+(TPersonnel[[#This Row],[Ancienneté (ans) à la date théorique de sortie]]-10)*TPersonnel[[#This Row],[Salaire Brut de référence]]/3)))) -> 0 | AH6: =IF(UPPER(TPersonnel[[#This Row],[Fonction à supprimer]])="NON",0,IF(TPersonnel[[#This Row],[Ancienneté (ans) à la date théorique de sortie]]<1,0,IF(OR(TPersonnel[[#This Row],[Catégorie]]="Ouvrier",TPersonnel[[#This Row],[Catégorie]]="Employe",TPersonnel[[#This Row],[Catégorie]]="Employé"),IF(TPersonnel[[#This Row],[Ancienneté (ans) à la date théorique de sortie]]<3,TPersonnel[[#This Row],[Ancienneté (ans) à la date théorique de sortie]]*TPersonnel[[#This Row],[Salaire Brut de référence]]/10,TPersonnel[[#This Row],[Ancienneté (ans) à la date théorique de sortie]]*TPersonnel[[#This Row],[Salaire Brut de référence]]*2/10),IF(OR(TPersonnel[[#This Row],[Catégorie]]="Agent Maitrise",TPersonnel[[#This Row],[Catégorie]]="Agent de maitrise",TPersonnel[[#This Row],[Catégorie]]="Haute maitrise"),IF(TPersonnel[[#This Row],[Ancienneté (ans) à la date théorique de sortie]]<3,TPersonnel[[#This Row],[Ancienneté (ans) à la date théorique de sortie]]*TPersonnel[[#This Row],[Salaire Brut de référence]]/10,TPersonnel[[#This Row],[Ancienneté (ans) à la date théorique de sortie]]*TPersonnel[[#This Row],[Salaire Brut de référence]]*3/10),IF(TPersonnel[[#This Row],[Catégorie]]="Cadre",IF(TPersonnel[[#This Row],[Ancienneté (ans) à la date théorique de sortie]]<3,0,TPersonnel[[#This Row],[Ancienneté (ans) à la date théorique de sortie]]*TPersonnel[[#This Row],[Salaire Brut de référence]]*4/10),0))))) -> 0 | AI6: =IF(TPersonnel[[#This Row],[INDEM LÉGALE]]=0,"",IF(TPersonnel[[#This Row],[INDEM LÉGALE]]>TPersonnel[[#This Row],[INDEM CONV.]],"LEGAL","CONVENTIONNEL")) | AJ6: =MAX(TPersonnel[[#This Row],[INDEM LÉGALE]],TPersonnel[[#This Row],[INDEM CONV.]]) -> 0 | AK6: =TPersonnel[[#This Row],[INDEM RETENUE]]*'⚙️ Parametres'!$B$5 -> 0 | AL6: =TPersonnel[[#This Row],[INDEM RETENUE]]+TPersonnel[[#This Row],[Majoration PSE]] -> 0 | AM6: =IF(UPPER(TPersonnel[[#This Row],[Fonction à supprimer]])="NON",0,IF(OR(TPersonnel[[#This Row],[Catégorie]]="Cadre"),3,IF(TPersonnel[[#This Row],[Catégorie]]="Haute maitrise",2,IF(OR(TPersonnel[[#This Row],[Catégorie]]="Agent Maitrise",TPersonnel[[#This Row],[Catégorie]]="Agent de maitrise"),IF(TPersonnel[[#This Row],[Ancienneté (ans) à la date théorique de sortie]]<2/12,0,IF(TPersonnel[[#This Row],[Ancienneté (ans) à la date théorique de sortie]]<2,1,2)),IF(OR(TPersonnel[[#This Row],[Catégorie]]="Ouvrier",TPersonnel[[#This Row],[Catégorie]]="Employe",TPersonnel[[#This Row],[Catégorie]]="Employé"),IF(TPersonnel[[#This Row],[Ancienneté (ans) à la date théorique de sortie]]<6/12,IF(TPersonnel[[#This Row],[Catégorie]]="Ouvrier",1/4,IF(TPersonnel[[#This Row],[Ancienneté (ans) à la date théorique de sortie]]<1/12,0,1)),IF(TPersonnel[[#This Row],[Ancienneté (ans) à la date théorique de sortie]]<2,1,2)),2))))) -> 0 | AN6: =IF(UPPER(TPersonnel[[#This Row],[Fonction à supprimer]])="NON",0,TPersonnel[[#This Row],[Préavis Calc (mois)]]*TPersonnel[[#This Row],[Salaire Brut de référence]]) -> 0 | AO6: =IF(TPersonnel[[#This Row],[Fonction à supprimer]]="NON",0,TPersonnel[[#This Row],[Nb CP Acquis]]+TPersonnel[[#This Row],[Préavis Calc (mois)]]*2.08) -> 0 | AP6: =TPersonnel[[#This Row],[CP Calc (jrs)]]*TPersonnel[[#This Row],[Salaire Brut de référence]]/21.67 -> 0 | AQ6: =IF(UPPER(TPersonnel[[#This Row],[Fonction à supprimer]])="NON",0,_xlfn.LET(_xlpm.taux,IF(TPersonnel[[#This Row],[Catégorie]]="Ouvrier",'📈 Dashboard'!$B$32,IF(TPersonnel[[#This Row],[Catégorie]]="Cadre",'📈 Dashboard'!$B$34,'📈 Dashboard'!$B$33)),_xlpm.csp,UPPER(TPersonnel[[#This Row],[CSP (contrat de sécurisation professionnel)]])="OUI",IF(AND(_xlpm.csp,TPersonnel[[#This Row],[Ancienneté (ans) à la date théorique de sortie]]>=1),MIN(TPersonnel[[#This Row],[Préavis Calc (mois)]],3)*TPersonnel[[#This Row],[Salaire Brut de référence]]*(_xlpm.taux+'⚙️ Parametres'!$B$11)+IF(TPersonnel[[#This Row],[Préavis Calc (mois)]]>3,(TPersonnel[[#This Row],[Préavis Calc (mois)]]-3)*TPersonnel[[#This Row],[Salaire Brut de référence]]*_xlpm.taux,0)+TPersonnel[[#This Row],[Indem CP]]*_xlpm.taux,IF(_xlpm.csp,TPersonnel[[#This Row],[Indem CP]]*_xlpm.taux,(TPersonnel[[#This Row],[Indem Préavis Brut]]+TPersonnel[[#This Row],[Indem CP]])*_xlpm.taux)))) -> 0 | AR6: =TPersonnel[[#This Row],[TOTAL INDEM]]+TPersonnel[[#This Row],[Indem Préavis Brut]]+TPersonnel[[#This Row],[Indem CP]]+TPersonnel[[#This Row],[COÛT Charges Patronales]] -> 0
A7: 18 | B7: Non | C7: PAVARD | D7: Joel | E7: ROGNAC | F7: Chauffeur PL | G7: CDI | H7: Ouvrier | I7: 150M | J7: H | K7: 37734 | L7: 37734 | M7: 23348 | N7: 3098.37 | P7: 22.08 | Q7: =IF(UPPER(B7)="OUI",'📈 Dashboard'!$B$37,"") | R7: =MAX(N7,O7/12) -> 3098.37 | S7: 3362.77 | T7: =IF(L7="",(TODAY()-K7)/365.25,MAX((TODAY()-K7)/365.25,(TODAY()-L7)/365.25)) -> 22.896646 | U7: =IF(M7="","",(TODAY()-M7)/365.25) -> 62.283368 | V7: =N7*12 -> 37180.44 | W7: =IF(H7="Cadre",3,IF(H7="Haute maitrise",2,IF(OR(H7="Agent Maitrise",H7="Agent de maitrise"),IF(T7<2/12,0,IF(T7<2,1,2)),IF(OR(H7="Ouvrier"),IF(T7<6/12,1/4,IF(T7<2,1,2)),IF(OR(H7="Employe",H7="Employé"),IF(T7<1/12,0,IF(T7<2,1,2)),2))))) -> 2 | X7: =IF(Q7="",T7,(Q7-K7)/365.25) -> 22.896646 | AG7: =IF(TPersonnel[[#This Row],[Fonction à supprimer]]="NON",0,IF(TPersonnel[[#This Row],[Ancienneté (ans) à la date théorique de sortie]]<0.67,0,IF(TPersonnel[[#This Row],[Ancienneté (ans) à la date théorique de sortie]]<=10,TPersonnel[[#This Row],[Ancienneté (ans) à la date théorique de sortie]]*TPersonnel[[#This Row],[Salaire Brut de référence]]/4,(10*TPersonnel[[#This Row],[Salaire Brut de référence]]/4+(TPersonnel[[#This Row],[Ancienneté (ans) à la date théorique de sortie]]-10)*TPersonnel[[#This Row],[Salaire Brut de référence]]/3)))) -> 0 | AH7: =IF(UPPER(TPersonnel[[#This Row],[Fonction à supprimer]])="NON",0,IF(TPersonnel[[#This Row],[Ancienneté (ans) à la date théorique de sortie]]<1,0,IF(OR(TPersonnel[[#This Row],[Catégorie]]="Ouvrier",TPersonnel[[#This Row],[Catégorie]]="Employe",TPersonnel[[#This Row],[Catégorie]]="Employé"),IF(TPersonnel[[#This Row],[Ancienneté (ans) à la date théorique de sortie]]<3,TPersonnel[[#This Row],[Ancienneté (ans) à la date théorique de sortie]]*TPersonnel[[#This Row],[Salaire Brut de référence]]/10,TPersonnel[[#This Row],[Ancienneté (ans) à la date théorique de sortie]]*TPersonnel[[#This Row],[Salaire Brut de référence]]*2/10),IF(OR(TPersonnel[[#This Row],[Catégorie]]="Agent Maitrise",TPersonnel[[#This Row],[Catégorie]]="Agent de maitrise",TPersonnel[[#This Row],[Catégorie]]="Haute maitrise"),IF(TPersonnel[[#This Row],[Ancienneté (ans) à la date théorique de sortie]]<3,TPersonnel[[#This Row],[Ancienneté (ans) à la date théorique de sortie]]*TPersonnel[[#This Row],[Salaire Brut de référence]]/10,TPersonnel[[#This Row],[Ancienneté (ans) à la date théorique de sortie]]*TPersonnel[[#This Row],[Salaire Brut de référence]]*3/10),IF(TPersonnel[[#This Row],[Catégorie]]="Cadre",IF(TPersonnel[[#This Row],[Ancienneté (ans) à la date théorique de sortie]]<3,0,TPersonnel[[#This Row],[Ancienneté (ans) à la date théorique de sortie]]*TPersonnel[[#This Row],[Salaire Brut de référence]]*4/10),0))))) -> 0 | AI7: =IF(TPersonnel[[#This Row],[INDEM LÉGALE]]=0,"",IF(TPersonnel[[#This Row],[INDEM LÉGALE]]>TPersonnel[[#This Row],[INDEM CONV.]],"LEGAL","CONVENTIONNEL")) | AJ7: =MAX(TPersonnel[[#This Row],[INDEM LÉGALE]],TPersonnel[[#This Row],[INDEM CONV.]]) -> 0 | AK7: =TPersonnel[[#This Row],[INDEM RETENUE]]*'⚙️ Parametres'!$B$5 -> 0 | AL7: =TPersonnel[[#This Row],[INDEM RETENUE]]+TPersonnel[[#This Row],[Majoration PSE]] -> 0 | AM7: =IF(UPPER(TPersonnel[[#This Row],[Fonction à supprimer]])="NON",0,IF(OR(TPersonnel[[#This Row],[Catégorie]]="Cadre"),3,IF(TPersonnel[[#This Row],[Catégorie]]="Haute maitrise",2,IF(OR(TPersonnel[[#This Row],[Catégorie]]="Agent Maitrise",TPersonnel[[#This Row],[Catégorie]]="Agent de maitrise"),IF(TPersonnel[[#This Row],[Ancienneté (ans) à la date théorique de sortie]]<2/12,0,IF(TPersonnel[[#This Row],[Ancienneté (ans) à la date théorique de sortie]]<2,1,2)),IF(OR(TPersonnel[[#This Row],[Catégorie]]="Ouvrier",TPersonnel[[#This Row],[Catégorie]]="Employe",TPersonnel[[#This Row],[Catégorie]]="Employé"),IF(TPersonnel[[#This Row],[Ancienneté (ans) à la date théorique de sortie]]<6/12,IF(TPersonnel[[#This Row],[Catégorie]]="Ouvrier",1/4,IF(TPersonnel[[#This Row],[Ancienneté (ans) à la date théorique de sortie]]<1/12,0,1)),IF(TPersonnel[[#This Row],[Ancienneté (ans) à la date théorique de sortie]]<2,1,2)),2))))) -> 0 | AN7: =IF(UPPER(TPersonnel[[#This Row],[Fonction à supprimer]])="NON",0,TPersonnel[[#This Row],[Préavis Calc (mois)]]*TPersonnel[[#This Row],[Salaire Brut de référence]]) -> 0 | AO7: =IF(TPersonnel[[#This Row],[Fonction à supprimer]]="NON",0,TPersonnel[[#This Row],[Nb CP Acquis]]+TPersonnel[[#This Row],[Préavis Calc (mois)]]*2.08) -> 0 | AP7: =TPersonnel[[#This Row],[CP Calc (jrs)]]*TPersonnel[[#This Row],[Salaire Brut de référence]]/21.67 -> 0 | AQ7: =IF(UPPER(TPersonnel[[#This Row],[Fonction à supprimer]])="NON",0,_xlfn.LET(_xlpm.taux,IF(TPersonnel[[#This Row],[Catégorie]]="Ouvrier",'📈 Dashboard'!$B$32,IF(TPersonnel[[#This Row],[Catégorie]]="Cadre",'📈 Dashboard'!$B$34,'📈 Dashboard'!$B$33)),_xlpm.csp,UPPER(TPersonnel[[#This Row],[CSP (contrat de sécurisation professionnel)]])="OUI",IF(AND(_xlpm.csp,TPersonnel[[#This Row],[Ancienneté (ans) à la date théorique de sortie]]>=1),MIN(TPersonnel[[#This Row],[Préavis Calc (mois)]],3)*TPersonnel[[#This Row],[Salaire Brut de référence]]*(_xlpm.taux+'⚙️ Parametres'!$B$11)+IF(TPersonnel[[#This Row],[Préavis Calc (mois)]]>3,(TPersonnel[[#This Row],[Préavis Calc (mois)]]-3)*TPersonnel[[#This Row],[Salaire Brut de référence]]*_xlpm.taux,0)+TPersonnel[[#This Row],[Indem CP]]*_xlpm.taux,IF(_xlpm.csp,TPersonnel[[#This Row],[Indem CP]]*_xlpm.taux,(TPersonnel[[#This Row],[Indem Préavis Brut]]+TPersonnel[[#This Row],[Indem CP]])*_xlpm.taux)))) -> 0 | AR7: =TPersonnel[[#This Row],[TOTAL INDEM]]+TPersonnel[[#This Row],[Indem Préavis Brut]]+TPersonnel[[#This Row],[Indem CP]]+TPersonnel[[#This Row],[COÛT Charges Patronales]] -> 0
A8: 19 | B8: Non | C8: MOKRANI | D8: Eric | E8: ROGNAC | F8: Chauffeur PL | G8: CDI | H8: Ouvrier | I8: 150M | J8: H | K8: 36026 | L8: 36026 | M8: 26580 | N8: 3238.84 | P8: 24.58 | Q8: =IF(UPPER(B8)="OUI",'📈 Dashboard'!$B$37,"") | R8: =MAX(N8,O8/12) -> 3238.84 | S8: 3815.22 | T8: =IF(L8="",(TODAY()-K8)/365.25,MAX((TODAY()-K8)/365.25,(TODAY()-L8)/365.25)) -> 27.572895 | U8: =IF(M8="","",(TODAY()-M8)/365.25) -> 53.434634 | V8: =N8*12 -> 38866.08 | W8: =IF(H8="Cadre",3,IF(H8="Haute maitrise",2,IF(OR(H8="Agent Maitrise",H8="Agent de maitrise"),IF(T8<2/12,0,IF(T8<2,1,2)),IF(OR(H8="Ouvrier"),IF(T8<6/12,1/4,IF(T8<2,1,2)),IF(OR(H8="Employe",H8="Employé"),IF(T8<1/12,0,IF(T8<2,1,2)),2))))) -> 2 | X8: =IF(Q8="",T8,(Q8-K8)/365.25) -> 27.572895 | AG8: =IF(TPersonnel[[#This Row],[Fonction à supprimer]]="NON",0,IF(TPersonnel[[#This Row],[Ancienneté (ans) à la date théorique de sortie]]<0.67,0,IF(TPersonnel[[#This Row],[Ancienneté (ans) à la date théorique de sortie]]<=10,TPersonnel[[#This Row],[Ancienneté (ans) à la date théorique de sortie]]*TPersonnel[[#This Row],[Salaire Brut de référence]]/4,(10*TPersonnel[[#This Row],[Salaire Brut de référence]]/4+(TPersonnel[[#This Row],[Ancienneté (ans) à la date théorique de sortie]]-10)*TPersonnel[[#This Row],[Salaire Brut de référence]]/3)))) -> 0 | AH8: =IF(UPPER(TPersonnel[[#This Row],[Fonction à supprimer]])="NON",0,IF(TPersonnel[[#This Row],[Ancienneté (ans) à la date théorique de sortie]]<1,0,IF(OR(TPersonnel[[#This Row],[Catégorie]]="Ouvrier",TPersonnel[[#This Row],[Catégorie]]="Employe",TPersonnel[[#This Row],[Catégorie]]="Employé"),IF(TPersonnel[[#This Row],[Ancienneté (ans) à la date théorique de sortie]]<3,TPersonnel[[#This Row],[Ancienneté (ans) à la date théorique de sortie]]*TPersonnel[[#This Row],[Salaire Brut de référence]]/10,TPersonnel[[#This Row],[Ancienneté (ans) à la date théorique de sortie]]*TPersonnel[[#This Row],[Salaire Brut de référence]]*2/10),IF(OR(TPersonnel[[#This Row],[Catégorie]]="Agent Maitrise",TPersonnel[[#This Row],[Catégorie]]="Agent de maitrise",TPersonnel[[#This Row],[Catégorie]]="Haute maitrise"),IF(TPersonnel[[#This Row],[Ancienneté (ans) à la date théorique de sortie]]<3,TPersonnel[[#This Row],[Ancienneté (ans) à la date théorique de sortie]]*TPersonnel[[#This Row],[Salaire Brut de référence]]/10,TPersonnel[[#This Row],[Ancienneté (ans) à la date théorique de sortie]]*TPersonnel[[#This Row],[Salaire Brut de référence]]*3/10),IF(TPersonnel[[#This Row],[Catégorie]]="Cadre",IF(TPersonnel[[#This Row],[Ancienneté (ans) à la date théorique de sortie]]<3,0,TPersonnel[[#This Row],[Ancienneté (ans) à la date théorique de sortie]]*TPersonnel[[#This Row],[Salaire Brut de référence]]*4/10),0))))) -> 0 | AI8: =IF(TPersonnel[[#This Row],[INDEM LÉGALE]]=0,"",IF(TPersonnel[[#This Row],[INDEM LÉGALE]]>TPersonnel[[#This Row],[INDEM CONV.]],"LEGAL","CONVENTIONNEL")) | AJ8: =MAX(TPersonnel[[#This Row],[INDEM LÉGALE]],TPersonnel[[#This Row],[INDEM CONV.]]) -> 0 | AK8: =TPersonnel[[#This Row],[INDEM RETENUE]]*'⚙️ Parametres'!$B$5 -> 0 | AL8: =TPersonnel[[#This Row],[INDEM RETENUE]]+TPersonnel[[#This Row],[Majoration PSE]] -> 0 | AM8: =IF(UPPER(TPersonnel[[#This Row],[Fonction à supprimer]])="NON",0,IF(OR(TPersonnel[[#This Row],[Catégorie]]="Cadre"),3,IF(TPersonnel[[#This Row],[Catégorie]]="Haute maitrise",2,IF(OR(TPersonnel[[#This Row],[Catégorie]]="Agent Maitrise",TPersonnel[[#This Row],[Catégorie]]="Agent de maitrise"),IF(TPersonnel[[#This Row],[Ancienneté (ans) à la date théorique de sortie]]<2/12,0,IF(TPersonnel[[#This Row],[Ancienneté (ans) à la date théorique de sortie]]<2,1,2)),IF(OR(TPersonnel[[#This Row],[Catégorie]]="Ouvrier",TPersonnel[[#This Row],[Catégorie]]="Employe",TPersonnel[[#This Row],[Catégorie]]="Employé"),IF(TPersonnel[[#This Row],[Ancienneté (ans) à la date théorique de sortie]]<6/12,IF(TPersonnel[[#This Row],[Catégorie]]="Ouvrier",1/4,IF(TPersonnel[[#This Row],[Ancienneté (ans) à la date théorique de sortie]]<1/12,0,1)),IF(TPersonnel[[#This Row],[Ancienneté (ans) à la date théorique de sortie]]<2,1,2)),2))))) -> 0 | AN8: =IF(UPPER(TPersonnel[[#This Row],[Fonction à supprimer]])="NON",0,TPersonnel[[#This Row],[Préavis Calc (mois)]]*TPersonnel[[#This Row],[Salaire Brut de référence]]) -> 0 | AO8: =IF(TPersonnel[[#This Row],[Fonction à supprimer]]="NON",0,TPersonnel[[#This Row],[Nb CP Acquis]]+TPersonnel[[#This Row],[Préavis Calc (mois)]]*2.08) -> 0 | AP8: =TPersonnel[[#This Row],[CP Calc (jrs)]]*TPersonnel[[#This Row],[Salaire Brut de référence]]/21.67 -> 0 | AQ8: =IF(UPPER(TPersonnel[[#This Row],[Fonction à supprimer]])="NON",0,_xlfn.LET(_xlpm.taux,IF(TPersonnel[[#This Row],[Catégorie]]="Ouvrier",'📈 Dashboard'!$B$32,IF(TPersonnel[[#This Row],[Catégorie]]="Cadre",'📈 Dashboard'!$B$34,'📈 Dashboard'!$B$33)),_xlpm.csp,UPPER(TPersonnel[[#This Row],[CSP (contrat de sécurisation professionnel)]])="OUI",IF(AND(_xlpm.csp,TPersonnel[[#This Row],[Ancienneté (ans) à la date théorique de sortie]]>=1),MIN(TPersonnel[[#This Row],[Préavis Calc (mois)]],3)*TPersonnel[[#This Row],[Salaire Brut de référence]]*(_xlpm.taux+'⚙️ Parametres'!$B$11)+IF(TPersonnel[[#This Row],[Préavis Calc (mois)]]>3,(TPersonnel[[#This Row],[Préavis Calc (mois)]]-3)*TPersonnel[[#This Row],[Salaire Brut de référence]]*_xlpm.taux,0)+TPersonnel[[#This Row],[Indem CP]]*_xlpm.taux,IF(_xlpm.csp,TPersonnel[[#This Row],[Indem CP]]*_xlpm.taux,(TPersonnel[[#This Row],[Indem Préavis Brut]]+TPersonnel[[#This Row],[Indem CP]])*_xlpm.taux)))) -> 0 | AR8: =TPersonnel[[#This Row],[TOTAL INDEM]]+TPersonnel[[#This Row],[Indem Préavis Brut]]+TPersonnel[[#This Row],[Indem CP]]+TPersonnel[[#This Row],[COÛT Charges Patronales]] -> 0
A9: 28 | B9: Non | C9: BENSID AHMED | D9: Ali | E9: VALENCE | F9: Chauffeur PL | G9: CDI | H9: Ouvrier | I9: 150M | J9: H | K9: 39301 | L9: 39301 | M9: 29066 | N9: 3110.06 | P9: 17.58 | Q9: =IF(UPPER(B9)="OUI",'📈 Dashboard'!$B$37,"") | R9: =MAX(N9,O9/12) -> 3110.06 | S9: 2616.89 | T9: =IF(L9="",(TODAY()-K9)/365.25,MAX((TODAY()-K9)/365.25,(TODAY()-L9)/365.25)) -> 18.606434 | U9: =IF(M9="","",(TODAY()-M9)/365.25) -> 46.628337 | V9: =N9*12 -> 37320.72 | W9: =IF(H9="Cadre",3,IF(H9="Haute maitrise",2,IF(OR(H9="Agent Maitrise",H9="Agent de maitrise"),IF(T9<2/12,0,IF(T9<2,1,2)),IF(OR(H9="Ouvrier"),IF(T9<6/12,1/4,IF(T9<2,1,2)),IF(OR(H9="Employe",H9="Employé"),IF(T9<1/12,0,IF(T9<2,1,2)),2))))) -> 2 | X9: =IF(Q9="",T9,(Q9-K9)/365.25) -> 18.606434 | AG9: =IF(TPersonnel[[#This Row],[Fonction à supprimer]]="NON",0,IF(TPersonnel[[#This Row],[Ancienneté (ans) à la date théorique de sortie]]<0.67,0,IF(TPersonnel[[#This Row],[Ancienneté (ans) à la date théorique de sortie]]<=10,TPersonnel[[#This Row],[Ancienneté (ans) à la date théorique de sortie]]*TPersonnel[[#This Row],[Salaire Brut de référence]]/4,(10*TPersonnel[[#This Row],[Salaire Brut de référence]]/4+(TPersonnel[[#This Row],[Ancienneté (ans) à la date théorique de sortie]]-10)*TPersonnel[[#This Row],[Salaire Brut de référence]]/3)))) -> 0 | AH9: =IF(UPPER(TPersonnel[[#This Row],[Fonction à supprimer]])="NON",0,IF(TPersonnel[[#This Row],[Ancienneté (ans) à la date théorique de sortie]]<1,0,IF(OR(TPersonnel[[#This Row],[Catégorie]]="Ouvrier",TPersonnel[[#This Row],[Catégorie]]="Employe",TPersonnel[[#This Row],[Catégorie]]="Employé"),IF(TPersonnel[[#This Row],[Ancienneté (ans) à la date théorique de sortie]]<3,TPersonnel[[#This Row],[Ancienneté (ans) à la date théorique de sortie]]*TPersonnel[[#This Row],[Salaire Brut de référence]]/10,TPersonnel[[#This Row],[Ancienneté (ans) à la date théorique de sortie]]*TPersonnel[[#This Row],[Salaire Brut de référence]]*2/10),IF(OR(TPersonnel[[#This Row],[Catégorie]]="Agent Maitrise",TPersonnel[[#This Row],[Catégorie]]="Agent de maitrise",TPersonnel[[#This Row],[Catégorie]]="Haute maitrise"),IF(TPersonnel[[#This Row],[Ancienneté (ans) à la date théorique de sortie]]<3,TPersonnel[[#This Row],[Ancienneté (ans) à la date théorique de sortie]]*TPersonnel[[#This Row],[Salaire Brut de référence]]/10,TPersonnel[[#This Row],[Ancienneté (ans) à la date théorique de sortie]]*TPersonnel[[#This Row],[Salaire Brut de référence]]*3/10),IF(TPersonnel[[#This Row],[Catégorie]]="Cadre",IF(TPersonnel[[#This Row],[Ancienneté (ans) à la date théorique de sortie]]<3,0,TPersonnel[[#This Row],[Ancienneté (ans) à la date théorique de sortie]]*TPersonnel[[#This Row],[Salaire Brut de référence]]*4/10),0))))) -> 0 | AI9: =IF(TPersonnel[[#This Row],[INDEM LÉGALE]]=0,"",IF(TPersonnel[[#This Row],[INDEM LÉGALE]]>TPersonnel[[#This Row],[INDEM CONV.]],"LEGAL","CONVENTIONNEL")) | AJ9: =MAX(TPersonnel[[#This Row],[INDEM LÉGALE]],TPersonnel[[#This Row],[INDEM CONV.]]) -> 0 | AK9: =TPersonnel[[#This Row],[INDEM RETENUE]]*'⚙️ Parametres'!$B$5 -> 0 | AL9: =TPersonnel[[#This Row],[INDEM RETENUE]]+TPersonnel[[#This Row],[Majoration PSE]] -> 0 | AM9: =IF(UPPER(TPersonnel[[#This Row],[Fonction à supprimer]])="NON",0,IF(OR(TPersonnel[[#This Row],[Catégorie]]="Cadre"),3,IF(TPersonnel[[#This Row],[Catégorie]]="Haute maitrise",2,IF(OR(TPersonnel[[#This Row],[Catégorie]]="Agent Maitrise",TPersonnel[[#This Row],[Catégorie]]="Agent de maitrise"),IF(TPersonnel[[#This Row],[Ancienneté (ans) à la date théorique de sortie]]<2/12,0,IF(TPersonnel[[#This Row],[Ancienneté (ans) à la date théorique de sortie]]<2,1,2)),IF(OR(TPersonnel[[#This Row],[Catégorie]]="Ouvrier",TPersonnel[[#This Row],[Catégorie]]="Employe",TPersonnel[[#This Row],[Catégorie]]="Employé"),IF(TPersonnel[[#This Row],[Ancienneté (ans) à la date théorique de sortie]]<6/12,IF(TPersonnel[[#This Row],[Catégorie]]="Ouvrier",1/4,IF(TPersonnel[[#This Row],[Ancienneté (ans) à la date théorique de sortie]]<1/12,0,1)),IF(TPersonnel[[#This Row],[Ancienneté (ans) à la date théorique de sortie]]<2,1,2)),2))))) -> 0 | AN9: =IF(UPPER(TPersonnel[[#This Row],[Fonction à supprimer]])="NON",0,TPersonnel[[#This Row],[Préavis Calc (mois)]]*TPersonnel[[#This Row],[Salaire Brut de référence]]) -> 0 | AO9: =IF(TPersonnel[[#This Row],[Fonction à supprimer]]="NON",0,TPersonnel[[#This Row],[Nb CP Acquis]]+TPersonnel[[#This Row],[Préavis Calc (mois)]]*2.08) -> 0 | AP9: =TPersonnel[[#This Row],[CP Calc (jrs)]]*TPersonnel[[#This Row],[Salaire Brut de référence]]/21.67 -> 0 | AQ9: =IF(UPPER(TPersonnel[[#This Row],[Fonction à supprimer]])="NON",0,_xlfn.LET(_xlpm.taux,IF(TPersonnel[[#This Row],[Catégorie]]="Ouvrier",'📈 Dashboard'!$B$32,IF(TPersonnel[[#This Row],[Catégorie]]="Cadre",'📈 Dashboard'!$B$34,'📈 Dashboard'!$B$33)),_xlpm.csp,UPPER(TPersonnel[[#This Row],[CSP (contrat de sécurisation professionnel)]])="OUI",IF(AND(_xlpm.csp,TPersonnel[[#This Row],[Ancienneté (ans) à la date théorique de sortie]]>=1),MIN(TPersonnel[[#This Row],[Préavis Calc (mois)]],3)*TPersonnel[[#This Row],[Salaire Brut de référence]]*(_xlpm.taux+'⚙️ Parametres'!$B$11)+IF(TPersonnel[[#This Row],[Préavis Calc (mois)]]>3,(TPersonnel[[#This Row],[Préavis Calc (mois)]]-3)*TPersonnel[[#This Row],[Salaire Brut de référence]]*_xlpm.taux,0)+TPersonnel[[#This Row],[Indem CP]]*_xlpm.taux,IF(_xlpm.csp,TPersonnel[[#This Row],[Indem CP]]*_xlpm.taux,(TPersonnel[[#This Row],[Indem Préavis Brut]]+TPersonnel[[#This Row],[Indem CP]])*_xlpm.taux)))) -> 0 | AR9: =TPersonnel[[#This Row],[TOTAL INDEM]]+TPersonnel[[#This Row],[Indem Préavis Brut]]+TPersonnel[[#This Row],[Indem CP]]+TPersonnel[[#This Row],[COÛT Charges Patronales]] -> 0
A10: 31 | B10: Non | C10: BOULAKHSOUMI | D10: Mostafa | E10: VALENCE | F10: Resp Exploitation | G10: CDI | H10: Agent de maîtrise | I10: 185 | J10: H | K10: 42107 | L10: 42107 | M10: 24222 | N10: 3250 | P10: 51.58 | Q10: =IF(UPPER(B10)="OUI",'📈 Dashboard'!$B$37,"") | R10: =MAX(N10,O10/12) -> 3250 | S10: 7735.79 | T10: =IF(L10="",(TODAY()-K10)/365.25,MAX((TODAY()-K10)/365.25,(TODAY()-L10)/365.25)) -> 10.924025 | U10: =IF(M10="","",(TODAY()-M10)/365.25) -> 59.890486 | V10: =N10*12 -> 39000 | W10: =IF(H10="Cadre",3,IF(H10="Haute maitrise",2,IF(OR(H10="Agent Maitrise",H10="Agent de maitrise"),IF(T10<2/12,0,IF(T10<2,1,2)),IF(OR(H10="Ouvrier"),IF(T10<6/12,1/4,IF(T10<2,1,2)),IF(OR(H10="Employe",H10="Employé"),IF(T10<1/12,0,IF(T10<2,1,2)),2))))) -> 2 | X10: =IF(Q10="",T10,(Q10-K10)/365.25) -> 10.924025 | AG10: =IF(TPersonnel[[#This Row],[Fonction à supprimer]]="NON",0,IF(TPersonnel[[#This Row],[Ancienneté (ans) à la date théorique de sortie]]<0.67,0,IF(TPersonnel[[#This Row],[Ancienneté (ans) à la date théorique de sortie]]<=10,TPersonnel[[#This Row],[Ancienneté (ans) à la date théorique de sortie]]*TPersonnel[[#This Row],[Salaire Brut de référence]]/4,(10*TPersonnel[[#This Row],[Salaire Brut de référence]]/4+(TPersonnel[[#This Row],[Ancienneté (ans) à la date théorique de sortie]]-10)*TPersonnel[[#This Row],[Salaire Brut de référence]]/3)))) -> 0 | AH10: =IF(UPPER(TPersonnel[[#This Row],[Fonction à supprimer]])="NON",0,IF(TPersonnel[[#This Row],[Ancienneté (ans) à la date théorique de sortie]]<1,0,IF(OR(TPersonnel[[#This Row],[Catégorie]]="Ouvrier",TPersonnel[[#This Row],[Catégorie]]="Employe",TPersonnel[[#This Row],[Catégorie]]="Employé"),IF(TPersonnel[[#This Row],[Ancienneté (ans) à la date théorique de sortie]]<3,TPersonnel[[#This Row],[Ancienneté (ans) à la date théorique de sortie]]*TPersonnel[[#This Row],[Salaire Brut de référence]]/10,TPersonnel[[#This Row],[Ancienneté (ans) à la date théorique de sortie]]*TPersonnel[[#This Row],[Salaire Brut de référence]]*2/10),IF(OR(TPersonnel[[#This Row],[Catégorie]]="Agent Maitrise",TPersonnel[[#This Row],[Catégorie]]="Agent de maitrise",TPersonnel[[#This Row],[Catégorie]]="Haute maitrise"),IF(TPersonnel[[#This Row],[Ancienneté (ans) à la date théorique de sortie]]<3,TPersonnel[[#This Row],[Ancienneté (ans) à la date théorique de sortie]]*TPersonnel[[#This Row],[Salaire Brut de référence]]/10,TPersonnel[[#This Row],[Ancienneté (ans) à la date théorique de sortie]]*TPersonnel[[#This Row],[Salaire Brut de référence]]*3/10),IF(TPersonnel[[#This Row],[Catégorie]]="Cadre",IF(TPersonnel[[#This Row],[Ancienneté (ans) à la date théorique de sortie]]<3,0,TPersonnel[[#This Row],[Ancienneté (ans) à la date théorique de sortie]]*TPersonnel[[#This Row],[Salaire Brut de référence]]*4/10),0))))) -> 0 | AI10: =IF(TPersonnel[[#This Row],[INDEM LÉGALE]]=0,"",IF(TPersonnel[[#This Row],[INDEM LÉGALE]]>TPersonnel[[#This Row],[INDEM CONV.]],"LEGAL","CONVENTIONNEL")) | AJ10: =MAX(TPersonnel[[#This Row],[INDEM LÉGALE]],TPersonnel[[#This Row],[INDEM CONV.]]) -> 0 | AK10: =TPersonnel[[#This Row],[INDEM RETENUE]]*'⚙️ Parametres'!$B$5 -> 0 | AL10: =TPersonnel[[#This Row],[INDEM RETENUE]]+TPersonnel[[#This Row],[Majoration PSE]] -> 0 | AM10: =IF(UPPER(TPersonnel[[#This Row],[Fonction à supprimer]])="NON",0,IF(OR(TPersonnel[[#This Row],[Catégorie]]="Cadre"),3,IF(TPersonnel[[#This Row],[Catégorie]]="Haute maitrise",2,IF(OR(TPersonnel[[#This Row],[Catégorie]]="Agent Maitrise",TPersonnel[[#This Row],[Catégorie]]="Agent de maitrise"),IF(TPersonnel[[#This Row],[Ancienneté (ans) à la date théorique de sortie]]<2/12,0,IF(TPersonnel[[#This Row],[Ancienneté (ans) à la date théorique de sortie]]<2,1,2)),IF(OR(TPersonnel[[#This Row],[Catégorie]]="Ouvrier",TPersonnel[[#This Row],[Catégorie]]="Employe",TPersonnel[[#This Row],[Catégorie]]="Employé"),IF(TPersonnel[[#This Row],[Ancienneté (ans) à la date théorique de sortie]]<6/12,IF(TPersonnel[[#This Row],[Catégorie]]="Ouvrier",1/4,IF(TPersonnel[[#This Row],[Ancienneté (ans) à la date théorique de sortie]]<1/12,0,1)),IF(TPersonnel[[#This Row],[Ancienneté (ans) à la date théorique de sortie]]<2,1,2)),2))))) -> 0 | AN10: =IF(UPPER(TPersonnel[[#This Row],[Fonction à supprimer]])="NON",0,TPersonnel[[#This Row],[Préavis Calc (mois)]]*TPersonnel[[#This Row],[Salaire Brut de référence]]) -> 0 | AO10: =IF(TPersonnel[[#This Row],[Fonction à supprimer]]="NON",0,TPersonnel[[#This Row],[Nb CP Acquis]]+TPersonnel[[#This Row],[Préavis Calc (mois)]]*2.08) -> 0 | AP10: =TPersonnel[[#This Row],[CP Calc (jrs)]]*TPersonnel[[#This Row],[Salaire Brut de référence]]/21.67 -> 0 | AQ10: =IF(UPPER(TPersonnel[[#This Row],[Fonction à supprimer]])="NON",0,_xlfn.LET(_xlpm.taux,IF(TPersonnel[[#This Row],[Catégorie]]="Ouvrier",'📈 Dashboard'!$B$32,IF(TPersonnel[[#This Row],[Catégorie]]="Cadre",'📈 Dashboard'!$B$34,'📈 Dashboard'!$B$33)),_xlpm.csp,UPPER(TPersonnel[[#This Row],[CSP (contrat de sécurisation professionnel)]])="OUI",IF(AND(_xlpm.csp,TPersonnel[[#This Row],[Ancienneté (ans) à la date théorique de sortie]]>=1),MIN(TPersonnel[[#This Row],[Préavis Calc (mois)]],3)*TPersonnel[[#This Row],[Salaire Brut de référence]]*(_xlpm.taux+'⚙️ Parametres'!$B$11)+IF(TPersonnel[[#This Row],[Préavis Calc (mois)]]>3,(TPersonnel[[#This Row],[Préavis Calc (mois)]]-3)*TPersonnel[[#This Row],[Salaire Brut de référence]]*_xlpm.taux,0)+TPersonnel[[#This Row],[Indem CP]]*_xlpm.taux,IF(_xlpm.csp,TPersonnel[[#This Row],[Indem CP]]*_xlpm.taux,(TPersonnel[[#This Row],[Indem Préavis Brut]]+TPersonnel[[#This Row],[Indem CP]])*_xlpm.taux)))) -> 0 | AR10: =TPersonnel[[#This Row],[TOTAL INDEM]]+TPersonnel[[#This Row],[Indem Préavis Brut]]+TPersonnel[[#This Row],[Indem CP]]+TPersonnel[[#This Row],[COÛT Charges Patronales]] -> 0
A11: 33 | B11: Non | C11: HAOUARI | D11: Khaled | E11: VALENCE | F11: Chauffeur PL | G11: CDI | H11: Ouvrier | I11: 150M | J11: H | K11: 39182 | L11: 39182 | M11: 24037 | N11: 2827.92 | P11: 13.58 | Q11: =IF(UPPER(B11)="OUI",'📈 Dashboard'!$B$37,"") | R11: =MAX(N11,O11/12) -> 2827.92 | S11: 1852.93 | T11: =IF(L11="",(TODAY()-K11)/365.25,MAX((TODAY()-K11)/365.25,(TODAY()-L11)/365.25)) -> 18.932238 | U11: =IF(M11="","",(TODAY()-M11)/365.25) -> 60.396988 | V11: =N11*12 -> 33935.04 | W11: =IF(H11="Cadre",3,IF(H11="Haute maitrise",2,IF(OR(H11="Agent Maitrise",H11="Agent de maitrise"),IF(T11<2/12,0,IF(T11<2,1,2)),IF(OR(H11="Ouvrier"),IF(T11<6/12,1/4,IF(T11<2,1,2)),IF(OR(H11="Employe",H11="Employé"),IF(T11<1/12,0,IF(T11<2,1,2)),2))))) -> 2 | X11: =IF(Q11="",T11,(Q11-K11)/365.25) -> 18.932238 | AG11: =IF(TPersonnel[[#This Row],[Fonction à supprimer]]="NON",0,IF(TPersonnel[[#This Row],[Ancienneté (ans) à la date théorique de sortie]]<0.67,0,IF(TPersonnel[[#This Row],[Ancienneté (ans) à la date théorique de sortie]]<=10,TPersonnel[[#This Row],[Ancienneté (ans) à la date théorique de sortie]]*TPersonnel[[#This Row],[Salaire Brut de référence]]/4,(10*TPersonnel[[#This Row],[Salaire Brut de référence]]/4+(TPersonnel[[#This Row],[Ancienneté (ans) à la date théorique de sortie]]-10)*TPersonnel[[#This Row],[Salaire Brut de référence]]/3)))) -> 0 | AH11: =IF(UPPER(TPersonnel[[#This Row],[Fonction à supprimer]])="NON",0,IF(TPersonnel[[#This Row],[Ancienneté (ans) à la date théorique de sortie]]<1,0,IF(OR(TPersonnel[[#This Row],[Catégorie]]="Ouvrier",TPersonnel[[#This Row],[Catégorie]]="Employe",TPersonnel[[#This Row],[Catégorie]]="Employé"),IF(TPersonnel[[#This Row],[Ancienneté (ans) à la date théorique de sortie]]<3,TPersonnel[[#This Row],[Ancienneté (ans) à la date théorique de sortie]]*TPersonnel[[#This Row],[Salaire Brut de référence]]/10,TPersonnel[[#This Row],[Ancienneté (ans) à la date théorique de sortie]]*TPersonnel[[#This Row],[Salaire Brut de référence]]*2/10),IF(OR(TPersonnel[[#This Row],[Catégorie]]="Agent Maitrise",TPersonnel[[#This Row],[Catégorie]]="Agent de maitrise",TPersonnel[[#This Row],[Catégorie]]="Haute maitrise"),IF(TPersonnel[[#This Row],[Ancienneté (ans) à la date théorique de sortie]]<3,TPersonnel[[#This Row],[Ancienneté (ans) à la date théorique de sortie]]*TPersonnel[[#This Row],[Salaire Brut de référence]]/10,TPersonnel[[#This Row],[Ancienneté (ans) à la date théorique de sortie]]*TPersonnel[[#This Row],[Salaire Brut de référence]]*3/10),IF(TPersonnel[[#This Row],[Catégorie]]="Cadre",IF(TPersonnel[[#This Row],[Ancienneté (ans) à la date théorique de sortie]]<3,0,TPersonnel[[#This Row],[Ancienneté (ans) à la date théorique de sortie]]*TPersonnel[[#This Row],[Salaire Brut de référence]]*4/10),0))))) -> 0 | AI11: =IF(TPersonnel[[#This Row],[INDEM LÉGALE]]=0,"",IF(TPersonnel[[#This Row],[INDEM LÉGALE]]>TPersonnel[[#This Row],[INDEM CONV.]],"LEGAL","CONVENTIONNEL")) | AJ11: =MAX(TPersonnel[[#This Row],[INDEM LÉGALE]],TPersonnel[[#This Row],[INDEM CONV.]]) -> 0 | AK11: =TPersonnel[[#This Row],[INDEM RETENUE]]*'⚙️ Parametres'!$B$5 -> 0 | AL11: =TPersonnel[[#This Row],[INDEM RETENUE]]+TPersonnel[[#This Row],[Majoration PSE]] -> 0 | AM11: =IF(UPPER(TPersonnel[[#This Row],[Fonction à supprimer]])="NON",0,IF(OR(TPersonnel[[#This Row],[Catégorie]]="Cadre"),3,IF(TPersonnel[[#This Row],[Catégorie]]="Haute maitrise",2,IF(OR(TPersonnel[[#This Row],[Catégorie]]="Agent Maitrise",TPersonnel[[#This Row],[Catégorie]]="Agent de maitrise"),IF(TPersonnel[[#This Row],[Ancienneté (ans) à la date théorique de sortie]]<2/12,0,IF(TPersonnel[[#This Row],[Ancienneté (ans) à la date théorique de sortie]]<2,1,2)),IF(OR(TPersonnel[[#This Row],[Catégorie]]="Ouvrier",TPersonnel[[#This Row],[Catégorie]]="Employe",TPersonnel[[#This Row],[Catégorie]]="Employé"),IF(TPersonnel[[#This Row],[Ancienneté (ans) à la date théorique de sortie]]<6/12,IF(TPersonnel[[#This Row],[Catégorie]]="Ouvrier",1/4,IF(TPersonnel[[#This Row],[Ancienneté (ans) à la date théorique de sortie]]<1/12,0,1)),IF(TPersonnel[[#This Row],[Ancienneté (ans) à la date théorique de sortie]]<2,1,2)),2))))) -> 0 | AN11: =IF(UPPER(TPersonnel[[#This Row],[Fonction à supprimer]])="NON",0,TPersonnel[[#This Row],[Préavis Calc (mois)]]*TPersonnel[[#This Row],[Salaire Brut de référence]]) -> 0 | AO11: =IF(TPersonnel[[#This Row],[Fonction à supprimer]]="NON",0,TPersonnel[[#This Row],[Nb CP Acquis]]+TPersonnel[[#This Row],[Préavis Calc (mois)]]*2.08) -> 0 | AP11: =TPersonnel[[#This Row],[CP Calc (jrs)]]*TPersonnel[[#This Row],[Salaire Brut de référence]]/21.67 -> 0 | AQ11: =IF(UPPER(TPersonnel[[#This Row],[Fonction à supprimer]])="NON",0,_xlfn.LET(_xlpm.taux,IF(TPersonnel[[#This Row],[Catégorie]]="Ouvrier",'📈 Dashboard'!$B$32,IF(TPersonnel[[#This Row],[Catégorie]]="Cadre",'📈 Dashboard'!$B$34,'📈 Dashboard'!$B$33)),_xlpm.csp,UPPER(TPersonnel[[#This Row],[CSP (contrat de sécurisation professionnel)]])="OUI",IF(AND(_xlpm.csp,TPersonnel[[#This Row],[Ancienneté (ans) à la date théorique de sortie]]>=1),MIN(TPersonnel[[#This Row],[Préavis Calc (mois)]],3)*TPersonnel[[#This Row],[Salaire Brut de référence]]*(_xlpm.taux+'⚙️ Parametres'!$B$11)+IF(TPersonnel[[#This Row],[Préavis Calc (mois)]]>3,(TPersonnel[[#This Row],[Préavis Calc (mois)]]-3)*TPersonnel[[#This Row],[Salaire Brut de référence]]*_xlpm.taux,0)+TPersonnel[[#This Row],[Indem CP]]*_xlpm.taux,IF(_xlpm.csp,TPersonnel[[#This Row],[Indem CP]]*_xlpm.taux,(TPersonnel[[#This Row],[Indem Préavis Brut]]+TPersonnel[[#This Row],[Indem CP]])*_xlpm.taux)))) -> 0 | AR11: =TPersonnel[[#This Row],[TOTAL INDEM]]+TPersonnel[[#This Row],[Indem Préavis Brut]]+TPersonnel[[#This Row],[Indem CP]]+TPersonnel[[#This Row],[COÛT Charges Patronales]] -> 0
A12: 35 | B12: Non | C12: GUENIFI | D12: Abdelkader | E12: VALENCE | F12: Chauffeur SPL | G12: CDI | H12: Ouvrier | I12: 138M | J12: H | K12: 41673 | L12: 41673 | M12: 31288 | N12: 2842.93 | P12: 18.53 | Q12: =IF(UPPER(B12)="OUI",'📈 Dashboard'!$B$37,"") | R12: =MAX(N12,O12/12) -> 2842.93 | S12: 2773.39 | T12: =IF(L12="",(TODAY()-K12)/365.25,MAX((TODAY()-K12)/365.25,(TODAY()-L12)/365.25)) -> 12.112252 | U12: =IF(M12="","",(TODAY()-M12)/365.25) -> 40.544832 | V12: =N12*12 -> 34115.16 | W12: =IF(H12="Cadre",3,IF(H12="Haute maitrise",2,IF(OR(H12="Agent Maitrise",H12="Agent de maitrise"),IF(T12<2/12,0,IF(T12<2,1,2)),IF(OR(H12="Ouvrier"),IF(T12<6/12,1/4,IF(T12<2,1,2)),IF(OR(H12="Employe",H12="Employé"),IF(T12<1/12,0,IF(T12<2,1,2)),2))))) -> 2 | X12: =IF(Q12="",T12,(Q12-K12)/365.25) -> 12.112252 | AG12: =IF(TPersonnel[[#This Row],[Fonction à supprimer]]="NON",0,IF(TPersonnel[[#This Row],[Ancienneté (ans) à la date théorique de sortie]]<0.67,0,IF(TPersonnel[[#This Row],[Ancienneté (ans) à la date théorique de sortie]]<=10,TPersonnel[[#This Row],[Ancienneté (ans) à la date théorique de sortie]]*TPersonnel[[#This Row],[Salaire Brut de référence]]/4,(10*TPersonnel[[#This Row],[Salaire Brut de référence]]/4+(TPersonnel[[#This Row],[Ancienneté (ans) à la date théorique de sortie]]-10)*TPersonnel[[#This Row],[Salaire Brut de référence]]/3)))) -> 0 | AH12: =IF(UPPER(TPersonnel[[#This Row],[Fonction à supprimer]])="NON",0,IF(TPersonnel[[#This Row],[Ancienneté (ans) à la date théorique de sortie]]<1,0,IF(OR(TPersonnel[[#This Row],[Catégorie]]="Ouvrier",TPersonnel[[#This Row],[Catégorie]]="Employe",TPersonnel[[#This Row],[Catégorie]]="Employé"),IF(TPersonnel[[#This Row],[Ancienneté (ans) à la date théorique de sortie]]<3,TPersonnel[[#This Row],[Ancienneté (ans) à la date théorique de sortie]]*TPersonnel[[#This Row],[Salaire Brut de référence]]/10,TPersonnel[[#This Row],[Ancienneté (ans) à la date théorique de sortie]]*TPersonnel[[#This Row],[Salaire Brut de référence]]*2/10),IF(OR(TPersonnel[[#This Row],[Catégorie]]="Agent Maitrise",TPersonnel[[#This Row],[Catégorie]]="Agent de maitrise",TPersonnel[[#This Row],[Catégorie]]="Haute maitrise"),IF(TPersonnel[[#This Row],[Ancienneté (ans) à la date théorique de sortie]]<3,TPersonnel[[#This Row],[Ancienneté (ans) à la date théorique de sortie]]*TPersonnel[[#This Row],[Salaire Brut de référence]]/10,TPersonnel[[#This Row],[Ancienneté (ans) à la date théorique de sortie]]*TPersonnel[[#This Row],[Salaire Brut de référence]]*3/10),IF(TPersonnel[[#This Row],[Catégorie]]="Cadre",IF(TPersonnel[[#This Row],[Ancienneté (ans) à la date théorique de sortie]]<3,0,TPersonnel[[#This Row],[Ancienneté (ans) à la date théorique de sortie]]*TPersonnel[[#This Row],[Salaire Brut de référence]]*4/10),0))))) -> 0 | AI12: =IF(TPersonnel[[#This Row],[INDEM LÉGALE]]=0,"",IF(TPersonnel[[#This Row],[INDEM LÉGALE]]>TPersonnel[[#This Row],[INDEM CONV.]],"LEGAL","CONVENTIONNEL")) | AJ12: =MAX(TPersonnel[[#This Row],[INDEM LÉGALE]],TPersonnel[[#This Row],[INDEM CONV.]]) -> 0 | AK12: =TPersonnel[[#This Row],[INDEM RETENUE]]*'⚙️ Parametres'!$B$5 -> 0 | AL12: =TPersonnel[[#This Row],[INDEM RETENUE]]+TPersonnel[[#This Row],[Majoration PSE]] -> 0 | AM12: =IF(UPPER(TPersonnel[[#This Row],[Fonction à supprimer]])="NON",0,IF(OR(TPersonnel[[#This Row],[Catégorie]]="Cadre"),3,IF(TPersonnel[[#This Row],[Catégorie]]="Haute maitrise",2,IF(OR(TPersonnel[[#This Row],[Catégorie]]="Agent Maitrise",TPersonnel[[#This Row],[Catégorie]]="Agent de maitrise"),IF(TPersonnel[[#This Row],[Ancienneté (ans) à la date théorique de sortie]]<2/12,0,IF(TPersonnel[[#This Row],[Ancienneté (ans) à la date théorique de sortie]]<2,1,2)),IF(OR(TPersonnel[[#This Row],[Catégorie]]="Ouvrier",TPersonnel[[#This Row],[Catégorie]]="Employe",TPersonnel[[#This Row],[Catégorie]]="Employé"),IF(TPersonnel[[#This Row],[Ancienneté (ans) à la date théorique de sortie]]<6/12,IF(TPersonnel[[#This Row],[Catégorie]]="Ouvrier",1/4,IF(TPersonnel[[#This Row],[Ancienneté (ans) à la date théorique de sortie]]<1/12,0,1)),IF(TPersonnel[[#This Row],[Ancienneté (ans) à la date théorique de sortie]]<2,1,2)),2))))) -> 0 | AN12: =IF(UPPER(TPersonnel[[#This Row],[Fonction à supprimer]])="NON",0,TPersonnel[[#This Row],[Préavis Calc (mois)]]*TPersonnel[[#This Row],[Salaire Brut de référence]]) -> 0 | AO12: =IF(TPersonnel[[#This Row],[Fonction à supprimer]]="NON",0,TPersonnel[[#This Row],[Nb CP Acquis]]+TPersonnel[[#This Row],[Préavis Calc (mois)]]*2.08) -> 0 | AP12: =TPersonnel[[#This Row],[CP Calc (jrs)]]*TPersonnel[[#This Row],[Salaire Brut de référence]]/21.67 -> 0 | AQ12: =IF(UPPER(TPersonnel[[#This Row],[Fonction à supprimer]])="NON",0,_xlfn.LET(_xlpm.taux,IF(TPersonnel[[#This Row],[Catégorie]]="Ouvrier",'📈 Dashboard'!$B$32,IF(TPersonnel[[#This Row],[Catégorie]]="Cadre",'📈 Dashboard'!$B$34,'📈 Dashboard'!$B$33)),_xlpm.csp,UPPER(TPersonnel[[#This Row],[CSP (contrat de sécurisation professionnel)]])="OUI",IF(AND(_xlpm.csp,TPersonnel[[#This Row],[Ancienneté (ans) à la date théorique de sortie]]>=1),MIN(TPersonnel[[#This Row],[Préavis Calc (mois)]],3)*TPersonnel[[#This Row],[Salaire Brut de référence]]*(_xlpm.taux+'⚙️ Parametres'!$B$11)+IF(TPersonnel[[#This Row],[Préavis Calc (mois)]]>3,(TPersonnel[[#This Row],[Préavis Calc (mois)]]-3)*TPersonnel[[#This Row],[Salaire Brut de référence]]*_xlpm.taux,0)+TPersonnel[[#This Row],[Indem CP]]*_xlpm.taux,IF(_xlpm.csp,TPersonnel[[#This Row],[Indem CP]]*_xlpm.taux,(TPersonnel[[#This Row],[Indem Préavis Brut]]+TPersonnel[[#This Row],[Indem CP]])*_xlpm.taux)))) -> 0 | AR12: =TPersonnel[[#This Row],[TOTAL INDEM]]+TPersonnel[[#This Row],[Indem Préavis Brut]]+TPersonnel[[#This Row],[Indem CP]]+TPersonnel[[#This Row],[COÛT Charges Patronales]] -> 0
A13: 40 | B13: Non | C13: TESTARD | D13: Jean-Claude | E13: VALENCE | F13: Chauffeur PL | G13: CDI | H13: Ouvrier | I13: 150M | J13: H | K13: 41334 | L13: 33512 | M13: 24052 | N13: 2974.39 | P13: 25.58 | Q13: =IF(UPPER(B13)="OUI",'📈 Dashboard'!$B$37,"") | R13: =MAX(N13,O13/12) -> 2974.39 | S13: 3650.41 | T13: =IF(L13="",(TODAY()-K13)/365.25,MAX((TODAY()-K13)/365.25,(TODAY()-L13)/365.25)) -> 34.455852 | U13: =IF(M13="","",(TODAY()-M13)/365.25) -> 60.355921 | V13: =N13*12 -> 35692.68 | W13: =IF(H13="Cadre",3,IF(H13="Haute maitrise",2,IF(OR(H13="Agent Maitrise",H13="Agent de maitrise"),IF(T13<2/12,0,IF(T13<2,1,2)),IF(OR(H13="Ouvrier"),IF(T13<6/12,1/4,IF(T13<2,1,2)),IF(OR(H13="Employe",H13="Employé"),IF(T13<1/12,0,IF(T13<2,1,2)),2))))) -> 2 | X13: =IF(Q13="",T13,(Q13-K13)/365.25) -> 34.455852 | AG13: =IF(TPersonnel[[#This Row],[Fonction à supprimer]]="NON",0,IF(TPersonnel[[#This Row],[Ancienneté (ans) à la date théorique de sortie]]<0.67,0,IF(TPersonnel[[#This Row],[Ancienneté (ans) à la date théorique de sortie]]<=10,TPersonnel[[#This Row],[Ancienneté (ans) à la date théorique de sortie]]*TPersonnel[[#This Row],[Salaire Brut de référence]]/4,(10*TPersonnel[[#This Row],[Salaire Brut de référence]]/4+(TPersonnel[[#This Row],[Ancienneté (ans) à la date théorique de sortie]]-10)*TPersonnel[[#This Row],[Salaire Brut de référence]]/3)))) -> 0 | AH13: =IF(UPPER(TPersonnel[[#This Row],[Fonction à supprimer]])="NON",0,IF(TPersonnel[[#This Row],[Ancienneté (ans) à la date théorique de sortie]]<1,0,IF(OR(TPersonnel[[#This Row],[Catégorie]]="Ouvrier",TPersonnel[[#This Row],[Catégorie]]="Employe",TPersonnel[[#This Row],[Catégorie]]="Employé"),IF(TPersonnel[[#This Row],[Ancienneté (ans) à la date théorique de sortie]]<3,TPersonnel[[#This Row],[Ancienneté (ans) à la date théorique de sortie]]*TPersonnel[[#This Row],[Salaire Brut de référence]]/10,TPersonnel[[#This Row],[Ancienneté (ans) à la date théorique de sortie]]*TPersonnel[[#This Row],[Salaire Brut de référence]]*2/10),IF(OR(TPersonnel[[#This Row],[Catégorie]]="Agent Maitrise",TPersonnel[[#This Row],[Catégorie]]="Agent de maitrise",TPersonnel[[#This Row],[Catégorie]]="Haute maitrise"),IF(TPersonnel[[#This Row],[Ancienneté (ans) à la date théorique de sortie]]<3,TPersonnel[[#This Row],[Ancienneté (ans) à la date théorique de sortie]]*TPersonnel[[#This Row],[Salaire Brut de référence]]/10,TPersonnel[[#This Row],[Ancienneté (ans) à la date théorique de sortie]]*TPersonnel[[#This Row],[Salaire Brut de référence]]*3/10),IF(TPersonnel[[#This Row],[Catégorie]]="Cadre",IF(TPersonnel[[#This Row],[Ancienneté (ans) à la date théorique de sortie]]<3,0,TPersonnel[[#This Row],[Ancienneté (ans) à la date théorique de sortie]]*TPersonnel[[#This Row],[Salaire Brut de référence]]*4/10),0))))) -> 0 | AI13: =IF(TPersonnel[[#This Row],[INDEM LÉGALE]]=0,"",IF(TPersonnel[[#This Row],[INDEM LÉGALE]]>TPersonnel[[#This Row],[INDEM CONV.]],"LEGAL","CONVENTIONNEL")) | AJ13: =MAX(TPersonnel[[#This Row],[INDEM LÉGALE]],TPersonnel[[#This Row],[INDEM CONV.]]) -> 0 | AK13: =TPersonnel[[#This Row],[INDEM RETENUE]]*'⚙️ Parametres'!$B$5 -> 0 | AL13: =TPersonnel[[#This Row],[INDEM RETENUE]]+TPersonnel[[#This Row],[Majoration PSE]] -> 0 | AM13: =IF(UPPER(TPersonnel[[#This Row],[Fonction à supprimer]])="NON",0,IF(OR(TPersonnel[[#This Row],[Catégorie]]="Cadre"),3,IF(TPersonnel[[#This Row],[Catégorie]]="Haute maitrise",2,IF(OR(TPersonnel[[#This Row],[Catégorie]]="Agent Maitrise",TPersonnel[[#This Row],[Catégorie]]="Agent de maitrise"),IF(TPersonnel[[#This Row],[Ancienneté (ans) à la date théorique de sortie]]<2/12,0,IF(TPersonnel[[#This Row],[Ancienneté (ans) à la date théorique de sortie]]<2,1,2)),IF(OR(TPersonnel[[#This Row],[Catégorie]]="Ouvrier",TPersonnel[[#This Row],[Catégorie]]="Employe",TPersonnel[[#This Row],[Catégorie]]="Employé"),IF(TPersonnel[[#This Row],[Ancienneté (ans) à la date théorique de sortie]]<6/12,IF(TPersonnel[[#This Row],[Catégorie]]="Ouvrier",1/4,IF(TPersonnel[[#This Row],[Ancienneté (ans) à la date théorique de sortie]]<1/12,0,1)),IF(TPersonnel[[#This Row],[Ancienneté (ans) à la date théorique de sortie]]<2,1,2)),2))))) -> 0 | AN13: =IF(UPPER(TPersonnel[[#This Row],[Fonction à supprimer]])="NON",0,TPersonnel[[#This Row],[Préavis Calc (mois)]]*TPersonnel[[#This Row],[Salaire Brut de référence]]) -> 0 | AO13: =IF(TPersonnel[[#This Row],[Fonction à supprimer]]="NON",0,TPersonnel[[#This Row],[Nb CP Acquis]]+TPersonnel[[#This Row],[Préavis Calc (mois)]]*2.08) -> 0 | AP13: =TPersonnel[[#This Row],[CP Calc (jrs)]]*TPersonnel[[#This Row],[Salaire Brut de référence]]/21.67 -> 0 | AQ13: =IF(UPPER(TPersonnel[[#This Row],[Fonction à supprimer]])="NON",0,_xlfn.LET(_xlpm.taux,IF(TPersonnel[[#This Row],[Catégorie]]="Ouvrier",'📈 Dashboard'!$B$32,IF(TPersonnel[[#This Row],[Catégorie]]="Cadre",'📈 Dashboard'!$B$34,'📈 Dashboard'!$B$33)),_xlpm.csp,UPPER(TPersonnel[[#This Row],[CSP (contrat de sécurisation professionnel)]])="OUI",IF(AND(_xlpm.csp,TPersonnel[[#This Row],[Ancienneté (ans) à la date théorique de sortie]]>=1),MIN(TPersonnel[[#This Row],[Préavis Calc (mois)]],3)*TPersonnel[[#This Row],[Salaire Brut de référence]]*(_xlpm.taux+'⚙️ Parametres'!$B$11)+IF(TPersonnel[[#This Row],[Préavis Calc (mois)]]>3,(TPersonnel[[#This Row],[Préavis Calc (mois)]]-3)*TPersonnel[[#This Row],[Salaire Brut de référence]]*_xlpm.taux,0)+TPersonnel[[#This Row],[Indem CP]]*_xlpm.taux,IF(_xlpm.csp,TPersonnel[[#This Row],[Indem CP]]*_xlpm.taux,(TPersonnel[[#This Row],[Indem Préavis Brut]]+TPersonnel[[#This Row],[Indem CP]])*_xlpm.taux)))) -> 0 | AR13: =TPersonnel[[#This Row],[TOTAL INDEM]]+TPersonnel[[#This Row],[Indem Préavis Brut]]+TPersonnel[[#This Row],[Indem CP]]+TPersonnel[[#This Row],[COÛT Charges Patronales]] -> 0
A14: 68 | B14: Non | C14: MERLE | D14: Xavier | E14: PUSIGNAN | F14: Chauffeur SPL | G14: CDI | H14: Ouvrier | I14: 150M | J14: H | K14: 43556 | L14: 43556 | M14: 29105 | N14: 2239.63 | P14: 32.22 | Q14: =IF(UPPER(B14)="OUI",'📈 Dashboard'!$B$37,"") | R14: =MAX(N14,O14/12) -> 2239.63 | S14: 4116.06 | T14: =IF(L14="",(TODAY()-K14)/365.25,MAX((TODAY()-K14)/365.25,(TODAY()-L14)/365.25)) -> 6.9568789 | U14: =IF(M14="","",(TODAY()-M14)/365.25) -> 46.521561 | V14: =N14*12 -> 26875.56 | W14: =IF(H14="Cadre",3,IF(H14="Haute maitrise",2,IF(OR(H14="Agent Maitrise",H14="Agent de maitrise"),IF(T14<2/12,0,IF(T14<2,1,2)),IF(OR(H14="Ouvrier"),IF(T14<6/12,1/4,IF(T14<2,1,2)),IF(OR(H14="Employe",H14="Employé"),IF(T14<1/12,0,IF(T14<2,1,2)),2))))) -> 2 | X14: =IF(Q14="",T14,(Q14-K14)/365.25) -> 6.9568789 | AG14: =IF(TPersonnel[[#This Row],[Fonction à supprimer]]="NON",0,IF(TPersonnel[[#This Row],[Ancienneté (ans) à la date théorique de sortie]]<0.67,0,IF(TPersonnel[[#This Row],[Ancienneté (ans) à la date théorique de sortie]]<=10,TPersonnel[[#This Row],[Ancienneté (ans) à la date théorique de sortie]]*TPersonnel[[#This Row],[Salaire Brut de référence]]/4,(10*TPersonnel[[#This Row],[Salaire Brut de référence]]/4+(TPersonnel[[#This Row],[Ancienneté (ans) à la date théorique de sortie]]-10)*TPersonnel[[#This Row],[Salaire Brut de référence]]/3)))) -> 0 | AH14: =IF(UPPER(TPersonnel[[#This Row],[Fonction à supprimer]])="NON",0,IF(TPersonnel[[#This Row],[Ancienneté (ans) à la date théorique de sortie]]<1,0,IF(OR(TPersonnel[[#This Row],[Catégorie]]="Ouvrier",TPersonnel[[#This Row],[Catégorie]]="Employe",TPersonnel[[#This Row],[Catégorie]]="Employé"),IF(TPersonnel[[#This Row],[Ancienneté (ans) à la date théorique de sortie]]<3,TPersonnel[[#This Row],[Ancienneté (ans) à la date théorique de sortie]]*TPersonnel[[#This Row],[Salaire Brut de référence]]/10,TPersonnel[[#This Row],[Ancienneté (ans) à la date théorique de sortie]]*TPersonnel[[#This Row],[Salaire Brut de référence]]*2/10),IF(OR(TPersonnel[[#This Row],[Catégorie]]="Agent Maitrise",TPersonnel[[#This Row],[Catégorie]]="Agent de maitrise",TPersonnel[[#This Row],[Catégorie]]="Haute maitrise"),IF(TPersonnel[[#This Row],[Ancienneté (ans) à la date théorique de sortie]]<3,TPersonnel[[#This Row],[Ancienneté (ans) à la date théorique de sortie]]*TPersonnel[[#This Row],[Salaire Brut de référence]]/10,TPersonnel[[#This Row],[Ancienneté (ans) à la date théorique de sortie]]*TPersonnel[[#This Row],[Salaire Brut de référence]]*3/10),IF(TPersonnel[[#This Row],[Catégorie]]="Cadre",IF(TPersonnel[[#This Row],[Ancienneté (ans) à la date théorique de sortie]]<3,0,TPersonnel[[#This Row],[Ancienneté (ans) à la date théorique de sortie]]*TPersonnel[[#This Row],[Salaire Brut de référence]]*4/10),0))))) -> 0 | AI14: =IF(TPersonnel[[#This Row],[INDEM LÉGALE]]=0,"",IF(TPersonnel[[#This Row],[INDEM LÉGALE]]>TPersonnel[[#This Row],[INDEM CONV.]],"LEGAL","CONVENTIONNEL")) | AJ14: =MAX(TPersonnel[[#This Row],[INDEM LÉGALE]],TPersonnel[[#This Row],[INDEM CONV.]]) -> 0 | AK14: =TPersonnel[[#This Row],[INDEM RETENUE]]*'⚙️ Parametres'!$B$5 -> 0 | AL14: =TPersonnel[[#This Row],[INDEM RETENUE]]+TPersonnel[[#This Row],[Majoration PSE]] -> 0 | AM14: =IF(UPPER(TPersonnel[[#This Row],[Fonction à supprimer]])="NON",0,IF(OR(TPersonnel[[#This Row],[Catégorie]]="Cadre"),3,IF(TPersonnel[[#This Row],[Catégorie]]="Haute maitrise",2,IF(OR(TPersonnel[[#This Row],[Catégorie]]="Agent Maitrise",TPersonnel[[#This Row],[Catégorie]]="Agent de maitrise"),IF(TPersonnel[[#This Row],[Ancienneté (ans) à la date théorique de sortie]]<2/12,0,IF(TPersonnel[[#This Row],[Ancienneté (ans) à la date théorique de sortie]]<2,1,2)),IF(OR(TPersonnel[[#This Row],[Catégorie]]="Ouvrier",TPersonnel[[#This Row],[Catégorie]]="Employe",TPersonnel[[#This Row],[Catégorie]]="Employé"),IF(TPersonnel[[#This Row],[Ancienneté (ans) à la date théorique de sortie]]<6/12,IF(TPersonnel[[#This Row],[Catégorie]]="Ouvrier",1/4,IF(TPersonnel[[#This Row],[Ancienneté (ans) à la date théorique de sortie]]<1/12,0,1)),IF(TPersonnel[[#This Row],[Ancienneté (ans) à la date théorique de sortie]]<2,1,2)),2))))) -> 0 | AN14: =IF(UPPER(TPersonnel[[#This Row],[Fonction à supprimer]])="NON",0,TPersonnel[[#This Row],[Préavis Calc (mois)]]*TPersonnel[[#This Row],[Salaire Brut de référence]]) -> 0 | AO14: =IF(TPersonnel[[#This Row],[Fonction à supprimer]]="NON",0,TPersonnel[[#This Row],[Nb CP Acquis]]+TPersonnel[[#This Row],[Préavis Calc (mois)]]*2.08) -> 0 | AP14: =TPersonnel[[#This Row],[CP Calc (jrs)]]*TPersonnel[[#This Row],[Salaire Brut de référence]]/21.67 -> 0 | AQ14: =IF(UPPER(TPersonnel[[#This Row],[Fonction à supprimer]])="NON",0,_xlfn.LET(_xlpm.taux,IF(TPersonnel[[#This Row],[Catégorie]]="Ouvrier",'📈 Dashboard'!$B$32,IF(TPersonnel[[#This Row],[Catégorie]]="Cadre",'📈 Dashboard'!$B$34,'📈 Dashboard'!$B$33)),_xlpm.csp,UPPER(TPersonnel[[#This Row],[CSP (contrat de sécurisation professionnel)]])="OUI",IF(AND(_xlpm.csp,TPersonnel[[#This Row],[Ancienneté (ans) à la date théorique de sortie]]>=1),MIN(TPersonnel[[#This Row],[Préavis Calc (mois)]],3)*TPersonnel[[#This Row],[Salaire Brut de référence]]*(_xlpm.taux+'⚙️ Parametres'!$B$11)+IF(TPersonnel[[#This Row],[Préavis Calc (mois)]]>3,(TPersonnel[[#This Row],[Préavis Calc (mois)]]-3)*TPersonnel[[#This Row],[Salaire Brut de référence]]*_xlpm.taux,0)+TPersonnel[[#This Row],[Indem CP]]*_xlpm.taux,IF(_xlpm.csp,TPersonnel[[#This Row],[Indem CP]]*_xlpm.taux,(TPersonnel[[#This Row],[Indem Préavis Brut]]+TPersonnel[[#This Row],[Indem CP]])*_xlpm.taux)))) -> 0 | AR14: =TPersonnel[[#This Row],[TOTAL INDEM]]+TPersonnel[[#This Row],[Indem Préavis Brut]]+TPersonnel[[#This Row],[Indem CP]]+TPersonnel[[#This Row],[COÛT Charges Patronales]] -> 0
A15: 69 | B15: Non | C15: FERDJI | D15: Abdenour | E15: VALENCE | F15: Chauffeur SPL | G15: CDI | H15: Ouvrier | I15: 138M | J15: H | K15: 43591 | L15: 43591 | M15: 31417 | N15: 2720.81 | P15: 48.45 | Q15: =IF(UPPER(B15)="OUI",'📈 Dashboard'!$B$37,"") | R15: =MAX(N15,O15/12) -> 2720.81 | S15: 6156.32 | T15: =IF(L15="",(TODAY()-K15)/365.25,MAX((TODAY()-K15)/365.25,(TODAY()-L15)/365.25)) -> 6.8610541 | U15: =IF(M15="","",(TODAY()-M15)/365.25) -> 40.19165 | V15: =N15*12 -> 32649.72 | W15: =IF(H15="Cadre",3,IF(H15="Haute maitrise",2,IF(OR(H15="Agent Maitrise",H15="Agent de maitrise"),IF(T15<2/12,0,IF(T15<2,1,2)),IF(OR(H15="Ouvrier"),IF(T15<6/12,1/4,IF(T15<2,1,2)),IF(OR(H15="Employe",H15="Employé"),IF(T15<1/12,0,IF(T15<2,1,2)),2))))) -> 2 | X15: =IF(Q15="",T15,(Q15-K15)/365.25) -> 6.8610541 | AG15: =IF(TPersonnel[[#This Row],[Fonction à supprimer]]="NON",0,IF(TPersonnel[[#This Row],[Ancienneté (ans) à la date théorique de sortie]]<0.67,0,IF(TPersonnel[[#This Row],[Ancienneté (ans) à la date théorique de sortie]]<=10,TPersonnel[[#This Row],[Ancienneté (ans) à la date théorique de sortie]]*TPersonnel[[#This Row],[Salaire Brut de référence]]/4,(10*TPersonnel[[#This Row],[Salaire Brut de référence]]/4+(TPersonnel[[#This Row],[Ancienneté (ans) à la date théorique de sortie]]-10)*TPersonnel[[#This Row],[Salaire Brut de référence]]/3)))) -> 0 | AH15: =IF(UPPER(TPersonnel[[#This Row],[Fonction à supprimer]])="NON",0,IF(TPersonnel[[#This Row],[Ancienneté (ans) à la date théorique de sortie]]<1,0,IF(OR(TPersonnel[[#This Row],[Catégorie]]="Ouvrier",TPersonnel[[#This Row],[Catégorie]]="Employe",TPersonnel[[#This Row],[Catégorie]]="Employé"),IF(TPersonnel[[#This Row],[Ancienneté (ans) à la date théorique de sortie]]<3,TPersonnel[[#This Row],[Ancienneté (ans) à la date théorique de sortie]]*TPersonnel[[#This Row],[Salaire Brut de référence]]/10,TPersonnel[[#This Row],[Ancienneté (ans) à la date théorique de sortie]]*TPersonnel[[#This Row],[Salaire Brut de référence]]*2/10),IF(OR(TPersonnel[[#This Row],[Catégorie]]="Agent Maitrise",TPersonnel[[#This Row],[Catégorie]]="Agent de maitrise",TPersonnel[[#This Row],[Catégorie]]="Haute maitrise"),IF(TPersonnel[[#This Row],[Ancienneté (ans) à la date théorique de sortie]]<3,TPersonnel[[#This Row],[Ancienneté (ans) à la date théorique de sortie]]*TPersonnel[[#This Row],[Salaire Brut de référence]]/10,TPersonnel[[#This Row],[Ancienneté (ans) à la date théorique de sortie]]*TPersonnel[[#This Row],[Salaire Brut de référence]]*3/10),IF(TPersonnel[[#This Row],[Catégorie]]="Cadre",IF(TPersonnel[[#This Row],[Ancienneté (ans) à la date théorique de sortie]]<3,0,TPersonnel[[#This Row],[Ancienneté (ans) à la date théorique de sortie]]*TPersonnel[[#This Row],[Salaire Brut de référence]]*4/10),0))))) -> 0 | AI15: =IF(TPersonnel[[#This Row],[INDEM LÉGALE]]=0,"",IF(TPersonnel[[#This Row],[INDEM LÉGALE]]>TPersonnel[[#This Row],[INDEM CONV.]],"LEGAL","CONVENTIONNEL")) | AJ15: =MAX(TPersonnel[[#This Row],[INDEM LÉGALE]],TPersonnel[[#This Row],[INDEM CONV.]]) -> 0 | AK15: =TPersonnel[[#This Row],[INDEM RETENUE]]*'⚙️ Parametres'!$B$5 -> 0 | AL15: =TPersonnel[[#This Row],[INDEM RETENUE]]+TPersonnel[[#This Row],[Majoration PSE]] -> 0 | AM15: =IF(UPPER(TPersonnel[[#This Row],[Fonction à supprimer]])="NON",0,IF(OR(TPersonnel[[#This Row],[Catégorie]]="Cadre"),3,IF(TPersonnel[[#This Row],[Catégorie]]="Haute maitrise",2,IF(OR(TPersonnel[[#This Row],[Catégorie]]="Agent Maitrise",TPersonnel[[#This Row],[Catégorie]]="Agent de maitrise"),IF(TPersonnel[[#This Row],[Ancienneté (ans) à la date théorique de sortie]]<2/12,0,IF(TPersonnel[[#This Row],[Ancienneté (ans) à la date théorique de sortie]]<2,1,2)),IF(OR(TPersonnel[[#This Row],[Catégorie]]="Ouvrier",TPersonnel[[#This Row],[Catégorie]]="Employe",TPersonnel[[#This Row],[Catégorie]]="Employé"),IF(TPersonnel[[#This Row],[Ancienneté (ans) à la date théorique de sortie]]<6/12,IF(TPersonnel[[#This Row],[Catégorie]]="Ouvrier",1/4,IF(TPersonnel[[#This Row],[Ancienneté (ans) à la date théorique de sortie]]<1/12,0,1)),IF(TPersonnel[[#This Row],[Ancienneté (ans) à la date théorique de sortie]]<2,1,2)),2))))) -> 0 | AN15: =IF(UPPER(TPersonnel[[#This Row],[Fonction à supprimer]])="NON",0,TPersonnel[[#This Row],[Préavis Calc (mois)]]*TPersonnel[[#This Row],[Salaire Brut de référence]]) -> 0 | AO15: =IF(TPersonnel[[#This Row],[Fonction à supprimer]]="NON",0,TPersonnel[[#This Row],[Nb CP Acquis]]+TPersonnel[[#This Row],[Préavis Calc (mois)]]*2.08) -> 0 | AP15: =TPersonnel[[#This Row],[CP Calc (jrs)]]*TPersonnel[[#This Row],[Salaire Brut de référence]]/21.67 -> 0 | AQ15: =IF(UPPER(TPersonnel[[#This Row],[Fonction à supprimer]])="NON",0,_xlfn.LET(_xlpm.taux,IF(TPersonnel[[#This Row],[Catégorie]]="Ouvrier",'📈 Dashboard'!$B$32,IF(TPersonnel[[#This Row],[Catégorie]]="Cadre",'📈 Dashboard'!$B$34,'📈 Dashboard'!$B$33)),_xlpm.csp,UPPER(TPersonnel[[#This Row],[CSP (contrat de sécurisation professionnel)]])="OUI",IF(AND(_xlpm.csp,TPersonnel[[#This Row],[Ancienneté (ans) à la date théorique de sortie]]>=1),MIN(TPersonnel[[#This Row],[Préavis Calc (mois)]],3)*TPersonnel[[#This Row],[Salaire Brut de référence]]*(_xlpm.taux+'⚙️ Parametres'!$B$11)+IF(TPersonnel[[#This Row],[Préavis Calc (mois)]]>3,(TPersonnel[[#This Row],[Préavis Calc (mois)]]-3)*TPersonnel[[#This Row],[Salaire Brut de référence]]*_xlpm.taux,0)+TPersonnel[[#This Row],[Indem CP]]*_xlpm.taux,IF(_xlpm.csp,TPersonnel[[#This Row],[Indem CP]]*_xlpm.taux,(TPersonnel[[#This Row],[Indem Préavis Brut]]+TPersonnel[[#This Row],[Indem CP]])*_xlpm.taux)))) -> 0 | AR15: =TPersonnel[[#This Row],[TOTAL INDEM]]+TPersonnel[[#This Row],[Indem Préavis Brut]]+TPersonnel[[#This Row],[Indem CP]]+TPersonnel[[#This Row],[COÛT Charges Patronales]] -> 0
A16: 70 | B16: Non | C16: BEN HASSINE | D16: Sami | E16: VALENCE | F16: Conducteur PL | G16: CDI | H16: Ouvrier | I16: 150M | J16: H | K16: 43710 | L16: 43710 | M16: 26138 | N16: 2668.64 | P16: 15.58 | Q16: =IF(UPPER(B16)="OUI",'📈 Dashboard'!$B$37,"") | R16: =MAX(N16,O16/12) -> 2668.64 | S16: 2094.42 | T16: =IF(L16="",(TODAY()-K16)/365.25,MAX((TODAY()-K16)/365.25,(TODAY()-L16)/365.25)) -> 6.5352498 | U16: =IF(M16="","",(TODAY()-M16)/365.25) -> 54.644764 | V16: =N16*12 -> 32023.68 | W16: =IF(H16="Cadre",3,IF(H16="Haute maitrise",2,IF(OR(H16="Agent Maitrise",H16="Agent de maitrise"),IF(T16<2/12,0,IF(T16<2,1,2)),IF(OR(H16="Ouvrier"),IF(T16<6/12,1/4,IF(T16<2,1,2)),IF(OR(H16="Employe",H16="Employé"),IF(T16<1/12,0,IF(T16<2,1,2)),2))))) -> 2 | X16: =IF(Q16="",T16,(Q16-K16)/365.25) -> 6.5352498 | AG16: =IF(TPersonnel[[#This Row],[Fonction à supprimer]]="NON",0,IF(TPersonnel[[#This Row],[Ancienneté (ans) à la date théorique de sortie]]<0.67,0,IF(TPersonnel[[#This Row],[Ancienneté (ans) à la date théorique de sortie]]<=10,TPersonnel[[#This Row],[Ancienneté (ans) à la date théorique de sortie]]*TPersonnel[[#This Row],[Salaire Brut de référence]]/4,(10*TPersonnel[[#This Row],[Salaire Brut de référence]]/4+(TPersonnel[[#This Row],[Ancienneté (ans) à la date théorique de sortie]]-10)*TPersonnel[[#This Row],[Salaire Brut de référence]]/3)))) -> 0 | AH16: =IF(UPPER(TPersonnel[[#This Row],[Fonction à supprimer]])="NON",0,IF(TPersonnel[[#This Row],[Ancienneté (ans) à la date théorique de sortie]]<1,0,IF(OR(TPersonnel[[#This Row],[Catégorie]]="Ouvrier",TPersonnel[[#This Row],[Catégorie]]="Employe",TPersonnel[[#This Row],[Catégorie]]="Employé"),IF(TPersonnel[[#This Row],[Ancienneté (ans) à la date théorique de sortie]]<3,TPersonnel[[#This Row],[Ancienneté (ans) à la date théorique de sortie]]*TPersonnel[[#This Row],[Salaire Brut de référence]]/10,TPersonnel[[#This Row],[Ancienneté (ans) à la date théorique de sortie]]*TPersonnel[[#This Row],[Salaire Brut de référence]]*2/10),IF(OR(TPersonnel[[#This Row],[Catégorie]]="Agent Maitrise",TPersonnel[[#This Row],[Catégorie]]="Agent de maitrise",TPersonnel[[#This Row],[Catégorie]]="Haute maitrise"),IF(TPersonnel[[#This Row],[Ancienneté (ans) à la date théorique de sortie]]<3,TPersonnel[[#This Row],[Ancienneté (ans) à la date théorique de sortie]]*TPersonnel[[#This Row],[Salaire Brut de référence]]/10,TPersonnel[[#This Row],[Ancienneté (ans) à la date théorique de sortie]]*TPersonnel[[#This Row],[Salaire Brut de référence]]*3/10),IF(TPersonnel[[#This Row],[Catégorie]]="Cadre",IF(TPersonnel[[#This Row],[Ancienneté (ans) à la date théorique de sortie]]<3,0,TPersonnel[[#This Row],[Ancienneté (ans) à la date théorique de sortie]]*TPersonnel[[#This Row],[Salaire Brut de référence]]*4/10),0))))) -> 0 | AI16: =IF(TPersonnel[[#This Row],[INDEM LÉGALE]]=0,"",IF(TPersonnel[[#This Row],[INDEM LÉGALE]]>TPersonnel[[#This Row],[INDEM CONV.]],"LEGAL","CONVENTIONNEL")) | AJ16: =MAX(TPersonnel[[#This Row],[INDEM LÉGALE]],TPersonnel[[#This Row],[INDEM CONV.]]) -> 0 | AK16: =TPersonnel[[#This Row],[INDEM RETENUE]]*'⚙️ Parametres'!$B$5 -> 0 | AL16: =TPersonnel[[#This Row],[INDEM RETENUE]]+TPersonnel[[#This Row],[Majoration PSE]] -> 0 | AM16: =IF(UPPER(TPersonnel[[#This Row],[Fonction à supprimer]])="NON",0,IF(OR(TPersonnel[[#This Row],[Catégorie]]="Cadre"),3,IF(TPersonnel[[#This Row],[Catégorie]]="Haute maitrise",2,IF(OR(TPersonnel[[#This Row],[Catégorie]]="Agent Maitrise",TPersonnel[[#This Row],[Catégorie]]="Agent de maitrise"),IF(TPersonnel[[#This Row],[Ancienneté (ans) à la date théorique de sortie]]<2/12,0,IF(TPersonnel[[#This Row],[Ancienneté (ans) à la date théorique de sortie]]<2,1,2)),IF(OR(TPersonnel[[#This Row],[Catégorie]]="Ouvrier",TPersonnel[[#This Row],[Catégorie]]="Employe",TPersonnel[[#This Row],[Catégorie]]="Employé"),IF(TPersonnel[[#This Row],[Ancienneté (ans) à la date théorique de sortie]]<6/12,IF(TPersonnel[[#This Row],[Catégorie]]="Ouvrier",1/4,IF(TPersonnel[[#This Row],[Ancienneté (ans) à la date théorique de sortie]]<1/12,0,1)),IF(TPersonnel[[#This Row],[Ancienneté (ans) à la date théorique de sortie]]<2,1,2)),2))))) -> 0 | AN16: =IF(UPPER(TPersonnel[[#This Row],[Fonction à supprimer]])="NON",0,TPersonnel[[#This Row],[Préavis Calc (mois)]]*TPersonnel[[#This Row],[Salaire Brut de référence]]) -> 0 | AO16: =IF(TPersonnel[[#This Row],[Fonction à supprimer]]="NON",0,TPersonnel[[#This Row],[Nb CP Acquis]]+TPersonnel[[#This Row],[Préavis Calc (mois)]]*2.08) -> 0 | AP16: =TPersonnel[[#This Row],[CP Calc (jrs)]]*TPersonnel[[#This Row],[Salaire Brut de référence]]/21.67 -> 0 | AQ16: =IF(UPPER(TPersonnel[[#This Row],[Fonction à supprimer]])="NON",0,_xlfn.LET(_xlpm.taux,IF(TPersonnel[[#This Row],[Catégorie]]="Ouvrier",'📈 Dashboard'!$B$32,IF(TPersonnel[[#This Row],[Catégorie]]="Cadre",'📈 Dashboard'!$B$34,'📈 Dashboard'!$B$33)),_xlpm.csp,UPPER(TPersonnel[[#This Row],[CSP (contrat de sécurisation professionnel)]])="OUI",IF(AND(_xlpm.csp,TPersonnel[[#This Row],[Ancienneté (ans) à la date théorique de sortie]]>=1),MIN(TPersonnel[[#This Row],[Préavis Calc (mois)]],3)*TPersonnel[[#This Row],[Salaire Brut de référence]]*(_xlpm.taux+'⚙️ Parametres'!$B$11)+IF(TPersonnel[[#This Row],[Préavis Calc (mois)]]>3,(TPersonnel[[#This Row],[Préavis Calc (mois)]]-3)*TPersonnel[[#This Row],[Salaire Brut de référence]]*_xlpm.taux,0)+TPersonnel[[#This Row],[Indem CP]]*_xlpm.taux,IF(_xlpm.csp,TPersonnel[[#This Row],[Indem CP]]*_xlpm.taux,(TPersonnel[[#This Row],[Indem Préavis Brut]]+TPersonnel[[#This Row],[Indem CP]])*_xlpm.taux)))) -> 0 | AR16: =TPersonnel[[#This Row],[TOTAL INDEM]]+TPersonnel[[#This Row],[Indem Préavis Brut]]+TPersonnel[[#This Row],[Indem CP]]+TPersonnel[[#This Row],[COÛT Charges Patronales]] -> 0
A17: 77 | B17: Non | C17: RODRIGUES | D17: Paula | E17: VALENCE | F17: Chauffeur PL | G17: CDI | H17: Ouvrier | I17: 150M | J17: F | K17: 38586 | L17: 38586 | M17: 23227 | N17: 2325.78 | P17: 28.58 | Q17: =IF(UPPER(B17)="OUI",'📈 Dashboard'!$B$37,"") | R17: =MAX(N17,O17/12) -> 2325.78 | S17: 3400.2 | T17: =IF(L17="",(TODAY()-K17)/365.25,MAX((TODAY()-K17)/365.25,(TODAY()-L17)/365.25)) -> 20.563997 | U17: =IF(M17="","",(TODAY()-M17)/365.25) -> 62.614648 | V17: =N17*12 -> 27909.36 | W17: =IF(H17="Cadre",3,IF(H17="Haute maitrise",2,IF(OR(H17="Agent Maitrise",H17="Agent de maitrise"),IF(T17<2/12,0,IF(T17<2,1,2)),IF(OR(H17="Ouvrier"),IF(T17<6/12,1/4,IF(T17<2,1,2)),IF(OR(H17="Employe",H17="Employé"),IF(T17<1/12,0,IF(T17<2,1,2)),2))))) -> 2 | X17: =IF(Q17="",T17,(Q17-K17)/365.25) -> 20.563997 | AG17: =IF(TPersonnel[[#This Row],[Fonction à supprimer]]="NON",0,IF(TPersonnel[[#This Row],[Ancienneté (ans) à la date théorique de sortie]]<0.67,0,IF(TPersonnel[[#This Row],[Ancienneté (ans) à la date théorique de sortie]]<=10,TPersonnel[[#This Row],[Ancienneté (ans) à la date théorique de sortie]]*TPersonnel[[#This Row],[Salaire Brut de référence]]/4,(10*TPersonnel[[#This Row],[Salaire Brut de référence]]/4+(TPersonnel[[#This Row],[Ancienneté (ans) à la date théorique de sortie]]-10)*TPersonnel[[#This Row],[Salaire Brut de référence]]/3)))) -> 0 | AH17: =IF(UPPER(TPersonnel[[#This Row],[Fonction à supprimer]])="NON",0,IF(TPersonnel[[#This Row],[Ancienneté (ans) à la date théorique de sortie]]<1,0,IF(OR(TPersonnel[[#This Row],[Catégorie]]="Ouvrier",TPersonnel[[#This Row],[Catégorie]]="Employe",TPersonnel[[#This Row],[Catégorie]]="Employé"),IF(TPersonnel[[#This Row],[Ancienneté (ans) à la date théorique de sortie]]<3,TPersonnel[[#This Row],[Ancienneté (ans) à la date théorique de sortie]]*TPersonnel[[#This Row],[Salaire Brut de référence]]/10,TPersonnel[[#This Row],[Ancienneté (ans) à la date théorique de sortie]]*TPersonnel[[#This Row],[Salaire Brut de référence]]*2/10),IF(OR(TPersonnel[[#This Row],[Catégorie]]="Agent Maitrise",TPersonnel[[#This Row],[Catégorie]]="Agent de maitrise",TPersonnel[[#This Row],[Catégorie]]="Haute maitrise"),IF(TPersonnel[[#This Row],[Ancienneté (ans) à la date théorique de sortie]]<3,TPersonnel[[#This Row],[Ancienneté (ans) à la date théorique de sortie]]*TPersonnel[[#This Row],[Salaire Brut de référence]]/10,TPersonnel[[#This Row],[Ancienneté (ans) à la date théorique de sortie]]*TPersonnel[[#This Row],[Salaire Brut de référence]]*3/10),IF(TPersonnel[[#This Row],[Catégorie]]="Cadre",IF(TPersonnel[[#This Row],[Ancienneté (ans) à la date théorique de sortie]]<3,0,TPersonnel[[#This Row],[Ancienneté (ans) à la date théorique de sortie]]*TPersonnel[[#This Row],[Salaire Brut de référence]]*4/10),0))))) -> 0 | AI17: =IF(TPersonnel[[#This Row],[INDEM LÉGALE]]=0,"",IF(TPersonnel[[#This Row],[INDEM LÉGALE]]>TPersonnel[[#This Row],[INDEM CONV.]],"LEGAL","CONVENTIONNEL")) | AJ17: =MAX(TPersonnel[[#This Row],[INDEM LÉGALE]],TPersonnel[[#This Row],[INDEM CONV.]]) -> 0 | AK17: =TPersonnel[[#This Row],[INDEM RETENUE]]*'⚙️ Parametres'!$B$5 -> 0 | AL17: =TPersonnel[[#This Row],[INDEM RETENUE]]+TPersonnel[[#This Row],[Majoration PSE]] -> 0 | AM17: =IF(UPPER(TPersonnel[[#This Row],[Fonction à supprimer]])="NON",0,IF(OR(TPersonnel[[#This Row],[Catégorie]]="Cadre"),3,IF(TPersonnel[[#This Row],[Catégorie]]="Haute maitrise",2,IF(OR(TPersonnel[[#This Row],[Catégorie]]="Agent Maitrise",TPersonnel[[#This Row],[Catégorie]]="Agent de maitrise"),IF(TPersonnel[[#This Row],[Ancienneté (ans) à la date théorique de sortie]]<2/12,0,IF(TPersonnel[[#This Row],[Ancienneté (ans) à la date théorique de sortie]]<2,1,2)),IF(OR(TPersonnel[[#This Row],[Catégorie]]="Ouvrier",TPersonnel[[#This Row],[Catégorie]]="Employe",TPersonnel[[#This Row],[Catégorie]]="Employé"),IF(TPersonnel[[#This Row],[Ancienneté (ans) à la date théorique de sortie]]<6/12,IF(TPersonnel[[#This Row],[Catégorie]]="Ouvrier",1/4,IF(TPersonnel[[#This Row],[Ancienneté (ans) à la date théorique de sortie]]<1/12,0,1)),IF(TPersonnel[[#This Row],[Ancienneté (ans) à la date théorique de sortie]]<2,1,2)),2))))) -> 0 | AN17: =IF(UPPER(TPersonnel[[#This Row],[Fonction à supprimer]])="NON",0,TPersonnel[[#This Row],[Préavis Calc (mois)]]*TPersonnel[[#This Row],[Salaire Brut de référence]]) -> 0 | AO17: =IF(TPersonnel[[#This Row],[Fonction à supprimer]]="NON",0,TPersonnel[[#This Row],[Nb CP Acquis]]+TPersonnel[[#This Row],[Préavis Calc (mois)]]*2.08) -> 0 | AP17: =TPersonnel[[#This Row],[CP Calc (jrs)]]*TPersonnel[[#This Row],[Salaire Brut de référence]]/21.67 -> 0 | AQ17: =IF(UPPER(TPersonnel[[#This Row],[Fonction à supprimer]])="NON",0,_xlfn.LET(_xlpm.taux,IF(TPersonnel[[#This Row],[Catégorie]]="Ouvrier",'📈 Dashboard'!$B$32,IF(TPersonnel[[#This Row],[Catégorie]]="Cadre",'📈 Dashboard'!$B$34,'📈 Dashboard'!$B$33)),_xlpm.csp,UPPER(TPersonnel[[#This Row],[CSP (contrat de sécurisation professionnel)]])="OUI",IF(AND(_xlpm.csp,TPersonnel[[#This Row],[Ancienneté (ans) à la date théorique de sortie]]>=1),MIN(TPersonnel[[#This Row],[Préavis Calc (mois)]],3)*TPersonnel[[#This Row],[Salaire Brut de référence]]*(_xlpm.taux+'⚙️ Parametres'!$B$11)+IF(TPersonnel[[#This Row],[Préavis Calc (mois)]]>3,(TPersonnel[[#This Row],[Préavis Calc (mois)]]-3)*TPersonnel[[#This Row],[Salaire Brut de référence]]*_xlpm.taux,0)+TPersonnel[[#This Row],[Indem CP]]*_xlpm.taux,IF(_xlpm.csp,TPersonnel[[#This Row],[Indem CP]]*_xlpm.taux,(TPersonnel[[#This Row],[Indem Préavis Brut]]+TPersonnel[[#This Row],[Indem CP]])*_xlpm.taux)))) -> 0 | AR17: =TPersonnel[[#This Row],[TOTAL INDEM]]+TPersonnel[[#This Row],[Indem Préavis Brut]]+TPersonnel[[#This Row],[Indem CP]]+TPersonnel[[#This Row],[COÛT Charges Patronales]] -> 0
A18: 80 | B18: Non | C18: MORIM | D18: Enola | E18: PUSIGNAN | F18: Responsable Exploitation | G18: CDI | H18: Agent de maîtrise | I18: 150 | J18: F | K18: 45165 | L18: 44435 | M18: 37594 | N18: 3200 | P18: 35.58 | Q18: =IF(UPPER(B18)="OUI",'📈 Dashboard'!$B$37,"") | R18: =MAX(N18,O18/12) -> 3200 | S18: 5281.06 | T18: =IF(L18="",(TODAY()-K18)/365.25,MAX((TODAY()-K18)/365.25,(TODAY()-L18)/365.25)) -> 4.550308 | U18: =IF(M18="","",(TODAY()-M18)/365.25) -> 23.279945 | V18: =N18*12 -> 38400 | W18: =IF(H18="Cadre",3,IF(H18="Haute maitrise",2,IF(OR(H18="Agent Maitrise",H18="Agent de maitrise"),IF(T18<2/12,0,IF(T18<2,1,2)),IF(OR(H18="Ouvrier"),IF(T18<6/12,1/4,IF(T18<2,1,2)),IF(OR(H18="Employe",H18="Employé"),IF(T18<1/12,0,IF(T18<2,1,2)),2))))) -> 2 | X18: =IF(Q18="",T18,(Q18-K18)/365.25) -> 4.550308 | AG18: =IF(TPersonnel[[#This Row],[Fonction à supprimer]]="NON",0,IF(TPersonnel[[#This Row],[Ancienneté (ans) à la date théorique de sortie]]<0.67,0,IF(TPersonnel[[#This Row],[Ancienneté (ans) à la date théorique de sortie]]<=10,TPersonnel[[#This Row],[Ancienneté (ans) à la date théorique de sortie]]*TPersonnel[[#This Row],[Salaire Brut de référence]]/4,(10*TPersonnel[[#This Row],[Salaire Brut de référence]]/4+(TPersonnel[[#This Row],[Ancienneté (ans) à la date théorique de sortie]]-10)*TPersonnel[[#This Row],[Salaire Brut de référence]]/3)))) -> 0 | AH18: =IF(UPPER(TPersonnel[[#This Row],[Fonction à supprimer]])="NON",0,IF(TPersonnel[[#This Row],[Ancienneté (ans) à la date théorique de sortie]]<1,0,IF(OR(TPersonnel[[#This Row],[Catégorie]]="Ouvrier",TPersonnel[[#This Row],[Catégorie]]="Employe",TPersonnel[[#This Row],[Catégorie]]="Employé"),IF(TPersonnel[[#This Row],[Ancienneté (ans) à la date théorique de sortie]]<3,TPersonnel[[#This Row],[Ancienneté (ans) à la date théorique de sortie]]*TPersonnel[[#This Row],[Salaire Brut de référence]]/10,TPersonnel[[#This Row],[Ancienneté (ans) à la date théorique de sortie]]*TPersonnel[[#This Row],[Salaire Brut de référence]]*2/10),IF(OR(TPersonnel[[#This Row],[Catégorie]]="Agent Maitrise",TPersonnel[[#This Row],[Catégorie]]="Agent de maitrise",TPersonnel[[#This Row],[Catégorie]]="Haute maitrise"),IF(TPersonnel[[#This Row],[Ancienneté (ans) à la date théorique de sortie]]<3,TPersonnel[[#This Row],[Ancienneté (ans) à la date théorique de sortie]]*TPersonnel[[#This Row],[Salaire Brut de référence]]/10,TPersonnel[[#This Row],[Ancienneté (ans) à la date théorique de sortie]]*TPersonnel[[#This Row],[Salaire Brut de référence]]*3/10),IF(TPersonnel[[#This Row],[Catégorie]]="Cadre",IF(TPersonnel[[#This Row],[Ancienneté (ans) à la date théorique de sortie]]<3,0,TPersonnel[[#This Row],[Ancienneté (ans) à la date théorique de sortie]]*TPersonnel[[#This Row],[Salaire Brut de référence]]*4/10),0))))) -> 0 | AI18: =IF(TPersonnel[[#This Row],[INDEM LÉGALE]]=0,"",IF(TPersonnel[[#This Row],[INDEM LÉGALE]]>TPersonnel[[#This Row],[INDEM CONV.]],"LEGAL","CONVENTIONNEL")) | AJ18: =MAX(TPersonnel[[#This Row],[INDEM LÉGALE]],TPersonnel[[#This Row],[INDEM CONV.]]) -> 0 | AK18: =TPersonnel[[#This Row],[INDEM RETENUE]]*'⚙️ Parametres'!$B$5 -> 0 | AL18: =TPersonnel[[#This Row],[INDEM RETENUE]]+TPersonnel[[#This Row],[Majoration PSE]] -> 0 | AM18: =IF(UPPER(TPersonnel[[#This Row],[Fonction à supprimer]])="NON",0,IF(OR(TPersonnel[[#This Row],[Catégorie]]="Cadre"),3,IF(TPersonnel[[#This Row],[Catégorie]]="Haute maitrise",2,IF(OR(TPersonnel[[#This Row],[Catégorie]]="Agent Maitrise",TPersonnel[[#This Row],[Catégorie]]="Agent de maitrise"),IF(TPersonnel[[#This Row],[Ancienneté (ans) à la date théorique de sortie]]<2/12,0,IF(TPersonnel[[#This Row],[Ancienneté (ans) à la date théorique de sortie]]<2,1,2)),IF(OR(TPersonnel[[#This Row],[Catégorie]]="Ouvrier",TPersonnel[[#This Row],[Catégorie]]="Employe",TPersonnel[[#This Row],[Catégorie]]="Employé"),IF(TPersonnel[[#This Row],[Ancienneté (ans) à la date théorique de sortie]]<6/12,IF(TPersonnel[[#This Row],[Catégorie]]="Ouvrier",1/4,IF(TPersonnel[[#This Row],[Ancienneté (ans) à la date théorique de sortie]]<1/12,0,1)),IF(TPersonnel[[#This Row],[Ancienneté (ans) à la date théorique de sortie]]<2,1,2)),2))))) -> 0 | AN18: =IF(UPPER(TPersonnel[[#This Row],[Fonction à supprimer]])="NON",0,TPersonnel[[#This Row],[Préavis Calc (mois)]]*TPersonnel[[#This Row],[Salaire Brut de référence]]) -> 0 | AO18: =IF(TPersonnel[[#This Row],[Fonction à supprimer]]="NON",0,TPersonnel[[#This Row],[Nb CP Acquis]]+TPersonnel[[#This Row],[Préavis Calc (mois)]]*2.08) -> 0 | AP18: =TPersonnel[[#This Row],[CP Calc (jrs)]]*TPersonnel[[#This Row],[Salaire Brut de référence]]/21.67 -> 0 | AQ18: =IF(UPPER(TPersonnel[[#This Row],[Fonction à supprimer]])="NON",0,_xlfn.LET(_xlpm.taux,IF(TPersonnel[[#This Row],[Catégorie]]="Ouvrier",'📈 Dashboard'!$B$32,IF(TPersonnel[[#This Row],[Catégorie]]="Cadre",'📈 Dashboard'!$B$34,'📈 Dashboard'!$B$33)),_xlpm.csp,UPPER(TPersonnel[[#This Row],[CSP (contrat de sécurisation professionnel)]])="OUI",IF(AND(_xlpm.csp,TPersonnel[[#This Row],[Ancienneté (ans) à la date théorique de sortie]]>=1),MIN(TPersonnel[[#This Row],[Préavis Calc (mois)]],3)*TPersonnel[[#This Row],[Salaire Brut de référence]]*(_xlpm.taux+'⚙️ Parametres'!$B$11)+IF(TPersonnel[[#This Row],[Préavis Calc (mois)]]>3,(TPersonnel[[#This Row],[Préavis Calc (mois)]]-3)*TPersonnel[[#This Row],[Salaire Brut de référence]]*_xlpm.taux,0)+TPersonnel[[#This Row],[Indem CP]]*_xlpm.taux,IF(_xlpm.csp,TPersonnel[[#This Row],[Indem CP]]*_xlpm.taux,(TPersonnel[[#This Row],[Indem Préavis Brut]]+TPersonnel[[#This Row],[Indem CP]])*_xlpm.taux)))) -> 0 | AR18: =TPersonnel[[#This Row],[TOTAL INDEM]]+TPersonnel[[#This Row],[Indem Préavis Brut]]+TPersonnel[[#This Row],[Indem CP]]+TPersonnel[[#This Row],[COÛT Charges Patronales]] -> 0
A19: 81 | B19: Non | C19: TALBI | D19: Mehdi | E19: VALENCE | F19: Conducteur PL | G19: CDI | H19: Ouvrier | I19: 138M | J19: H | K19: 44440 | L19: 44440 | M19: 36214 | N19: 2439.79 | P19: 19.58 | Q19: =IF(UPPER(B19)="OUI",'📈 Dashboard'!$B$37,"") | R19: =MAX(N19,O19/12) -> 2439.79 | S19: 2709.01 | T19: =IF(L19="",(TODAY()-K19)/365.25,MAX((TODAY()-K19)/365.25,(TODAY()-L19)/365.25)) -> 4.5366188 | U19: =IF(M19="","",(TODAY()-M19)/365.25) -> 27.058179 | V19: =N19*12 -> 29277.48 | W19: =IF(H19="Cadre",3,IF(H19="Haute maitrise",2,IF(OR(H19="Agent Maitrise",H19="Agent de maitrise"),IF(T19<2/12,0,IF(T19<2,1,2)),IF(OR(H19="Ouvrier"),IF(T19<6/12,1/4,IF(T19<2,1,2)),IF(OR(H19="Employe",H19="Employé"),IF(T19<1/12,0,IF(T19<2,1,2)),2))))) -> 2 | X19: =IF(Q19="",T19,(Q19-K19)/365.25) -> 4.5366188 | AG19: =IF(TPersonnel[[#This Row],[Fonction à supprimer]]="NON",0,IF(TPersonnel[[#This Row],[Ancienneté (ans) à la date théorique de sortie]]<0.67,0,IF(TPersonnel[[#This Row],[Ancienneté (ans) à la date théorique de sortie]]<=10,TPersonnel[[#This Row],[Ancienneté (ans) à la date théorique de sortie]]*TPersonnel[[#This Row],[Salaire Brut de référence]]/4,(10*TPersonnel[[#This Row],[Salaire Brut de référence]]/4+(TPersonnel[[#This Row],[Ancienneté (ans) à la date théorique de sortie]]-10)*TPersonnel[[#This Row],[Salaire Brut de référence]]/3)))) -> 0 | AH19: =IF(UPPER(TPersonnel[[#This Row],[Fonction à supprimer]])="NON",0,IF(TPersonnel[[#This Row],[Ancienneté (ans) à la date théorique de sortie]]<1,0,IF(OR(TPersonnel[[#This Row],[Catégorie]]="Ouvrier",TPersonnel[[#This Row],[Catégorie]]="Employe",TPersonnel[[#This Row],[Catégorie]]="Employé"),IF(TPersonnel[[#This Row],[Ancienneté (ans) à la date théorique de sortie]]<3,TPersonnel[[#This Row],[Ancienneté (ans) à la date théorique de sortie]]*TPersonnel[[#This Row],[Salaire Brut de référence]]/10,TPersonnel[[#This Row],[Ancienneté (ans) à la date théorique de sortie]]*TPersonnel[[#This Row],[Salaire Brut de référence]]*2/10),IF(OR(TPersonnel[[#This Row],[Catégorie]]="Agent Maitrise",TPersonnel[[#This Row],[Catégorie]]="Agent de maitrise",TPersonnel[[#This Row],[Catégorie]]="Haute maitrise"),IF(TPersonnel[[#This Row],[Ancienneté (ans) à la date théorique de sortie]]<3,TPersonnel[[#This Row],[Ancienneté (ans) à la date théorique de sortie]]*TPersonnel[[#This Row],[Salaire Brut de référence]]/10,TPersonnel[[#This Row],[Ancienneté (ans) à la date théorique de sortie]]*TPersonnel[[#This Row],[Salaire Brut de référence]]*3/10),IF(TPersonnel[[#This Row],[Catégorie]]="Cadre",IF(TPersonnel[[#This Row],[Ancienneté (ans) à la date théorique de sortie]]<3,0,TPersonnel[[#This Row],[Ancienneté (ans) à la date théorique de sortie]]*TPersonnel[[#This Row],[Salaire Brut de référence]]*4/10),0))))) -> 0 | AI19: =IF(TPersonnel[[#This Row],[INDEM LÉGALE]]=0,"",IF(TPersonnel[[#This Row],[INDEM LÉGALE]]>TPersonnel[[#This Row],[INDEM CONV.]],"LEGAL","CONVENTIONNEL")) | AJ19: =MAX(TPersonnel[[#This Row],[INDEM LÉGALE]],TPersonnel[[#This Row],[INDEM CONV.]]) -> 0 | AK19: =TPersonnel[[#This Row],[INDEM RETENUE]]*'⚙️ Parametres'!$B$5 -> 0 | AL19: =TPersonnel[[#This Row],[INDEM RETENUE]]+TPersonnel[[#This Row],[Majoration PSE]] -> 0 | AM19: =IF(UPPER(TPersonnel[[#This Row],[Fonction à supprimer]])="NON",0,IF(OR(TPersonnel[[#This Row],[Catégorie]]="Cadre"),3,IF(TPersonnel[[#This Row],[Catégorie]]="Haute maitrise",2,IF(OR(TPersonnel[[#This Row],[Catégorie]]="Agent Maitrise",TPersonnel[[#This Row],[Catégorie]]="Agent de maitrise"),IF(TPersonnel[[#This Row],[Ancienneté (ans) à la date théorique de sortie]]<2/12,0,IF(TPersonnel[[#This Row],[Ancienneté (ans) à la date théorique de sortie]]<2,1,2)),IF(OR(TPersonnel[[#This Row],[Catégorie]]="Ouvrier",TPersonnel[[#This Row],[Catégorie]]="Employe",TPersonnel[[#This Row],[Catégorie]]="Employé"),IF(TPersonnel[[#This Row],[Ancienneté (ans) à la date théorique de sortie]]<6/12,IF(TPersonnel[[#This Row],[Catégorie]]="Ouvrier",1/4,IF(TPersonnel[[#This Row],[Ancienneté (ans) à la date théorique de sortie]]<1/12,0,1)),IF(TPersonnel[[#This Row],[Ancienneté (ans) à la date théorique de sortie]]<2,1,2)),2))))) -> 0 | AN19: =IF(UPPER(TPersonnel[[#This Row],[Fonction à supprimer]])="NON",0,TPersonnel[[#This Row],[Préavis Calc (mois)]]*TPersonnel[[#This Row],[Salaire Brut de référence]]) -> 0 | AO19: =IF(TPersonnel[[#This Row],[Fonction à supprimer]]="NON",0,TPersonnel[[#This Row],[Nb CP Acquis]]+TPersonnel[[#This Row],[Préavis Calc (mois)]]*2.08) -> 0 | AP19: =TPersonnel[[#This Row],[CP Calc (jrs)]]*TPersonnel[[#This Row],[Salaire Brut de référence]]/21.67 -> 0 | AQ19: =IF(UPPER(TPersonnel[[#This Row],[Fonction à supprimer]])="NON",0,_xlfn.LET(_xlpm.taux,IF(TPersonnel[[#This Row],[Catégorie]]="Ouvrier",'📈 Dashboard'!$B$32,IF(TPersonnel[[#This Row],[Catégorie]]="Cadre",'📈 Dashboard'!$B$34,'📈 Dashboard'!$B$33)),_xlpm.csp,UPPER(TPersonnel[[#This Row],[CSP (contrat de sécurisation professionnel)]])="OUI",IF(AND(_xlpm.csp,TPersonnel[[#This Row],[Ancienneté (ans) à la date théorique de sortie]]>=1),MIN(TPersonnel[[#This Row],[Préavis Calc (mois)]],3)*TPersonnel[[#This Row],[Salaire Brut de référence]]*(_xlpm.taux+'⚙️ Parametres'!$B$11)+IF(TPersonnel[[#This Row],[Préavis Calc (mois)]]>3,(TPersonnel[[#This Row],[Préavis Calc (mois)]]-3)*TPersonnel[[#This Row],[Salaire Brut de référence]]*_xlpm.taux,0)+TPersonnel[[#This Row],[Indem CP]]*_xlpm.taux,IF(_xlpm.csp,TPersonnel[[#This Row],[Indem CP]]*_xlpm.taux,(TPersonnel[[#This Row],[Indem Préavis Brut]]+TPersonnel[[#This Row],[Indem CP]])*_xlpm.taux)))) -> 0 | AR19: =TPersonnel[[#This Row],[TOTAL INDEM]]+TPersonnel[[#This Row],[Indem Préavis Brut]]+TPersonnel[[#This Row],[Indem CP]]+TPersonnel[[#This Row],[COÛT Charges Patronales]] -> 0
A20: 83 | B20: Non | C20: ABDOULKARIM | D20: Amir | E20: ROGNAC | F20: Conducteur PL | G20: CDI | H20: Ouvrier | I20: 138M | J20: H | K20: 44446 | L20: 44446 | M20: 29677 | N20: 3151.19 | P20: 7.08 | Q20: =IF(UPPER(B20)="OUI",'📈 Dashboard'!$B$37,"") | R20: =MAX(N20,O20/12) -> 3151.19 | S20: 1038.15 | T20: =IF(L20="",(TODAY()-K20)/365.25,MAX((TODAY()-K20)/365.25,(TODAY()-L20)/365.25)) -> 4.5201916 | U20: =IF(M20="","",(TODAY()-M20)/365.25) -> 44.95551 | V20: =N20*12 -> 37814.28 | W20: =IF(H20="Cadre",3,IF(H20="Haute maitrise",2,IF(OR(H20="Agent Maitrise",H20="Agent de maitrise"),IF(T20<2/12,0,IF(T20<2,1,2)),IF(OR(H20="Ouvrier"),IF(T20<6/12,1/4,IF(T20<2,1,2)),IF(OR(H20="Employe",H20="Employé"),IF(T20<1/12,0,IF(T20<2,1,2)),2))))) -> 2 | X20: =IF(Q20="",T20,(Q20-K20)/365.25) -> 4.5201916 | AG20: =IF(TPersonnel[[#This Row],[Fonction à supprimer]]="NON",0,IF(TPersonnel[[#This Row],[Ancienneté (ans) à la date théorique de sortie]]<0.67,0,IF(TPersonnel[[#This Row],[Ancienneté (ans) à la date théorique de sortie]]<=10,TPersonnel[[#This Row],[Ancienneté (ans) à la date théorique de sortie]]*TPersonnel[[#This Row],[Salaire Brut de référence]]/4,(10*TPersonnel[[#This Row],[Salaire Brut de référence]]/4+(TPersonnel[[#This Row],[Ancienneté (ans) à la date théorique de sortie]]-10)*TPersonnel[[#This Row],[Salaire Brut de référence]]/3)))) -> 0 | AH20: =IF(UPPER(TPersonnel[[#This Row],[Fonction à supprimer]])="NON",0,IF(TPersonnel[[#This Row],[Ancienneté (ans) à la date théorique de sortie]]<1,0,IF(OR(TPersonnel[[#This Row],[Catégorie]]="Ouvrier",TPersonnel[[#This Row],[Catégorie]]="Employe",TPersonnel[[#This Row],[Catégorie]]="Employé"),IF(TPersonnel[[#This Row],[Ancienneté (ans) à la date théorique de sortie]]<3,TPersonnel[[#This Row],[Ancienneté (ans) à la date théorique de sortie]]*TPersonnel[[#This Row],[Salaire Brut de référence]]/10,TPersonnel[[#This Row],[Ancienneté (ans) à la date théorique de sortie]]*TPersonnel[[#This Row],[Salaire Brut de référence]]*2/10),IF(OR(TPersonnel[[#This Row],[Catégorie]]="Agent Maitrise",TPersonnel[[#This Row],[Catégorie]]="Agent de maitrise",TPersonnel[[#This Row],[Catégorie]]="Haute maitrise"),IF(TPersonnel[[#This Row],[Ancienneté (ans) à la date théorique de sortie]]<3,TPersonnel[[#This Row],[Ancienneté (ans) à la date théorique de sortie]]*TPersonnel[[#This Row],[Salaire Brut de référence]]/10,TPersonnel[[#This Row],[Ancienneté (ans) à la date théorique de sortie]]*TPersonnel[[#This Row],[Salaire Brut de référence]]*3/10),IF(TPersonnel[[#This Row],[Catégorie]]="Cadre",IF(TPersonnel[[#This Row],[Ancienneté (ans) à la date théorique de sortie]]<3,0,TPersonnel[[#This Row],[Ancienneté (ans) à la date théorique de sortie]]*TPersonnel[[#This Row],[Salaire Brut de référence]]*4/10),0))))) -> 0 | AI20: =IF(TPersonnel[[#This Row],[INDEM LÉGALE]]=0,"",IF(TPersonnel[[#This Row],[INDEM LÉGALE]]>TPersonnel[[#This Row],[INDEM CONV.]],"LEGAL","CONVENTIONNEL")) | AJ20: =MAX(TPersonnel[[#This Row],[INDEM LÉGALE]],TPersonnel[[#This Row],[INDEM CONV.]]) -> 0 | AK20: =TPersonnel[[#This Row],[INDEM RETENUE]]*'⚙️ Parametres'!$B$5 -> 0 | AL20: =TPersonnel[[#This Row],[INDEM RETENUE]]+TPersonnel[[#This Row],[Majoration PSE]] -> 0 | AM20: =IF(UPPER(TPersonnel[[#This Row],[Fonction à supprimer]])="NON",0,IF(OR(TPersonnel[[#This Row],[Catégorie]]="Cadre"),3,IF(TPersonnel[[#This Row],[Catégorie]]="Haute maitrise",2,IF(OR(TPersonnel[[#This Row],[Catégorie]]="Agent Maitrise",TPersonnel[[#This Row],[Catégorie]]="Agent de maitrise"),IF(TPersonnel[[#This Row],[Ancienneté (ans) à la date théorique de sortie]]<2/12,0,IF(TPersonnel[[#This Row],[Ancienneté (ans) à la date théorique de sortie]]<2,1,2)),IF(OR(TPersonnel[[#This Row],[Catégorie]]="Ouvrier",TPersonnel[[#This Row],[Catégorie]]="Employe",TPersonnel[[#This Row],[Catégorie]]="Employé"),IF(TPersonnel[[#This Row],[Ancienneté (ans) à la date théorique de sortie]]<6/12,IF(TPersonnel[[#This Row],[Catégorie]]="Ouvrier",1/4,IF(TPersonnel[[#This Row],[Ancienneté (ans) à la date théorique de sortie]]<1/12,0,1)),IF(TPersonnel[[#This Row],[Ancienneté (ans) à la date théorique de sortie]]<2,1,2)),2))))) -> 0 | AN20: =IF(UPPER(TPersonnel[[#This Row],[Fonction à supprimer]])="NON",0,TPersonnel[[#This Row],[Préavis Calc (mois)]]*TPersonnel[[#This Row],[Salaire Brut de référence]]) -> 0 | AO20: =IF(TPersonnel[[#This Row],[Fonction à supprimer]]="NON",0,TPersonnel[[#This Row],[Nb CP Acquis]]+TPersonnel[[#This Row],[Préavis Calc (mois)]]*2.08) -> 0 | AP20: =TPersonnel[[#This Row],[CP Calc (jrs)]]*TPersonnel[[#This Row],[Salaire Brut de référence]]/21.67 -> 0 | AQ20: =IF(UPPER(TPersonnel[[#This Row],[Fonction à supprimer]])="NON",0,_xlfn.LET(_xlpm.taux,IF(TPersonnel[[#This Row],[Catégorie]]="Ouvrier",'📈 Dashboard'!$B$32,IF(TPersonnel[[#This Row],[Catégorie]]="Cadre",'📈 Dashboard'!$B$34,'📈 Dashboard'!$B$33)),_xlpm.csp,UPPER(TPersonnel[[#This Row],[CSP (contrat de sécurisation professionnel)]])="OUI",IF(AND(_xlpm.csp,TPersonnel[[#This Row],[Ancienneté (ans) à la date théorique de sortie]]>=1),MIN(TPersonnel[[#This Row],[Préavis Calc (mois)]],3)*TPersonnel[[#This Row],[Salaire Brut de référence]]*(_xlpm.taux+'⚙️ Parametres'!$B$11)+IF(TPersonnel[[#This Row],[Préavis Calc (mois)]]>3,(TPersonnel[[#This Row],[Préavis Calc (mois)]]-3)*TPersonnel[[#This Row],[Salaire Brut de référence]]*_xlpm.taux,0)+TPersonnel[[#This Row],[Indem CP]]*_xlpm.taux,IF(_xlpm.csp,TPersonnel[[#This Row],[Indem CP]]*_xlpm.taux,(TPersonnel[[#This Row],[Indem Préavis Brut]]+TPersonnel[[#This Row],[Indem CP]])*_xlpm.taux)))) -> 0 | AR20: =TPersonnel[[#This Row],[TOTAL INDEM]]+TPersonnel[[#This Row],[Indem Préavis Brut]]+TPersonnel[[#This Row],[Indem CP]]+TPersonnel[[#This Row],[COÛT Charges Patronales]] -> 0
A21: 2772 | B21: Non | C21: LAGIER | D21: Vivien | E21: VALENCE | F21: Affréteur | G21: CDI | H21: Employé | I21: 125 | J21: H | K21: 44440 | L21: 44440 | M21: 31293 | N21: 2550 | P21: 28.08 | Q21: =IF(UPPER(B21)="OUI",'📈 Dashboard'!$B$37,"") | R21: =MAX(N21,O21/12) -> 2550 | S21: 3437.4 | T21: =IF(L21="",(TODAY()-K21)/365.25,MAX((TODAY()-K21)/365.25,(TODAY()-L21)/365.25)) -> 4.5366188 | U21: =IF(M21="","",(TODAY()-M21)/365.25) -> 40.531143 | V21: =N21*12 -> 30600 | W21: =IF(H21="Cadre",3,IF(H21="Haute maitrise",2,IF(OR(H21="Agent Maitrise",H21="Agent de maitrise"),IF(T21<2/12,0,IF(T21<2,1,2)),IF(OR(H21="Ouvrier"),IF(T21<6/12,1/4,IF(T21<2,1,2)),IF(OR(H21="Employe",H21="Employé"),IF(T21<1/12,0,IF(T21<2,1,2)),2))))) -> 2 | X21: =IF(Q21="",T21,(Q21-K21)/365.25) -> 4.5366188 | AG21: =IF(TPersonnel[[#This Row],[Fonction à supprimer]]="NON",0,IF(TPersonnel[[#This Row],[Ancienneté (ans) à la date théorique de sortie]]<0.67,0,IF(TPersonnel[[#This Row],[Ancienneté (ans) à la date théorique de sortie]]<=10,TPersonnel[[#This Row],[Ancienneté (ans) à la date théorique de sortie]]*TPersonnel[[#This Row],[Salaire Brut de référence]]/4,(10*TPersonnel[[#This Row],[Salaire Brut de référence]]/4+(TPersonnel[[#This Row],[Ancienneté (ans) à la date théorique de sortie]]-10)*TPersonnel[[#This Row],[Salaire Brut de référence]]/3)))) -> 0 | AH21: =IF(UPPER(TPersonnel[[#This Row],[Fonction à supprimer]])="NON",0,IF(TPersonnel[[#This Row],[Ancienneté (ans) à la date théorique de sortie]]<1,0,IF(OR(TPersonnel[[#This Row],[Catégorie]]="Ouvrier",TPersonnel[[#This Row],[Catégorie]]="Employe",TPersonnel[[#This Row],[Catégorie]]="Employé"),IF(TPersonnel[[#This Row],[Ancienneté (ans) à la date théorique de sortie]]<3,TPersonnel[[#This Row],[Ancienneté (ans) à la date théorique de sortie]]*TPersonnel[[#This Row],[Salaire Brut de référence]]/10,TPersonnel[[#This Row],[Ancienneté (ans) à la date théorique de sortie]]*TPersonnel[[#This Row],[Salaire Brut de référence]]*2/10),IF(OR(TPersonnel[[#This Row],[Catégorie]]="Agent Maitrise",TPersonnel[[#This Row],[Catégorie]]="Agent de maitrise",TPersonnel[[#This Row],[Catégorie]]="Haute maitrise"),IF(TPersonnel[[#This Row],[Ancienneté (ans) à la date théorique de sortie]]<3,TPersonnel[[#This Row],[Ancienneté (ans) à la date théorique de sortie]]*TPersonnel[[#This Row],[Salaire Brut de référence]]/10,TPersonnel[[#This Row],[Ancienneté (ans) à la date théorique de sortie]]*TPersonnel[[#This Row],[Salaire Brut de référence]]*3/10),IF(TPersonnel[[#This Row],[Catégorie]]="Cadre",IF(TPersonnel[[#This Row],[Ancienneté (ans) à la date théorique de sortie]]<3,0,TPersonnel[[#This Row],[Ancienneté (ans) à la date théorique de sortie]]*TPersonnel[[#This Row],[Salaire Brut de référence]]*4/10),0))))) -> 0 | AI21: =IF(TPersonnel[[#This Row],[INDEM LÉGALE]]=0,"",IF(TPersonnel[[#This Row],[INDEM LÉGALE]]>TPersonnel[[#This Row],[INDEM CONV.]],"LEGAL","CONVENTIONNEL")) | AJ21: =MAX(TPersonnel[[#This Row],[INDEM LÉGALE]],TPersonnel[[#This Row],[INDEM CONV.]]) -> 0 | AK21: =TPersonnel[[#This Row],[INDEM RETENUE]]*'⚙️ Parametres'!$B$5 -> 0 | AL21: =TPersonnel[[#This Row],[INDEM RETENUE]]+TPersonnel[[#This Row],[Majoration PSE]] -> 0 | AM21: =IF(UPPER(TPersonnel[[#This Row],[Fonction à supprimer]])="NON",0,IF(OR(TPersonnel[[#This Row],[Catégorie]]="Cadre"),3,IF(TPersonnel[[#This Row],[Catégorie]]="Haute maitrise",2,IF(OR(TPersonnel[[#This Row],[Catégorie]]="Agent Maitrise",TPersonnel[[#This Row],[Catégorie]]="Agent de maitrise"),IF(TPersonnel[[#This Row],[Ancienneté (ans) à la date théorique de sortie]]<2/12,0,IF(TPersonnel[[#This Row],[Ancienneté (ans) à la date théorique de sortie]]<2,1,2)),IF(OR(TPersonnel[[#This Row],[Catégorie]]="Ouvrier",TPersonnel[[#This Row],[Catégorie]]="Employe",TPersonnel[[#This Row],[Catégorie]]="Employé"),IF(TPersonnel[[#This Row],[Ancienneté (ans) à la date théorique de sortie]]<6/12,IF(TPersonnel[[#This Row],[Catégorie]]="Ouvrier",1/4,IF(TPersonnel[[#This Row],[Ancienneté (ans) à la date théorique de sortie]]<1/12,0,1)),IF(TPersonnel[[#This Row],[Ancienneté (ans) à la date théorique de sortie]]<2,1,2)),2))))) -> 0 | AN21: =IF(UPPER(TPersonnel[[#This Row],[Fonction à supprimer]])="NON",0,TPersonnel[[#This Row],[Préavis Calc (mois)]]*TPersonnel[[#This Row],[Salaire Brut de référence]]) -> 0 | AO21: =IF(TPersonnel[[#This Row],[Fonction à supprimer]]="NON",0,TPersonnel[[#This Row],[Nb CP Acquis]]+TPersonnel[[#This Row],[Préavis Calc (mois)]]*2.08) -> 0 | AP21: =TPersonnel[[#This Row],[CP Calc (jrs)]]*TPersonnel[[#This Row],[Salaire Brut de référence]]/21.67 -> 0 | AQ21: =IF(UPPER(TPersonnel[[#This Row],[Fonction à supprimer]])="NON",0,_xlfn.LET(_xlpm.taux,IF(TPersonnel[[#This Row],[Catégorie]]="Ouvrier",'📈 Dashboard'!$B$32,IF(TPersonnel[[#This Row],[Catégorie]]="Cadre",'📈 Dashboard'!$B$34,'📈 Dashboard'!$B$33)),_xlpm.csp,UPPER(TPersonnel[[#This Row],[CSP (contrat de sécurisation professionnel)]])="OUI",IF(AND(_xlpm.csp,TPersonnel[[#This Row],[Ancienneté (ans) à la date théorique de sortie]]>=1),MIN(TPersonnel[[#This Row],[Préavis Calc (mois)]],3)*TPersonnel[[#This Row],[Salaire Brut de référence]]*(_xlpm.taux+'⚙️ Parametres'!$B$11)+IF(TPersonnel[[#This Row],[Préavis Calc (mois)]]>3,(TPersonnel[[#This Row],[Préavis Calc (mois)]]-3)*TPersonnel[[#This Row],[Salaire Brut de référence]]*_xlpm.taux,0)+TPersonnel[[#This Row],[Indem CP]]*_xlpm.taux,IF(_xlpm.csp,TPersonnel[[#This Row],[Indem CP]]*_xlpm.taux,(TPersonnel[[#This Row],[Indem Préavis Brut]]+TPersonnel[[#This Row],[Indem CP]])*_xlpm.taux)))) -> 0 | AR21: =TPersonnel[[#This Row],[TOTAL INDEM]]+TPersonnel[[#This Row],[Indem Préavis Brut]]+TPersonnel[[#This Row],[Indem CP]]+TPersonnel[[#This Row],[COÛT Charges Patronales]] -> 0
A22: 2773 | B22: Non | C22: ALI | D22: Nassuf | E22: ROGNAC | F22: Conducteur PL | G22: CDI | H22: Ouvrier | I22: 138M | J22: H | K22: 44473 | L22: 44473 | M22: 31093 | N22: 2751.22 | P22: 6.58 | Q22: =IF(UPPER(B22)="OUI",'📈 Dashboard'!$B$37,"") | R22: =MAX(N22,O22/12) -> 2751.22 | S22: 889.17 | T22: =IF(L22="",(TODAY()-K22)/365.25,MAX((TODAY()-K22)/365.25,(TODAY()-L22)/365.25)) -> 4.4462697 | U22: =IF(M22="","",(TODAY()-M22)/365.25) -> 41.078713 | V22: =N22*12 -> 33014.64 | W22: =IF(H22="Cadre",3,IF(H22="Haute maitrise",2,IF(OR(H22="Agent Maitrise",H22="Agent de maitrise"),IF(T22<2/12,0,IF(T22<2,1,2)),IF(OR(H22="Ouvrier"),IF(T22<6/12,1/4,IF(T22<2,1,2)),IF(OR(H22="Employe",H22="Employé"),IF(T22<1/12,0,IF(T22<2,1,2)),2))))) -> 2 | X22: =IF(Q22="",T22,(Q22-K22)/365.25) -> 4.4462697 | AG22: =IF(TPersonnel[[#This Row],[Fonction à supprimer]]="NON",0,IF(TPersonnel[[#This Row],[Ancienneté (ans) à la date théorique de sortie]]<0.67,0,IF(TPersonnel[[#This Row],[Ancienneté (ans) à la date théorique de sortie]]<=10,TPersonnel[[#This Row],[Ancienneté (ans) à la date théorique de sortie]]*TPersonnel[[#This Row],[Salaire Brut de référence]]/4,(10*TPersonnel[[#This Row],[Salaire Brut de référence]]/4+(TPersonnel[[#This Row],[Ancienneté (ans) à la date théorique de sortie]]-10)*TPersonnel[[#This Row],[Salaire Brut de référence]]/3)))) -> 0 | AH22: =IF(UPPER(TPersonnel[[#This Row],[Fonction à supprimer]])="NON",0,IF(TPersonnel[[#This Row],[Ancienneté (ans) à la date théorique de sortie]]<1,0,IF(OR(TPersonnel[[#This Row],[Catégorie]]="Ouvrier",TPersonnel[[#This Row],[Catégorie]]="Employe",TPersonnel[[#This Row],[Catégorie]]="Employé"),IF(TPersonnel[[#This Row],[Ancienneté (ans) à la date théorique de sortie]]<3,TPersonnel[[#This Row],[Ancienneté (ans) à la date théorique de sortie]]*TPersonnel[[#This Row],[Salaire Brut de référence]]/10,TPersonnel[[#This Row],[Ancienneté (ans) à la date théorique de sortie]]*TPersonnel[[#This Row],[Salaire Brut de référence]]*2/10),IF(OR(TPersonnel[[#This Row],[Catégorie]]="Agent Maitrise",TPersonnel[[#This Row],[Catégorie]]="Agent de maitrise",TPersonnel[[#This Row],[Catégorie]]="Haute maitrise"),IF(TPersonnel[[#This Row],[Ancienneté (ans) à la date théorique de sortie]]<3,TPersonnel[[#This Row],[Ancienneté (ans) à la date théorique de sortie]]*TPersonnel[[#This Row],[Salaire Brut de référence]]/10,TPersonnel[[#This Row],[Ancienneté (ans) à la date théorique de sortie]]*TPersonnel[[#This Row],[Salaire Brut de référence]]*3/10),IF(TPersonnel[[#This Row],[Catégorie]]="Cadre",IF(TPersonnel[[#This Row],[Ancienneté (ans) à la date théorique de sortie]]<3,0,TPersonnel[[#This Row],[Ancienneté (ans) à la date théorique de sortie]]*TPersonnel[[#This Row],[Salaire Brut de référence]]*4/10),0))))) -> 0 | AI22: =IF(TPersonnel[[#This Row],[INDEM LÉGALE]]=0,"",IF(TPersonnel[[#This Row],[INDEM LÉGALE]]>TPersonnel[[#This Row],[INDEM CONV.]],"LEGAL","CONVENTIONNEL")) | AJ22: =MAX(TPersonnel[[#This Row],[INDEM LÉGALE]],TPersonnel[[#This Row],[INDEM CONV.]]) -> 0 | AK22: =TPersonnel[[#This Row],[INDEM RETENUE]]*'⚙️ Parametres'!$B$5 -> 0 | AL22: =TPersonnel[[#This Row],[INDEM RETENUE]]+TPersonnel[[#This Row],[Majoration PSE]] -> 0 | AM22: =IF(UPPER(TPersonnel[[#This Row],[Fonction à supprimer]])="NON",0,IF(OR(TPersonnel[[#This Row],[Catégorie]]="Cadre"),3,IF(TPersonnel[[#This Row],[Catégorie]]="Haute maitrise",2,IF(OR(TPersonnel[[#This Row],[Catégorie]]="Agent Maitrise",TPersonnel[[#This Row],[Catégorie]]="Agent de maitrise"),IF(TPersonnel[[#This Row],[Ancienneté (ans) à la date théorique de sortie]]<2/12,0,IF(TPersonnel[[#This Row],[Ancienneté (ans) à la date théorique de sortie]]<2,1,2)),IF(OR(TPersonnel[[#This Row],[Catégorie]]="Ouvrier",TPersonnel[[#This Row],[Catégorie]]="Employe",TPersonnel[[#This Row],[Catégorie]]="Employé"),IF(TPersonnel[[#This Row],[Ancienneté (ans) à la date théorique de sortie]]<6/12,IF(TPersonnel[[#This Row],[Catégorie]]="Ouvrier",1/4,IF(TPersonnel[[#This Row],[Ancienneté (ans) à la date théorique de sortie]]<1/12,0,1)),IF(TPersonnel[[#This Row],[Ancienneté (ans) à la date théorique de sortie]]<2,1,2)),2))))) -> 0 | AN22: =IF(UPPER(TPersonnel[[#This Row],[Fonction à supprimer]])="NON",0,TPersonnel[[#This Row],[Préavis Calc (mois)]]*TPersonnel[[#This Row],[Salaire Brut de référence]]) -> 0 | AO22: =IF(TPersonnel[[#This Row],[Fonction à supprimer]]="NON",0,TPersonnel[[#This Row],[Nb CP Acquis]]+TPersonnel[[#This Row],[Préavis Calc (mois)]]*2.08) -> 0 | AP22: =TPersonnel[[#This Row],[CP Calc (jrs)]]*TPersonnel[[#This Row],[Salaire Brut de référence]]/21.67 -> 0 | AQ22: =IF(UPPER(TPersonnel[[#This Row],[Fonction à supprimer]])="NON",0,_xlfn.LET(_xlpm.taux,IF(TPersonnel[[#This Row],[Catégorie]]="Ouvrier",'📈 Dashboard'!$B$32,IF(TPersonnel[[#This Row],[Catégorie]]="Cadre",'📈 Dashboard'!$B$34,'📈 Dashboard'!$B$33)),_xlpm.csp,UPPER(TPersonnel[[#This Row],[CSP (contrat de sécurisation professionnel)]])="OUI",IF(AND(_xlpm.csp,TPersonnel[[#This Row],[Ancienneté (ans) à la date théorique de sortie]]>=1),MIN(TPersonnel[[#This Row],[Préavis Calc (mois)]],3)*TPersonnel[[#This Row],[Salaire Brut de référence]]*(_xlpm.taux+'⚙️ Parametres'!$B$11)+IF(TPersonnel[[#This Row],[Préavis Calc (mois)]]>3,(TPersonnel[[#This Row],[Préavis Calc (mois)]]-3)*TPersonnel[[#This Row],[Salaire Brut de référence]]*_xlpm.taux,0)+TPersonnel[[#This Row],[Indem CP]]*_xlpm.taux,IF(_xlpm.csp,TPersonnel[[#This Row],[Indem CP]]*_xlpm.taux,(TPersonnel[[#This Row],[Indem Préavis Brut]]+TPersonnel[[#This Row],[Indem CP]])*_xlpm.taux)))) -> 0 | AR22: =TPersonnel[[#This Row],[TOTAL INDEM]]+TPersonnel[[#This Row],[Indem Préavis Brut]]+TPersonnel[[#This Row],[Indem CP]]+TPersonnel[[#This Row],[COÛT Charges Patronales]] -> 0
A23: 2774 | B23: Non | C23: BOUDALI | D23: Ouari | E23: VALENCE | F23: Conducteur PL | G23: CDI | H23: Ouvrier | I23: 138M | J23: H | K23: 44480 | L23: 44480 | M23: 28742 | N23: 2453.29 | P23: 24.58 | Q23: =IF(UPPER(B23)="OUI",'📈 Dashboard'!$B$37,"") | R23: =MAX(N23,O23/12) -> 2453.29 | S23: 3089.9 | T23: =IF(L23="",(TODAY()-K23)/365.25,MAX((TODAY()-K23)/365.25,(TODAY()-L23)/365.25)) -> 4.4271047 | U23: =IF(M23="","",(TODAY()-M23)/365.25) -> 47.5154 | V23: =N23*12 -> 29439.48 | W23: =IF(H23="Cadre",3,IF(H23="Haute maitrise",2,IF(OR(H23="Agent Maitrise",H23="Agent de maitrise"),IF(T23<2/12,0,IF(T23<2,1,2)),IF(OR(H23="Ouvrier"),IF(T23<6/12,1/4,IF(T23<2,1,2)),IF(OR(H23="Employe",H23="Employé"),IF(T23<1/12,0,IF(T23<2,1,2)),2))))) -> 2 | X23: =IF(Q23="",T23,(Q23-K23)/365.25) -> 4.4271047 | AG23: =IF(TPersonnel[[#This Row],[Fonction à supprimer]]="NON",0,IF(TPersonnel[[#This Row],[Ancienneté (ans) à la date théorique de sortie]]<0.67,0,IF(TPersonnel[[#This Row],[Ancienneté (ans) à la date théorique de sortie]]<=10,TPersonnel[[#This Row],[Ancienneté (ans) à la date théorique de sortie]]*TPersonnel[[#This Row],[Salaire Brut de référence]]/4,(10*TPersonnel[[#This Row],[Salaire Brut de référence]]/4+(TPersonnel[[#This Row],[Ancienneté (ans) à la date théorique de sortie]]-10)*TPersonnel[[#This Row],[Salaire Brut de référence]]/3)))) -> 0 | AH23: =IF(UPPER(TPersonnel[[#This Row],[Fonction à supprimer]])="NON",0,IF(TPersonnel[[#This Row],[Ancienneté (ans) à la date théorique de sortie]]<1,0,IF(OR(TPersonnel[[#This Row],[Catégorie]]="Ouvrier",TPersonnel[[#This Row],[Catégorie]]="Employe",TPersonnel[[#This Row],[Catégorie]]="Employé"),IF(TPersonnel[[#This Row],[Ancienneté (ans) à la date théorique de sortie]]<3,TPersonnel[[#This Row],[Ancienneté (ans) à la date théorique de sortie]]*TPersonnel[[#This Row],[Salaire Brut de référence]]/10,TPersonnel[[#This Row],[Ancienneté (ans) à la date théorique de sortie]]*TPersonnel[[#This Row],[Salaire Brut de référence]]*2/10),IF(OR(TPersonnel[[#This Row],[Catégorie]]="Agent Maitrise",TPersonnel[[#This Row],[Catégorie]]="Agent de maitrise",TPersonnel[[#This Row],[Catégorie]]="Haute maitrise"),IF(TPersonnel[[#This Row],[Ancienneté (ans) à la date théorique de sortie]]<3,TPersonnel[[#This Row],[Ancienneté (ans) à la date théorique de sortie]]*TPersonnel[[#This Row],[Salaire Brut de référence]]/10,TPersonnel[[#This Row],[Ancienneté (ans) à la date théorique de sortie]]*TPersonnel[[#This Row],[Salaire Brut de référence]]*3/10),IF(TPersonnel[[#This Row],[Catégorie]]="Cadre",IF(TPersonnel[[#This Row],[Ancienneté (ans) à la date théorique de sortie]]<3,0,TPersonnel[[#This Row],[Ancienneté (ans) à la date théorique de sortie]]*TPersonnel[[#This Row],[Salaire Brut de référence]]*4/10),0))))) -> 0 | AI23: =IF(TPersonnel[[#This Row],[INDEM LÉGALE]]=0,"",IF(TPersonnel[[#This Row],[INDEM LÉGALE]]>TPersonnel[[#This Row],[INDEM CONV.]],"LEGAL","CONVENTIONNEL")) | AJ23: =MAX(TPersonnel[[#This Row],[INDEM LÉGALE]],TPersonnel[[#This Row],[INDEM CONV.]]) -> 0 | AK23: =TPersonnel[[#This Row],[INDEM RETENUE]]*'⚙️ Parametres'!$B$5 -> 0 | AL23: =TPersonnel[[#This Row],[INDEM RETENUE]]+TPersonnel[[#This Row],[Majoration PSE]] -> 0 | AM23: =IF(UPPER(TPersonnel[[#This Row],[Fonction à supprimer]])="NON",0,IF(OR(TPersonnel[[#This Row],[Catégorie]]="Cadre"),3,IF(TPersonnel[[#This Row],[Catégorie]]="Haute maitrise",2,IF(OR(TPersonnel[[#This Row],[Catégorie]]="Agent Maitrise",TPersonnel[[#This Row],[Catégorie]]="Agent de maitrise"),IF(TPersonnel[[#This Row],[Ancienneté (ans) à la date théorique de sortie]]<2/12,0,IF(TPersonnel[[#This Row],[Ancienneté (ans) à la date théorique de sortie]]<2,1,2)),IF(OR(TPersonnel[[#This Row],[Catégorie]]="Ouvrier",TPersonnel[[#This Row],[Catégorie]]="Employe",TPersonnel[[#This Row],[Catégorie]]="Employé"),IF(TPersonnel[[#This Row],[Ancienneté (ans) à la date théorique de sortie]]<6/12,IF(TPersonnel[[#This Row],[Catégorie]]="Ouvrier",1/4,IF(TPersonnel[[#This Row],[Ancienneté (ans) à la date théorique de sortie]]<1/12,0,1)),IF(TPersonnel[[#This Row],[Ancienneté (ans) à la date théorique de sortie]]<2,1,2)),2))))) -> 0 | AN23: =IF(UPPER(TPersonnel[[#This Row],[Fonction à supprimer]])="NON",0,TPersonnel[[#This Row],[Préavis Calc (mois)]]*TPersonnel[[#This Row],[Salaire Brut de référence]]) -> 0 | AO23: =IF(TPersonnel[[#This Row],[Fonction à supprimer]]="NON",0,TPersonnel[[#This Row],[Nb CP Acquis]]+TPersonnel[[#This Row],[Préavis Calc (mois)]]*2.08) -> 0 | AP23: =TPersonnel[[#This Row],[CP Calc (jrs)]]*TPersonnel[[#This Row],[Salaire Brut de référence]]/21.67 -> 0 | AQ23: =IF(UPPER(TPersonnel[[#This Row],[Fonction à supprimer]])="NON",0,_xlfn.LET(_xlpm.taux,IF(TPersonnel[[#This Row],[Catégorie]]="Ouvrier",'📈 Dashboard'!$B$32,IF(TPersonnel[[#This Row],[Catégorie]]="Cadre",'📈 Dashboard'!$B$34,'📈 Dashboard'!$B$33)),_xlpm.csp,UPPER(TPersonnel[[#This Row],[CSP (contrat de sécurisation professionnel)]])="OUI",IF(AND(_xlpm.csp,TPersonnel[[#This Row],[Ancienneté (ans) à la date théorique de sortie]]>=1),MIN(TPersonnel[[#This Row],[Préavis Calc (mois)]],3)*TPersonnel[[#This Row],[Salaire Brut de référence]]*(_xlpm.taux+'⚙️ Parametres'!$B$11)+IF(TPersonnel[[#This Row],[Préavis Calc (mois)]]>3,(TPersonnel[[#This Row],[Préavis Calc (mois)]]-3)*TPersonnel[[#This Row],[Salaire Brut de référence]]*_xlpm.taux,0)+TPersonnel[[#This Row],[Indem CP]]*_xlpm.taux,IF(_xlpm.csp,TPersonnel[[#This Row],[Indem CP]]*_xlpm.taux,(TPersonnel[[#This Row],[Indem Préavis Brut]]+TPersonnel[[#This Row],[Indem CP]])*_xlpm.taux)))) -> 0 | AR23: =TPersonnel[[#This Row],[TOTAL INDEM]]+TPersonnel[[#This Row],[Indem Préavis Brut]]+TPersonnel[[#This Row],[Indem CP]]+TPersonnel[[#This Row],[COÛT Charges Patronales]] -> 0
A24: 2782 | B24: Non | C24: DUMIOT | D24: Julien | E24: ROGNAC | F24: Conducteur PL | G24: CDI | H24: Ouvrier | I24: 138M | J24: H | K24: 44867 | L24: 44867 | M24: 28437 | N24: 2303.26 | P24: 0.08 | Q24: =IF(UPPER(B24)="OUI",'📈 Dashboard'!$B$37,"") | R24: =MAX(N24,O24/12) -> 2303.26 | S24: 9.35 | T24: =IF(L24="",(TODAY()-K24)/365.25,MAX((TODAY()-K24)/365.25,(TODAY()-L24)/365.25)) -> 3.3675565 | U24: =IF(M24="","",(TODAY()-M24)/365.25) -> 48.350445 | V24: =N24*12 -> 27639.12 | W24: =IF(H24="Cadre",3,IF(H24="Haute maitrise",2,IF(OR(H24="Agent Maitrise",H24="Agent de maitrise"),IF(T24<2/12,0,IF(T24<2,1,2)),IF(OR(H24="Ouvrier"),IF(T24<6/12,1/4,IF(T24<2,1,2)),IF(OR(H24="Employe",H24="Employé"),IF(T24<1/12,0,IF(T24<2,1,2)),2))))) -> 2 | X24: =IF(Q24="",T24,(Q24-K24)/365.25) -> 3.3675565 | AG24: =IF(TPersonnel[[#This Row],[Fonction à supprimer]]="NON",0,IF(TPersonnel[[#This Row],[Ancienneté (ans) à la date théorique de sortie]]<0.67,0,IF(TPersonnel[[#This Row],[Ancienneté (ans) à la date théorique de sortie]]<=10,TPersonnel[[#This Row],[Ancienneté (ans) à la date théorique de sortie]]*TPersonnel[[#This Row],[Salaire Brut de référence]]/4,(10*TPersonnel[[#This Row],[Salaire Brut de référence]]/4+(TPersonnel[[#This Row],[Ancienneté (ans) à la date théorique de sortie]]-10)*TPersonnel[[#This Row],[Salaire Brut de référence]]/3)))) -> 0 | AH24: =IF(UPPER(TPersonnel[[#This Row],[Fonction à supprimer]])="NON",0,IF(TPersonnel[[#This Row],[Ancienneté (ans) à la date théorique de sortie]]<1,0,IF(OR(TPersonnel[[#This Row],[Catégorie]]="Ouvrier",TPersonnel[[#This Row],[Catégorie]]="Employe",TPersonnel[[#This Row],[Catégorie]]="Employé"),IF(TPersonnel[[#This Row],[Ancienneté (ans) à la date théorique de sortie]]<3,TPersonnel[[#This Row],[Ancienneté (ans) à la date théorique de sortie]]*TPersonnel[[#This Row],[Salaire Brut de référence]]/10,TPersonnel[[#This Row],[Ancienneté (ans) à la date théorique de sortie]]*TPersonnel[[#This Row],[Salaire Brut de référence]]*2/10),IF(OR(TPersonnel[[#This Row],[Catégorie]]="Agent Maitrise",TPersonnel[[#This Row],[Catégorie]]="Agent de maitrise",TPersonnel[[#This Row],[Catégorie]]="Haute maitrise"),IF(TPersonnel[[#This Row],[Ancienneté (ans) à la date théorique de sortie]]<3,TPersonnel[[#This Row],[Ancienneté (ans) à la date théorique de sortie]]*TPersonnel[[#This Row],[Salaire Brut de référence]]/10,TPersonnel[[#This Row],[Ancienneté (ans) à la date théorique de sortie]]*TPersonnel[[#This Row],[Salaire Brut de référence]]*3/10),IF(TPersonnel[[#This Row],[Catégorie]]="Cadre",IF(TPersonnel[[#This Row],[Ancienneté (ans) à la date théorique de sortie]]<3,0,TPersonnel[[#This Row],[Ancienneté (ans) à la date théorique de sortie]]*TPersonnel[[#This Row],[Salaire Brut de référence]]*4/10),0))))) -> 0 | AI24: =IF(TPersonnel[[#This Row],[INDEM LÉGALE]]=0,"",IF(TPersonnel[[#This Row],[INDEM LÉGALE]]>TPersonnel[[#This Row],[INDEM CONV.]],"LEGAL","CONVENTIONNEL")) | AJ24: =MAX(TPersonnel[[#This Row],[INDEM LÉGALE]],TPersonnel[[#This Row],[INDEM CONV.]]) -> 0 | AK24: =TPersonnel[[#This Row],[INDEM RETENUE]]*'⚙️ Parametres'!$B$5 -> 0 | AL24: =TPersonnel[[#This Row],[INDEM RETENUE]]+TPersonnel[[#This Row],[Majoration PSE]] -> 0 | AM24: =IF(UPPER(TPersonnel[[#This Row],[Fonction à supprimer]])="NON",0,IF(OR(TPersonnel[[#This Row],[Catégorie]]="Cadre"),3,IF(TPersonnel[[#This Row],[Catégorie]]="Haute maitrise",2,IF(OR(TPersonnel[[#This Row],[Catégorie]]="Agent Maitrise",TPersonnel[[#This Row],[Catégorie]]="Agent de maitrise"),IF(TPersonnel[[#This Row],[Ancienneté (ans) à la date théorique de sortie]]<2/12,0,IF(TPersonnel[[#This Row],[Ancienneté (ans) à la date théorique de sortie]]<2,1,2)),IF(OR(TPersonnel[[#This Row],[Catégorie]]="Ouvrier",TPersonnel[[#This Row],[Catégorie]]="Employe",TPersonnel[[#This Row],[Catégorie]]="Employé"),IF(TPersonnel[[#This Row],[Ancienneté (ans) à la date théorique de sortie]]<6/12,IF(TPersonnel[[#This Row],[Catégorie]]="Ouvrier",1/4,IF(TPersonnel[[#This Row],[Ancienneté (ans) à la date théorique de sortie]]<1/12,0,1)),IF(TPersonnel[[#This Row],[Ancienneté (ans) à la date théorique de sortie]]<2,1,2)),2))))) -> 0 | AN24: =IF(UPPER(TPersonnel[[#This Row],[Fonction à supprimer]])="NON",0,TPersonnel[[#This Row],[Préavis Calc (mois)]]*TPersonnel[[#This Row],[Salaire Brut de référence]]) -> 0 | AO24: =IF(TPersonnel[[#This Row],[Fonction à supprimer]]="NON",0,TPersonnel[[#This Row],[Nb CP Acquis]]+TPersonnel[[#This Row],[Préavis Calc (mois)]]*2.08) -> 0 | AP24: =TPersonnel[[#This Row],[CP Calc (jrs)]]*TPersonnel[[#This Row],[Salaire Brut de référence]]/21.67 -> 0 | AQ24: =IF(UPPER(TPersonnel[[#This Row],[Fonction à supprimer]])="NON",0,_xlfn.LET(_xlpm.taux,IF(TPersonnel[[#This Row],[Catégorie]]="Ouvrier",'📈 Dashboard'!$B$32,IF(TPersonnel[[#This Row],[Catégorie]]="Cadre",'📈 Dashboard'!$B$34,'📈 Dashboard'!$B$33)),_xlpm.csp,UPPER(TPersonnel[[#This Row],[CSP (contrat de sécurisation professionnel)]])="OUI",IF(AND(_xlpm.csp,TPersonnel[[#This Row],[Ancienneté (ans) à la date théorique de sortie]]>=1),MIN(TPersonnel[[#This Row],[Préavis Calc (mois)]],3)*TPersonnel[[#This Row],[Salaire Brut de référence]]*(_xlpm.taux+'⚙️ Parametres'!$B$11)+IF(TPersonnel[[#This Row],[Préavis Calc (mois)]]>3,(TPersonnel[[#This Row],[Préavis Calc (mois)]]-3)*TPersonnel[[#This Row],[Salaire Brut de référence]]*_xlpm.taux,0)+TPersonnel[[#This Row],[Indem CP]]*_xlpm.taux,IF(_xlpm.csp,TPersonnel[[#This Row],[Indem CP]]*_xlpm.taux,(TPersonnel[[#This Row],[Indem Préavis Brut]]+TPersonnel[[#This Row],[Indem CP]])*_xlpm.taux)))) -> 0 | AR24: =TPersonnel[[#This Row],[TOTAL INDEM]]+TPersonnel[[#This Row],[Indem Préavis Brut]]+TPersonnel[[#This Row],[Indem CP]]+TPersonnel[[#This Row],[COÛT Charges Patronales]] -> 0
A25: 2784 | B25: Non | C25: EGLAINE | D25: Florent | E25: VALENCE | F25: Chauffeur PL | G25: CDI | H25: Ouvrier | I25: 138M | J25: H | K25: 45027 | L25: 45027 | M25: 32534 | N25: 2288.84 | P25: -4.42 | Q25: =IF(UPPER(B25)="OUI",'📈 Dashboard'!$B$37,"") | R25: =MAX(N25,O25/12) -> 2288.84 | S25: -437.27 | T25: =IF(L25="",(TODAY()-K25)/365.25,MAX((TODAY()-K25)/365.25,(TODAY()-L25)/365.25)) -> 2.9295003 | U25: =IF(M25="","",(TODAY()-M25)/365.25) -> 37.13347 | V25: =N25*12 -> 27466.08 | W25: =IF(H25="Cadre",3,IF(H25="Haute maitrise",2,IF(OR(H25="Agent Maitrise",H25="Agent de maitrise"),IF(T25<2/12,0,IF(T25<2,1,2)),IF(OR(H25="Ouvrier"),IF(T25<6/12,1/4,IF(T25<2,1,2)),IF(OR(H25="Employe",H25="Employé"),IF(T25<1/12,0,IF(T25<2,1,2)),2))))) -> 2 | X25: =IF(Q25="",T25,(Q25-K25)/365.25) -> 2.9295003 | AG25: =IF(TPersonnel[[#This Row],[Fonction à supprimer]]="NON",0,IF(TPersonnel[[#This Row],[Ancienneté (ans) à la date théorique de sortie]]<0.67,0,IF(TPersonnel[[#This Row],[Ancienneté (ans) à la date théorique de sortie]]<=10,TPersonnel[[#This Row],[Ancienneté (ans) à la date théorique de sortie]]*TPersonnel[[#This Row],[Salaire Brut de référence]]/4,(10*TPersonnel[[#This Row],[Salaire Brut de référence]]/4+(TPersonnel[[#This Row],[Ancienneté (ans) à la date théorique de sortie]]-10)*TPersonnel[[#This Row],[Salaire Brut de référence]]/3)))) -> 0 | AH25: =IF(UPPER(TPersonnel[[#This Row],[Fonction à supprimer]])="NON",0,IF(TPersonnel[[#This Row],[Ancienneté (ans) à la date théorique de sortie]]<1,0,IF(OR(TPersonnel[[#This Row],[Catégorie]]="Ouvrier",TPersonnel[[#This Row],[Catégorie]]="Employe",TPersonnel[[#This Row],[Catégorie]]="Employé"),IF(TPersonnel[[#This Row],[Ancienneté (ans) à la date théorique de sortie]]<3,TPersonnel[[#This Row],[Ancienneté (ans) à la date théorique de sortie]]*TPersonnel[[#This Row],[Salaire Brut de référence]]/10,TPersonnel[[#This Row],[Ancienneté (ans) à la date théorique de sortie]]*TPersonnel[[#This Row],[Salaire Brut de référence]]*2/10),IF(OR(TPersonnel[[#This Row],[Catégorie]]="Agent Maitrise",TPersonnel[[#This Row],[Catégorie]]="Agent de maitrise",TPersonnel[[#This Row],[Catégorie]]="Haute maitrise"),IF(TPersonnel[[#This Row],[Ancienneté (ans) à la date théorique de sortie]]<3,TPersonnel[[#This Row],[Ancienneté (ans) à la date théorique de sortie]]*TPersonnel[[#This Row],[Salaire Brut de référence]]/10,TPersonnel[[#This Row],[Ancienneté (ans) à la date théorique de sortie]]*TPersonnel[[#This Row],[Salaire Brut de référence]]*3/10),IF(TPersonnel[[#This Row],[Catégorie]]="Cadre",IF(TPersonnel[[#This Row],[Ancienneté (ans) à la date théorique de sortie]]<3,0,TPersonnel[[#This Row],[Ancienneté (ans) à la date théorique de sortie]]*TPersonnel[[#This Row],[Salaire Brut de référence]]*4/10),0))))) -> 0 | AI25: =IF(TPersonnel[[#This Row],[INDEM LÉGALE]]=0,"",IF(TPersonnel[[#This Row],[INDEM LÉGALE]]>TPersonnel[[#This Row],[INDEM CONV.]],"LEGAL","CONVENTIONNEL")) | AJ25: =MAX(TPersonnel[[#This Row],[INDEM LÉGALE]],TPersonnel[[#This Row],[INDEM CONV.]]) -> 0 | AK25: =TPersonnel[[#This Row],[INDEM RETENUE]]*'⚙️ Parametres'!$B$5 -> 0 | AL25: =TPersonnel[[#This Row],[INDEM RETENUE]]+TPersonnel[[#This Row],[Majoration PSE]] -> 0 | AM25: =IF(UPPER(TPersonnel[[#This Row],[Fonction à supprimer]])="NON",0,IF(OR(TPersonnel[[#This Row],[Catégorie]]="Cadre"),3,IF(TPersonnel[[#This Row],[Catégorie]]="Haute maitrise",2,IF(OR(TPersonnel[[#This Row],[Catégorie]]="Agent Maitrise",TPersonnel[[#This Row],[Catégorie]]="Agent de maitrise"),IF(TPersonnel[[#This Row],[Ancienneté (ans) à la date théorique de sortie]]<2/12,0,IF(TPersonnel[[#This Row],[Ancienneté (ans) à la date théorique de sortie]]<2,1,2)),IF(OR(TPersonnel[[#This Row],[Catégorie]]="Ouvrier",TPersonnel[[#This Row],[Catégorie]]="Employe",TPersonnel[[#This Row],[Catégorie]]="Employé"),IF(TPersonnel[[#This Row],[Ancienneté (ans) à la date théorique de sortie]]<6/12,IF(TPersonnel[[#This Row],[Catégorie]]="Ouvrier",1/4,IF(TPersonnel[[#This Row],[Ancienneté (ans) à la date théorique de sortie]]<1/12,0,1)),IF(TPersonnel[[#This Row],[Ancienneté (ans) à la date théorique de sortie]]<2,1,2)),2))))) -> 0 | AN25: =IF(UPPER(TPersonnel[[#This Row],[Fonction à supprimer]])="NON",0,TPersonnel[[#This Row],[Préavis Calc (mois)]]*TPersonnel[[#This Row],[Salaire Brut de référence]]) -> 0 | AO25: =IF(TPersonnel[[#This Row],[Fonction à supprimer]]="NON",0,TPersonnel[[#This Row],[Nb CP Acquis]]+TPersonnel[[#This Row],[Préavis Calc (mois)]]*2.08) -> 0 | AP25: =TPersonnel[[#This Row],[CP Calc (jrs)]]*TPersonnel[[#This Row],[Salaire Brut de référence]]/21.67 -> 0 | AQ25: =IF(UPPER(TPersonnel[[#This Row],[Fonction à supprimer]])="NON",0,_xlfn.LET(_xlpm.taux,IF(TPersonnel[[#This Row],[Catégorie]]="Ouvrier",'📈 Dashboard'!$B$32,IF(TPersonnel[[#This Row],[Catégorie]]="Cadre",'📈 Dashboard'!$B$34,'📈 Dashboard'!$B$33)),_xlpm.csp,UPPER(TPersonnel[[#This Row],[CSP (contrat de sécurisation professionnel)]])="OUI",IF(AND(_xlpm.csp,TPersonnel[[#This Row],[Ancienneté (ans) à la date théorique de sortie]]>=1),MIN(TPersonnel[[#This Row],[Préavis Calc (mois)]],3)*TPersonnel[[#This Row],[Salaire Brut de référence]]*(_xlpm.taux+'⚙️ Parametres'!$B$11)+IF(TPersonnel[[#This Row],[Préavis Calc (mois)]]>3,(TPersonnel[[#This Row],[Préavis Calc (mois)]]-3)*TPersonnel[[#This Row],[Salaire Brut de référence]]*_xlpm.taux,0)+TPersonnel[[#This Row],[Indem CP]]*_xlpm.taux,IF(_xlpm.csp,TPersonnel[[#This Row],[Indem CP]]*_xlpm.taux,(TPersonnel[[#This Row],[Indem Préavis Brut]]+TPersonnel[[#This Row],[Indem CP]])*_xlpm.taux)))) -> 0 | AR25: =TPersonnel[[#This Row],[TOTAL INDEM]]+TPersonnel[[#This Row],[Indem Préavis Brut]]+TPersonnel[[#This Row],[Indem CP]]+TPersonnel[[#This Row],[COÛT Charges Patronales]] -> 0
A26: 2789 | B26: Non | C26: DJEBBAR | D26: Fettah | E26: PUSIGNAN | F26: Chef de quai | G26: CDI | H26: Ouvrier | I26: 150M | J26: H | K26: 45201 | L26: 45201 | M26: 31247 | N26: 2836.9 | P26: 18.58 | Q26: =IF(UPPER(B26)="OUI",'📈 Dashboard'!$B$37,"") | R26: =MAX(N26,O26/12) -> 2836.9 | S26: 2508.63 | T26: =IF(L26="",(TODAY()-K26)/365.25,MAX((TODAY()-K26)/365.25,(TODAY()-L26)/365.25)) -> 2.4531143 | U26: =IF(M26="","",(TODAY()-M26)/365.25) -> 40.657084 | V26: =N26*12 -> 34042.8 | W26: =IF(H26="Cadre",3,IF(H26="Haute maitrise",2,IF(OR(H26="Agent Maitrise",H26="Agent de maitrise"),IF(T26<2/12,0,IF(T26<2,1,2)),IF(OR(H26="Ouvrier"),IF(T26<6/12,1/4,IF(T26<2,1,2)),IF(OR(H26="Employe",H26="Employé"),IF(T26<1/12,0,IF(T26<2,1,2)),2))))) -> 2 | X26: =IF(Q26="",T26,(Q26-K26)/365.25) -> 2.4531143 | AG26: =IF(TPersonnel[[#This Row],[Fonction à supprimer]]="NON",0,IF(TPersonnel[[#This Row],[Ancienneté (ans) à la date théorique de sortie]]<0.67,0,IF(TPersonnel[[#This Row],[Ancienneté (ans) à la date théorique de sortie]]<=10,TPersonnel[[#This Row],[Ancienneté (ans) à la date théorique de sortie]]*TPersonnel[[#This Row],[Salaire Brut de référence]]/4,(10*TPersonnel[[#This Row],[Salaire Brut de référence]]/4+(TPersonnel[[#This Row],[Ancienneté (ans) à la date théorique de sortie]]-10)*TPersonnel[[#This Row],[Salaire Brut de référence]]/3)))) -> 0 | AH26: =IF(UPPER(TPersonnel[[#This Row],[Fonction à supprimer]])="NON",0,IF(TPersonnel[[#This Row],[Ancienneté (ans) à la date théorique de sortie]]<1,0,IF(OR(TPersonnel[[#This Row],[Catégorie]]="Ouvrier",TPersonnel[[#This Row],[Catégorie]]="Employe",TPersonnel[[#This Row],[Catégorie]]="Employé"),IF(TPersonnel[[#This Row],[Ancienneté (ans) à la date théorique de sortie]]<3,TPersonnel[[#This Row],[Ancienneté (ans) à la date théorique de sortie]]*TPersonnel[[#This Row],[Salaire Brut de référence]]/10,TPersonnel[[#This Row],[Ancienneté (ans) à la date théorique de sortie]]*TPersonnel[[#This Row],[Salaire Brut de référence]]*2/10),IF(OR(TPersonnel[[#This Row],[Catégorie]]="Agent Maitrise",TPersonnel[[#This Row],[Catégorie]]="Agent de maitrise",TPersonnel[[#This Row],[Catégorie]]="Haute maitrise"),IF(TPersonnel[[#This Row],[Ancienneté (ans) à la date théorique de sortie]]<3,TPersonnel[[#This Row],[Ancienneté (ans) à la date théorique de sortie]]*TPersonnel[[#This Row],[Salaire Brut de référence]]/10,TPersonnel[[#This Row],[Ancienneté (ans) à la date théorique de sortie]]*TPersonnel[[#This Row],[Salaire Brut de référence]]*3/10),IF(TPersonnel[[#This Row],[Catégorie]]="Cadre",IF(TPersonnel[[#This Row],[Ancienneté (ans) à la date théorique de sortie]]<3,0,TPersonnel[[#This Row],[Ancienneté (ans) à la date théorique de sortie]]*TPersonnel[[#This Row],[Salaire Brut de référence]]*4/10),0))))) -> 0 | AI26: =IF(TPersonnel[[#This Row],[INDEM LÉGALE]]=0,"",IF(TPersonnel[[#This Row],[INDEM LÉGALE]]>TPersonnel[[#This Row],[INDEM CONV.]],"LEGAL","CONVENTIONNEL")) | AJ26: =MAX(TPersonnel[[#This Row],[INDEM LÉGALE]],TPersonnel[[#This Row],[INDEM CONV.]]) -> 0 | AK26: =TPersonnel[[#This Row],[INDEM RETENUE]]*'⚙️ Parametres'!$B$5 -> 0 | AL26: =TPersonnel[[#This Row],[INDEM RETENUE]]+TPersonnel[[#This Row],[Majoration PSE]] -> 0 | AM26: =IF(UPPER(TPersonnel[[#This Row],[Fonction à supprimer]])="NON",0,IF(OR(TPersonnel[[#This Row],[Catégorie]]="Cadre"),3,IF(TPersonnel[[#This Row],[Catégorie]]="Haute maitrise",2,IF(OR(TPersonnel[[#This Row],[Catégorie]]="Agent Maitrise",TPersonnel[[#This Row],[Catégorie]]="Agent de maitrise"),IF(TPersonnel[[#This Row],[Ancienneté (ans) à la date théorique de sortie]]<2/12,0,IF(TPersonnel[[#This Row],[Ancienneté (ans) à la date théorique de sortie]]<2,1,2)),IF(OR(TPersonnel[[#This Row],[Catégorie]]="Ouvrier",TPersonnel[[#This Row],[Catégorie]]="Employe",TPersonnel[[#This Row],[Catégorie]]="Employé"),IF(TPersonnel[[#This Row],[Ancienneté (ans) à la date théorique de sortie]]<6/12,IF(TPersonnel[[#This Row],[Catégorie]]="Ouvrier",1/4,IF(TPersonnel[[#This Row],[Ancienneté (ans) à la date théorique de sortie]]<1/12,0,1)),IF(TPersonnel[[#This Row],[Ancienneté (ans) à la date théorique de sortie]]<2,1,2)),2))))) -> 0 | AN26: =IF(UPPER(TPersonnel[[#This Row],[Fonction à supprimer]])="NON",0,TPersonnel[[#This Row],[Préavis Calc (mois)]]*TPersonnel[[#This Row],[Salaire Brut de référence]]) -> 0 | AO26: =IF(TPersonnel[[#This Row],[Fonction à supprimer]]="NON",0,TPersonnel[[#This Row],[Nb CP Acquis]]+TPersonnel[[#This Row],[Préavis Calc (mois)]]*2.08) -> 0 | AP26: =TPersonnel[[#This Row],[CP Calc (jrs)]]*TPersonnel[[#This Row],[Salaire Brut de référence]]/21.67 -> 0 | AQ26: =IF(UPPER(TPersonnel[[#This Row],[Fonction à supprimer]])="NON",0,_xlfn.LET(_xlpm.taux,IF(TPersonnel[[#This Row],[Catégorie]]="Ouvrier",'📈 Dashboard'!$B$32,IF(TPersonnel[[#This Row],[Catégorie]]="Cadre",'📈 Dashboard'!$B$34,'📈 Dashboard'!$B$33)),_xlpm.csp,UPPER(TPersonnel[[#This Row],[CSP (contrat de sécurisation professionnel)]])="OUI",IF(AND(_xlpm.csp,TPersonnel[[#This Row],[Ancienneté (ans) à la date théorique de sortie]]>=1),MIN(TPersonnel[[#This Row],[Préavis Calc (mois)]],3)*TPersonnel[[#This Row],[Salaire Brut de référence]]*(_xlpm.taux+'⚙️ Parametres'!$B$11)+IF(TPersonnel[[#This Row],[Préavis Calc (mois)]]>3,(TPersonnel[[#This Row],[Préavis Calc (mois)]]-3)*TPersonnel[[#This Row],[Salaire Brut de référence]]*_xlpm.taux,0)+TPersonnel[[#This Row],[Indem CP]]*_xlpm.taux,IF(_xlpm.csp,TPersonnel[[#This Row],[Indem CP]]*_xlpm.taux,(TPersonnel[[#This Row],[Indem Préavis Brut]]+TPersonnel[[#This Row],[Indem CP]])*_xlpm.taux)))) -> 0 | AR26: =TPersonnel[[#This Row],[TOTAL INDEM]]+TPersonnel[[#This Row],[Indem Préavis Brut]]+TPersonnel[[#This Row],[Indem CP]]+TPersonnel[[#This Row],[COÛT Charges Patronales]] -> 0
A27: 2791 | B27: Non | C27: AZCUE | D27: Georges | E27: VALENCE | F27: Conducteur PL | G27: CDI | H27: Ouvrier | I27: 138M | J27: H | K27: 45208 | L27: 45208 | M27: 25564 | N27: 2295.41 | P27: 9.58 | Q27: =IF(UPPER(B27)="OUI",'📈 Dashboard'!$B$37,"") | R27: =MAX(N27,O27/12) -> 2295.41 | S27: 1083.43 | T27: =IF(L27="",(TODAY()-K27)/365.25,MAX((TODAY()-K27)/365.25,(TODAY()-L27)/365.25)) -> 2.4339493 | U27: =IF(M27="","",(TODAY()-M27)/365.25) -> 56.21629 | V27: =N27*12 -> 27544.92 | W27: =IF(H27="Cadre",3,IF(H27="Haute maitrise",2,IF(OR(H27="Agent Maitrise",H27="Agent de maitrise"),IF(T27<2/12,0,IF(T27<2,1,2)),IF(OR(H27="Ouvrier"),IF(T27<6/12,1/4,IF(T27<2,1,2)),IF(OR(H27="Employe",H27="Employé"),IF(T27<1/12,0,IF(T27<2,1,2)),2))))) -> 2 | X27: =IF(Q27="",T27,(Q27-K27)/365.25) -> 2.4339493 | AG27: =IF(TPersonnel[[#This Row],[Fonction à supprimer]]="NON",0,IF(TPersonnel[[#This Row],[Ancienneté (ans) à la date théorique de sortie]]<0.67,0,IF(TPersonnel[[#This Row],[Ancienneté (ans) à la date théorique de sortie]]<=10,TPersonnel[[#This Row],[Ancienneté (ans) à la date théorique de sortie]]*TPersonnel[[#This Row],[Salaire Brut de référence]]/4,(10*TPersonnel[[#This Row],[Salaire Brut de référence]]/4+(TPersonnel[[#This Row],[Ancienneté (ans) à la date théorique de sortie]]-10)*TPersonnel[[#This Row],[Salaire Brut de référence]]/3)))) -> 0 | AH27: =IF(UPPER(TPersonnel[[#This Row],[Fonction à supprimer]])="NON",0,IF(TPersonnel[[#This Row],[Ancienneté (ans) à la date théorique de sortie]]<1,0,IF(OR(TPersonnel[[#This Row],[Catégorie]]="Ouvrier",TPersonnel[[#This Row],[Catégorie]]="Employe",TPersonnel[[#This Row],[Catégorie]]="Employé"),IF(TPersonnel[[#This Row],[Ancienneté (ans) à la date théorique de sortie]]<3,TPersonnel[[#This Row],[Ancienneté (ans) à la date théorique de sortie]]*TPersonnel[[#This Row],[Salaire Brut de référence]]/10,TPersonnel[[#This Row],[Ancienneté (ans) à la date théorique de sortie]]*TPersonnel[[#This Row],[Salaire Brut de référence]]*2/10),IF(OR(TPersonnel[[#This Row],[Catégorie]]="Agent Maitrise",TPersonnel[[#This Row],[Catégorie]]="Agent de maitrise",TPersonnel[[#This Row],[Catégorie]]="Haute maitrise"),IF(TPersonnel[[#This Row],[Ancienneté (ans) à la date théorique de sortie]]<3,TPersonnel[[#This Row],[Ancienneté (ans) à la date théorique de sortie]]*TPersonnel[[#This Row],[Salaire Brut de référence]]/10,TPersonnel[[#This Row],[Ancienneté (ans) à la date théorique de sortie]]*TPersonnel[[#This Row],[Salaire Brut de référence]]*3/10),IF(TPersonnel[[#This Row],[Catégorie]]="Cadre",IF(TPersonnel[[#This Row],[Ancienneté (ans) à la date théorique de sortie]]<3,0,TPersonnel[[#This Row],[Ancienneté (ans) à la date théorique de sortie]]*TPersonnel[[#This Row],[Salaire Brut de référence]]*4/10),0))))) -> 0 | AI27: =IF(TPersonnel[[#This Row],[INDEM LÉGALE]]=0,"",IF(TPersonnel[[#This Row],[INDEM LÉGALE]]>TPersonnel[[#This Row],[INDEM CONV.]],"LEGAL","CONVENTIONNEL")) | AJ27: =MAX(TPersonnel[[#This Row],[INDEM LÉGALE]],TPersonnel[[#This Row],[INDEM CONV.]]) -> 0 | AK27: =TPersonnel[[#This Row],[INDEM RETENUE]]*'⚙️ Parametres'!$B$5 -> 0 | AL27: =TPersonnel[[#This Row],[INDEM RETENUE]]+TPersonnel[[#This Row],[Majoration PSE]] -> 0 | AM27: =IF(UPPER(TPersonnel[[#This Row],[Fonction à supprimer]])="NON",0,IF(OR(TPersonnel[[#This Row],[Catégorie]]="Cadre"),3,IF(TPersonnel[[#This Row],[Catégorie]]="Haute maitrise",2,IF(OR(TPersonnel[[#This Row],[Catégorie]]="Agent Maitrise",TPersonnel[[#This Row],[Catégorie]]="Agent de maitrise"),IF(TPersonnel[[#This Row],[Ancienneté (ans) à la date théorique de sortie]]<2/12,0,IF(TPersonnel[[#This Row],[Ancienneté (ans) à la date théorique de sortie]]<2,1,2)),IF(OR(TPersonnel[[#This Row],[Catégorie]]="Ouvrier",TPersonnel[[#This Row],[Catégorie]]="Employe",TPersonnel[[#This Row],[Catégorie]]="Employé"),IF(TPersonnel[[#This Row],[Ancienneté (ans) à la date théorique de sortie]]<6/12,IF(TPersonnel[[#This Row],[Catégorie]]="Ouvrier",1/4,IF(TPersonnel[[#This Row],[Ancienneté (ans) à la date théorique de sortie]]<1/12,0,1)),IF(TPersonnel[[#This Row],[Ancienneté (ans) à la date théorique de sortie]]<2,1,2)),2))))) -> 0 | AN27: =IF(UPPER(TPersonnel[[#This Row],[Fonction à supprimer]])="NON",0,TPersonnel[[#This Row],[Préavis Calc (mois)]]*TPersonnel[[#This Row],[Salaire Brut de référence]]) -> 0 | AO27: =IF(TPersonnel[[#This Row],[Fonction à supprimer]]="NON",0,TPersonnel[[#This Row],[Nb CP Acquis]]+TPersonnel[[#This Row],[Préavis Calc (mois)]]*2.08) -> 0 | AP27: =TPersonnel[[#This Row],[CP Calc (jrs)]]*TPersonnel[[#This Row],[Salaire Brut de référence]]/21.67 -> 0 | AQ27: =IF(UPPER(TPersonnel[[#This Row],[Fonction à supprimer]])="NON",0,_xlfn.LET(_xlpm.taux,IF(TPersonnel[[#This Row],[Catégorie]]="Ouvrier",'📈 Dashboard'!$B$32,IF(TPersonnel[[#This Row],[Catégorie]]="Cadre",'📈 Dashboard'!$B$34,'📈 Dashboard'!$B$33)),_xlpm.csp,UPPER(TPersonnel[[#This Row],[CSP (contrat de sécurisation professionnel)]])="OUI",IF(AND(_xlpm.csp,TPersonnel[[#This Row],[Ancienneté (ans) à la date théorique de sortie]]>=1),MIN(TPersonnel[[#This Row],[Préavis Calc (mois)]],3)*TPersonnel[[#This Row],[Salaire Brut de référence]]*(_xlpm.taux+'⚙️ Parametres'!$B$11)+IF(TPersonnel[[#This Row],[Préavis Calc (mois)]]>3,(TPersonnel[[#This Row],[Préavis Calc (mois)]]-3)*TPersonnel[[#This Row],[Salaire Brut de référence]]*_xlpm.taux,0)+TPersonnel[[#This Row],[Indem CP]]*_xlpm.taux,IF(_xlpm.csp,TPersonnel[[#This Row],[Indem CP]]*_xlpm.taux,(TPersonnel[[#This Row],[Indem Préavis Brut]]+TPersonnel[[#This Row],[Indem CP]])*_xlpm.taux)))) -> 0 | AR27: =TPersonnel[[#This Row],[TOTAL INDEM]]+TPersonnel[[#This Row],[Indem Préavis Brut]]+TPersonnel[[#This Row],[Indem CP]]+TPersonnel[[#This Row],[COÛT Charges Patronales]] -> 0
A28: 2792 | B28: Non | C28: FOSSE | D28: Eva | E28: VALENCE | F28: Exploitante | G28: CDI | H28: Agent de maîtrise | I28: 150 | J28: F | K28: 45222 | L28: 45222 | M28: 35704 | N28: 2800 | P28: 27.58 | Q28: =IF(UPPER(B28)="OUI",'📈 Dashboard'!$B$37,"") | R28: =MAX(N28,O28/12) -> 2800 | S28: 3688.28 | T28: =IF(L28="",(TODAY()-K28)/365.25,MAX((TODAY()-K28)/365.25,(TODAY()-L28)/365.25)) -> 2.3956194 | U28: =IF(M28="","",(TODAY()-M28)/365.25) -> 28.454483 | V28: =N28*12 -> 33600 | W28: =IF(H28="Cadre",3,IF(H28="Haute maitrise",2,IF(OR(H28="Agent Maitrise",H28="Agent de maitrise"),IF(T28<2/12,0,IF(T28<2,1,2)),IF(OR(H28="Ouvrier"),IF(T28<6/12,1/4,IF(T28<2,1,2)),IF(OR(H28="Employe",H28="Employé"),IF(T28<1/12,0,IF(T28<2,1,2)),2))))) -> 2 | X28: =IF(Q28="",T28,(Q28-K28)/365.25) -> 2.3956194 | AG28: =IF(TPersonnel[[#This Row],[Fonction à supprimer]]="NON",0,IF(TPersonnel[[#This Row],[Ancienneté (ans) à la date théorique de sortie]]<0.67,0,IF(TPersonnel[[#This Row],[Ancienneté (ans) à la date théorique de sortie]]<=10,TPersonnel[[#This Row],[Ancienneté (ans) à la date théorique de sortie]]*TPersonnel[[#This Row],[Salaire Brut de référence]]/4,(10*TPersonnel[[#This Row],[Salaire Brut de référence]]/4+(TPersonnel[[#This Row],[Ancienneté (ans) à la date théorique de sortie]]-10)*TPersonnel[[#This Row],[Salaire Brut de référence]]/3)))) -> 0 | AH28: =IF(UPPER(TPersonnel[[#This Row],[Fonction à supprimer]])="NON",0,IF(TPersonnel[[#This Row],[Ancienneté (ans) à la date théorique de sortie]]<1,0,IF(OR(TPersonnel[[#This Row],[Catégorie]]="Ouvrier",TPersonnel[[#This Row],[Catégorie]]="Employe",TPersonnel[[#This Row],[Catégorie]]="Employé"),IF(TPersonnel[[#This Row],[Ancienneté (ans) à la date théorique de sortie]]<3,TPersonnel[[#This Row],[Ancienneté (ans) à la date théorique de sortie]]*TPersonnel[[#This Row],[Salaire Brut de référence]]/10,TPersonnel[[#This Row],[Ancienneté (ans) à la date théorique de sortie]]*TPersonnel[[#This Row],[Salaire Brut de référence]]*2/10),IF(OR(TPersonnel[[#This Row],[Catégorie]]="Agent Maitrise",TPersonnel[[#This Row],[Catégorie]]="Agent de maitrise",TPersonnel[[#This Row],[Catégorie]]="Haute maitrise"),IF(TPersonnel[[#This Row],[Ancienneté (ans) à la date théorique de sortie]]<3,TPersonnel[[#This Row],[Ancienneté (ans) à la date théorique de sortie]]*TPersonnel[[#This Row],[Salaire Brut de référence]]/10,TPersonnel[[#This Row],[Ancienneté (ans) à la date théorique de sortie]]*TPersonnel[[#This Row],[Salaire Brut de référence]]*3/10),IF(TPersonnel[[#This Row],[Catégorie]]="Cadre",IF(TPersonnel[[#This Row],[Ancienneté (ans) à la date théorique de sortie]]<3,0,TPersonnel[[#This Row],[Ancienneté (ans) à la date théorique de sortie]]*TPersonnel[[#This Row],[Salaire Brut de référence]]*4/10),0))))) -> 0 | AI28: =IF(TPersonnel[[#This Row],[INDEM LÉGALE]]=0,"",IF(TPersonnel[[#This Row],[INDEM LÉGALE]]>TPersonnel[[#This Row],[INDEM CONV.]],"LEGAL","CONVENTIONNEL")) | AJ28: =MAX(TPersonnel[[#This Row],[INDEM LÉGALE]],TPersonnel[[#This Row],[INDEM CONV.]]) -> 0 | AK28: =TPersonnel[[#This Row],[INDEM RETENUE]]*'⚙️ Parametres'!$B$5 -> 0 | AL28: =TPersonnel[[#This Row],[INDEM RETENUE]]+TPersonnel[[#This Row],[Majoration PSE]] -> 0 | AM28: =IF(UPPER(TPersonnel[[#This Row],[Fonction à supprimer]])="NON",0,IF(OR(TPersonnel[[#This Row],[Catégorie]]="Cadre"),3,IF(TPersonnel[[#This Row],[Catégorie]]="Haute maitrise",2,IF(OR(TPersonnel[[#This Row],[Catégorie]]="Agent Maitrise",TPersonnel[[#This Row],[Catégorie]]="Agent de maitrise"),IF(TPersonnel[[#This Row],[Ancienneté (ans) à la date théorique de sortie]]<2/12,0,IF(TPersonnel[[#This Row],[Ancienneté (ans) à la date théorique de sortie]]<2,1,2)),IF(OR(TPersonnel[[#This Row],[Catégorie]]="Ouvrier",TPersonnel[[#This Row],[Catégorie]]="Employe",TPersonnel[[#This Row],[Catégorie]]="Employé"),IF(TPersonnel[[#This Row],[Ancienneté (ans) à la date théorique de sortie]]<6/12,IF(TPersonnel[[#This Row],[Catégorie]]="Ouvrier",1/4,IF(TPersonnel[[#This Row],[Ancienneté (ans) à la date théorique de sortie]]<1/12,0,1)),IF(TPersonnel[[#This Row],[Ancienneté (ans) à la date théorique de sortie]]<2,1,2)),2))))) -> 0 | AN28: =IF(UPPER(TPersonnel[[#This Row],[Fonction à supprimer]])="NON",0,TPersonnel[[#This Row],[Préavis Calc (mois)]]*TPersonnel[[#This Row],[Salaire Brut de référence]]) -> 0 | AO28: =IF(TPersonnel[[#This Row],[Fonction à supprimer]]="NON",0,TPersonnel[[#This Row],[Nb CP Acquis]]+TPersonnel[[#This Row],[Préavis Calc (mois)]]*2.08) -> 0 | AP28: =TPersonnel[[#This Row],[CP Calc (jrs)]]*TPersonnel[[#This Row],[Salaire Brut de référence]]/21.67 -> 0 | AQ28: =IF(UPPER(TPersonnel[[#This Row],[Fonction à supprimer]])="NON",0,_xlfn.LET(_xlpm.taux,IF(TPersonnel[[#This Row],[Catégorie]]="Ouvrier",'📈 Dashboard'!$B$32,IF(TPersonnel[[#This Row],[Catégorie]]="Cadre",'📈 Dashboard'!$B$34,'📈 Dashboard'!$B$33)),_xlpm.csp,UPPER(TPersonnel[[#This Row],[CSP (contrat de sécurisation professionnel)]])="OUI",IF(AND(_xlpm.csp,TPersonnel[[#This Row],[Ancienneté (ans) à la date théorique de sortie]]>=1),MIN(TPersonnel[[#This Row],[Préavis Calc (mois)]],3)*TPersonnel[[#This Row],[Salaire Brut de référence]]*(_xlpm.taux+'⚙️ Parametres'!$B$11)+IF(TPersonnel[[#This Row],[Préavis Calc (mois)]]>3,(TPersonnel[[#This Row],[Préavis Calc (mois)]]-3)*TPersonnel[[#This Row],[Salaire Brut de référence]]*_xlpm.taux,0)+TPersonnel[[#This Row],[Indem CP]]*_xlpm.taux,IF(_xlpm.csp,TPersonnel[[#This Row],[Indem CP]]*_xlpm.taux,(TPersonnel[[#This Row],[Indem Préavis Brut]]+TPersonnel[[#This Row],[Indem CP]])*_xlpm.taux)))) -> 0 | AR28: =TPersonnel[[#This Row],[TOTAL INDEM]]+TPersonnel[[#This Row],[Indem Préavis Brut]]+TPersonnel[[#This Row],[Indem CP]]+TPersonnel[[#This Row],[COÛT Charges Patronales]] -> 0
A29: 2793 | B29: Non | C29: JACQUOT | D29: Grégory | E29: PUSIGNAN | F29: Chef de quai | G29: CDI | H29: Ouvrier | I29: 150M | J29: H | K29: 45495 | L29: 45313 | M29: 36489 | N29: 2494.92 | P29: 10.08 | Q29: =IF(UPPER(B29)="OUI",'📈 Dashboard'!$B$37,"") | R29: =MAX(N29,O29/12) -> 2494.92 | S29: 1198.65 | T29: =IF(L29="",(TODAY()-K29)/365.25,MAX((TODAY()-K29)/365.25,(TODAY()-L29)/365.25)) -> 2.146475 | U29: =IF(M29="","",(TODAY()-M29)/365.25) -> 26.30527 | V29: =N29*12 -> 29939.04 | W29: =IF(H29="Cadre",3,IF(H29="Haute maitrise",2,IF(OR(H29="Agent Maitrise",H29="Agent de maitrise"),IF(T29<2/12,0,IF(T29<2,1,2)),IF(OR(H29="Ouvrier"),IF(T29<6/12,1/4,IF(T29<2,1,2)),IF(OR(H29="Employe",H29="Employé"),IF(T29<1/12,0,IF(T29<2,1,2)),2))))) -> 2 | X29: =IF(Q29="",T29,(Q29-K29)/365.25) -> 2.146475 | AG29: =IF(TPersonnel[[#This Row],[Fonction à supprimer]]="NON",0,IF(TPersonnel[[#This Row],[Ancienneté (ans) à la date théorique de sortie]]<0.67,0,IF(TPersonnel[[#This Row],[Ancienneté (ans) à la date théorique de sortie]]<=10,TPersonnel[[#This Row],[Ancienneté (ans) à la date théorique de sortie]]*TPersonnel[[#This Row],[Salaire Brut de référence]]/4,(10*TPersonnel[[#This Row],[Salaire Brut de référence]]/4+(TPersonnel[[#This Row],[Ancienneté (ans) à la date théorique de sortie]]-10)*TPersonnel[[#This Row],[Salaire Brut de référence]]/3)))) -> 0 | AH29: =IF(UPPER(TPersonnel[[#This Row],[Fonction à supprimer]])="NON",0,IF(TPersonnel[[#This Row],[Ancienneté (ans) à la date théorique de sortie]]<1,0,IF(OR(TPersonnel[[#This Row],[Catégorie]]="Ouvrier",TPersonnel[[#This Row],[Catégorie]]="Employe",TPersonnel[[#This Row],[Catégorie]]="Employé"),IF(TPersonnel[[#This Row],[Ancienneté (ans) à la date théorique de sortie]]<3,TPersonnel[[#This Row],[Ancienneté (ans) à la date théorique de sortie]]*TPersonnel[[#This Row],[Salaire Brut de référence]]/10,TPersonnel[[#This Row],[Ancienneté (ans) à la date théorique de sortie]]*TPersonnel[[#This Row],[Salaire Brut de référence]]*2/10),IF(OR(TPersonnel[[#This Row],[Catégorie]]="Agent Maitrise",TPersonnel[[#This Row],[Catégorie]]="Agent de maitrise",TPersonnel[[#This Row],[Catégorie]]="Haute maitrise"),IF(TPersonnel[[#This Row],[Ancienneté (ans) à la date théorique de sortie]]<3,TPersonnel[[#This Row],[Ancienneté (ans) à la date théorique de sortie]]*TPersonnel[[#This Row],[Salaire Brut de référence]]/10,TPersonnel[[#This Row],[Ancienneté (ans) à la date théorique de sortie]]*TPersonnel[[#This Row],[Salaire Brut de référence]]*3/10),IF(TPersonnel[[#This Row],[Catégorie]]="Cadre",IF(TPersonnel[[#This Row],[Ancienneté (ans) à la date théorique de sortie]]<3,0,TPersonnel[[#This Row],[Ancienneté (ans) à la date théorique de sortie]]*TPersonnel[[#This Row],[Salaire Brut de référence]]*4/10),0))))) -> 0 | AI29: =IF(TPersonnel[[#This Row],[INDEM LÉGALE]]=0,"",IF(TPersonnel[[#This Row],[INDEM LÉGALE]]>TPersonnel[[#This Row],[INDEM CONV.]],"LEGAL","CONVENTIONNEL")) | AJ29: =MAX(TPersonnel[[#This Row],[INDEM LÉGALE]],TPersonnel[[#This Row],[INDEM CONV.]]) -> 0 | AK29: =TPersonnel[[#This Row],[INDEM RETENUE]]*'⚙️ Parametres'!$B$5 -> 0 | AL29: =TPersonnel[[#This Row],[INDEM RETENUE]]+TPersonnel[[#This Row],[Majoration PSE]] -> 0 | AM29: =IF(UPPER(TPersonnel[[#This Row],[Fonction à supprimer]])="NON",0,IF(OR(TPersonnel[[#This Row],[Catégorie]]="Cadre"),3,IF(TPersonnel[[#This Row],[Catégorie]]="Haute maitrise",2,IF(OR(TPersonnel[[#This Row],[Catégorie]]="Agent Maitrise",TPersonnel[[#This Row],[Catégorie]]="Agent de maitrise"),IF(TPersonnel[[#This Row],[Ancienneté (ans) à la date théorique de sortie]]<2/12,0,IF(TPersonnel[[#This Row],[Ancienneté (ans) à la date théorique de sortie]]<2,1,2)),IF(OR(TPersonnel[[#This Row],[Catégorie]]="Ouvrier",TPersonnel[[#This Row],[Catégorie]]="Employe",TPersonnel[[#This Row],[Catégorie]]="Employé"),IF(TPersonnel[[#This Row],[Ancienneté (ans) à la date théorique de sortie]]<6/12,IF(TPersonnel[[#This Row],[Catégorie]]="Ouvrier",1/4,IF(TPersonnel[[#This Row],[Ancienneté (ans) à la date théorique de sortie]]<1/12,0,1)),IF(TPersonnel[[#This Row],[Ancienneté (ans) à la date théorique de sortie]]<2,1,2)),2))))) -> 0 | AN29: =IF(UPPER(TPersonnel[[#This Row],[Fonction à supprimer]])="NON",0,TPersonnel[[#This Row],[Préavis Calc (mois)]]*TPersonnel[[#This Row],[Salaire Brut de référence]]) -> 0 | AO29: =IF(TPersonnel[[#This Row],[Fonction à supprimer]]="NON",0,TPersonnel[[#This Row],[Nb CP Acquis]]+TPersonnel[[#This Row],[Préavis Calc (mois)]]*2.08) -> 0 | AP29: =TPersonnel[[#This Row],[CP Calc (jrs)]]*TPersonnel[[#This Row],[Salaire Brut de référence]]/21.67 -> 0 | AQ29: =IF(UPPER(TPersonnel[[#This Row],[Fonction à supprimer]])="NON",0,_xlfn.LET(_xlpm.taux,IF(TPersonnel[[#This Row],[Catégorie]]="Ouvrier",'📈 Dashboard'!$B$32,IF(TPersonnel[[#This Row],[Catégorie]]="Cadre",'📈 Dashboard'!$B$34,'📈 Dashboard'!$B$33)),_xlpm.csp,UPPER(TPersonnel[[#This Row],[CSP (contrat de sécurisation professionnel)]])="OUI",IF(AND(_xlpm.csp,TPersonnel[[#This Row],[Ancienneté (ans) à la date théorique de sortie]]>=1),MIN(TPersonnel[[#This Row],[Préavis Calc (mois)]],3)*TPersonnel[[#This Row],[Salaire Brut de référence]]*(_xlpm.taux+'⚙️ Parametres'!$B$11)+IF(TPersonnel[[#This Row],[Préavis Calc (mois)]]>3,(TPersonnel[[#This Row],[Préavis Calc (mois)]]-3)*TPersonnel[[#This Row],[Salaire Brut de référence]]*_xlpm.taux,0)+TPersonnel[[#This Row],[Indem CP]]*_xlpm.taux,IF(_xlpm.csp,TPersonnel[[#This Row],[Indem CP]]*_xlpm.taux,(TPersonnel[[#This Row],[Indem Préavis Brut]]+TPersonnel[[#This Row],[Indem CP]])*_xlpm.taux)))) -> 0 | AR29: =TPersonnel[[#This Row],[TOTAL INDEM]]+TPersonnel[[#This Row],[Indem Préavis Brut]]+TPersonnel[[#This Row],[Indem CP]]+TPersonnel[[#This Row],[COÛT Charges Patronales]] -> 0
A30: 2794 | B30: Non | C30: PENNACCHI | D30: Eric | E30: ROGNAC | F30: Conducteur PL | G30: CDI | H30: Ouvrier | I30: 138M | J30: H | K30: 45337 | L30: 45337 | M30: 26320 | N30: 2577.89 | P30: 2.08 | Q30: =IF(UPPER(B30)="OUI",'📈 Dashboard'!$B$37,"") | R30: =MAX(N30,O30/12) -> 2577.89 | S30: 258.63 | T30: =IF(L30="",(TODAY()-K30)/365.25,MAX((TODAY()-K30)/365.25,(TODAY()-L30)/365.25)) -> 2.0807666 | U30: =IF(M30="","",(TODAY()-M30)/365.25) -> 54.146475 | V30: =N30*12 -> 30934.68 | W30: =IF(H30="Cadre",3,IF(H30="Haute maitrise",2,IF(OR(H30="Agent Maitrise",H30="Agent de maitrise"),IF(T30<2/12,0,IF(T30<2,1,2)),IF(OR(H30="Ouvrier"),IF(T30<6/12,1/4,IF(T30<2,1,2)),IF(OR(H30="Employe",H30="Employé"),IF(T30<1/12,0,IF(T30<2,1,2)),2))))) -> 2 | X30: =IF(Q30="",T30,(Q30-K30)/365.25) -> 2.0807666 | AG30: =IF(TPersonnel[[#This Row],[Fonction à supprimer]]="NON",0,IF(TPersonnel[[#This Row],[Ancienneté (ans) à la date théorique de sortie]]<0.67,0,IF(TPersonnel[[#This Row],[Ancienneté (ans) à la date théorique de sortie]]<=10,TPersonnel[[#This Row],[Ancienneté (ans) à la date théorique de sortie]]*TPersonnel[[#This Row],[Salaire Brut de référence]]/4,(10*TPersonnel[[#This Row],[Salaire Brut de référence]]/4+(TPersonnel[[#This Row],[Ancienneté (ans) à la date théorique de sortie]]-10)*TPersonnel[[#This Row],[Salaire Brut de référence]]/3)))) -> 0 | AH30: =IF(UPPER(TPersonnel[[#This Row],[Fonction à supprimer]])="NON",0,IF(TPersonnel[[#This Row],[Ancienneté (ans) à la date théorique de sortie]]<1,0,IF(OR(TPersonnel[[#This Row],[Catégorie]]="Ouvrier",TPersonnel[[#This Row],[Catégorie]]="Employe",TPersonnel[[#This Row],[Catégorie]]="Employé"),IF(TPersonnel[[#This Row],[Ancienneté (ans) à la date théorique de sortie]]<3,TPersonnel[[#This Row],[Ancienneté (ans) à la date théorique de sortie]]*TPersonnel[[#This Row],[Salaire Brut de référence]]/10,TPersonnel[[#This Row],[Ancienneté (ans) à la date théorique de sortie]]*TPersonnel[[#This Row],[Salaire Brut de référence]]*2/10),IF(OR(TPersonnel[[#This Row],[Catégorie]]="Agent Maitrise",TPersonnel[[#This Row],[Catégorie]]="Agent de maitrise",TPersonnel[[#This Row],[Catégorie]]="Haute maitrise"),IF(TPersonnel[[#This Row],[Ancienneté (ans) à la date théorique de sortie]]<3,TPersonnel[[#This Row],[Ancienneté (ans) à la date théorique de sortie]]*TPersonnel[[#This Row],[Salaire Brut de référence]]/10,TPersonnel[[#This Row],[Ancienneté (ans) à la date théorique de sortie]]*TPersonnel[[#This Row],[Salaire Brut de référence]]*3/10),IF(TPersonnel[[#This Row],[Catégorie]]="Cadre",IF(TPersonnel[[#This Row],[Ancienneté (ans) à la date théorique de sortie]]<3,0,TPersonnel[[#This Row],[Ancienneté (ans) à la date théorique de sortie]]*TPersonnel[[#This Row],[Salaire Brut de référence]]*4/10),0))))) -> 0 | AI30: =IF(TPersonnel[[#This Row],[INDEM LÉGALE]]=0,"",IF(TPersonnel[[#This Row],[INDEM LÉGALE]]>TPersonnel[[#This Row],[INDEM CONV.]],"LEGAL","CONVENTIONNEL")) | AJ30: =MAX(TPersonnel[[#This Row],[INDEM LÉGALE]],TPersonnel[[#This Row],[INDEM CONV.]]) -> 0 | AK30: =TPersonnel[[#This Row],[INDEM RETENUE]]*'⚙️ Parametres'!$B$5 -> 0 | AL30: =TPersonnel[[#This Row],[INDEM RETENUE]]+TPersonnel[[#This Row],[Majoration PSE]] -> 0 | AM30: =IF(UPPER(TPersonnel[[#This Row],[Fonction à supprimer]])="NON",0,IF(OR(TPersonnel[[#This Row],[Catégorie]]="Cadre"),3,IF(TPersonnel[[#This Row],[Catégorie]]="Haute maitrise",2,IF(OR(TPersonnel[[#This Row],[Catégorie]]="Agent Maitrise",TPersonnel[[#This Row],[Catégorie]]="Agent de maitrise"),IF(TPersonnel[[#This Row],[Ancienneté (ans) à la date théorique de sortie]]<2/12,0,IF(TPersonnel[[#This Row],[Ancienneté (ans) à la date théorique de sortie]]<2,1,2)),IF(OR(TPersonnel[[#This Row],[Catégorie]]="Ouvrier",TPersonnel[[#This Row],[Catégorie]]="Employe",TPersonnel[[#This Row],[Catégorie]]="Employé"),IF(TPersonnel[[#This Row],[Ancienneté (ans) à la date théorique de sortie]]<6/12,IF(TPersonnel[[#This Row],[Catégorie]]="Ouvrier",1/4,IF(TPersonnel[[#This Row],[Ancienneté (ans) à la date théorique de sortie]]<1/12,0,1)),IF(TPersonnel[[#This Row],[Ancienneté (ans) à la date théorique de sortie]]<2,1,2)),2))))) -> 0 | AN30: =IF(UPPER(TPersonnel[[#This Row],[Fonction à supprimer]])="NON",0,TPersonnel[[#This Row],[Préavis Calc (mois)]]*TPersonnel[[#This Row],[Salaire Brut de référence]]) -> 0 | AO30: =IF(TPersonnel[[#This Row],[Fonction à supprimer]]="NON",0,TPersonnel[[#This Row],[Nb CP Acquis]]+TPersonnel[[#This Row],[Préavis Calc (mois)]]*2.08) -> 0 | AP30: =TPersonnel[[#This Row],[CP Calc (jrs)]]*TPersonnel[[#This Row],[Salaire Brut de référence]]/21.67 -> 0 | AQ30: =IF(UPPER(TPersonnel[[#This Row],[Fonction à supprimer]])="NON",0,_xlfn.LET(_xlpm.taux,IF(TPersonnel[[#This Row],[Catégorie]]="Ouvrier",'📈 Dashboard'!$B$32,IF(TPersonnel[[#This Row],[Catégorie]]="Cadre",'📈 Dashboard'!$B$34,'📈 Dashboard'!$B$33)),_xlpm.csp,UPPER(TPersonnel[[#This Row],[CSP (contrat de sécurisation professionnel)]])="OUI",IF(AND(_xlpm.csp,TPersonnel[[#This Row],[Ancienneté (ans) à la date théorique de sortie]]>=1),MIN(TPersonnel[[#This Row],[Préavis Calc (mois)]],3)*TPersonnel[[#This Row],[Salaire Brut de référence]]*(_xlpm.taux+'⚙️ Parametres'!$B$11)+IF(TPersonnel[[#This Row],[Préavis Calc (mois)]]>3,(TPersonnel[[#This Row],[Préavis Calc (mois)]]-3)*TPersonnel[[#This Row],[Salaire Brut de référence]]*_xlpm.taux,0)+TPersonnel[[#This Row],[Indem CP]]*_xlpm.taux,IF(_xlpm.csp,TPersonnel[[#This Row],[Indem CP]]*_xlpm.taux,(TPersonnel[[#This Row],[Indem Préavis Brut]]+TPersonnel[[#This Row],[Indem CP]])*_xlpm.taux)))) -> 0 | AR30: =TPersonnel[[#This Row],[TOTAL INDEM]]+TPersonnel[[#This Row],[Indem Préavis Brut]]+TPersonnel[[#This Row],[Indem CP]]+TPersonnel[[#This Row],[COÛT Charges Patronales]] -> 0
A31: 2797 | B31: Non | C31: BUJNOWSKYJ | D31: Sandrine née MOREL | E31: PUSIGNAN | F31: Assistante exploitation | G31: CDI | H31: Employé | I31: 125 | J31: F | K31: 45460 | L31: 45460 | M31: 26033 | N31: 2500 | P31: 8.08 | Q31: =IF(UPPER(B31)="OUI",'📈 Dashboard'!$B$37,"") | R31: =MAX(N31,O31/12) -> 2500 | S31: 969.99 | T31: =IF(L31="",(TODAY()-K31)/365.25,MAX((TODAY()-K31)/365.25,(TODAY()-L31)/365.25)) -> 1.744011 | U31: =IF(M31="","",(TODAY()-M31)/365.25) -> 54.932238 | V31: =N31*12 -> 30000 | W31: =IF(H31="Cadre",3,IF(H31="Haute maitrise",2,IF(OR(H31="Agent Maitrise",H31="Agent de maitrise"),IF(T31<2/12,0,IF(T31<2,1,2)),IF(OR(H31="Ouvrier"),IF(T31<6/12,1/4,IF(T31<2,1,2)),IF(OR(H31="Employe",H31="Employé"),IF(T31<1/12,0,IF(T31<2,1,2)),2))))) -> 1 | X31: =IF(Q31="",T31,(Q31-K31)/365.25) -> 1.744011 | AG31: =IF(TPersonnel[[#This Row],[Fonction à supprimer]]="NON",0,IF(TPersonnel[[#This Row],[Ancienneté (ans) à la date théorique de sortie]]<0.67,0,IF(TPersonnel[[#This Row],[Ancienneté (ans) à la date théorique de sortie]]<=10,TPersonnel[[#This Row],[Ancienneté (ans) à la date théorique de sortie]]*TPersonnel[[#This Row],[Salaire Brut de référence]]/4,(10*TPersonnel[[#This Row],[Salaire Brut de référence]]/4+(TPersonnel[[#This Row],[Ancienneté (ans) à la date théorique de sortie]]-10)*TPersonnel[[#This Row],[Salaire Brut de référence]]/3)))) -> 0 | AH31: =IF(UPPER(TPersonnel[[#This Row],[Fonction à supprimer]])="NON",0,IF(TPersonnel[[#This Row],[Ancienneté (ans) à la date théorique de sortie]]<1,0,IF(OR(TPersonnel[[#This Row],[Catégorie]]="Ouvrier",TPersonnel[[#This Row],[Catégorie]]="Employe",TPersonnel[[#This Row],[Catégorie]]="Employé"),IF(TPersonnel[[#This Row],[Ancienneté (ans) à la date théorique de sortie]]<3,TPersonnel[[#This Row],[Ancienneté (ans) à la date théorique de sortie]]*TPersonnel[[#This Row],[Salaire Brut de référence]]/10,TPersonnel[[#This Row],[Ancienneté (ans) à la date théorique de sortie]]*TPersonnel[[#This Row],[Salaire Brut de référence]]*2/10),IF(OR(TPersonnel[[#This Row],[Catégorie]]="Agent Maitrise",TPersonnel[[#This Row],[Catégorie]]="Agent de maitrise",TPersonnel[[#This Row],[Catégorie]]="Haute maitrise"),IF(TPersonnel[[#This Row],[Ancienneté (ans) à la date théorique de sortie]]<3,TPersonnel[[#This Row],[Ancienneté (ans) à la date théorique de sortie]]*TPersonnel[[#This Row],[Salaire Brut de référence]]/10,TPersonnel[[#This Row],[Ancienneté (ans) à la date théorique de sortie]]*TPersonnel[[#This Row],[Salaire Brut de référence]]*3/10),IF(TPersonnel[[#This Row],[Catégorie]]="Cadre",IF(TPersonnel[[#This Row],[Ancienneté (ans) à la date théorique de sortie]]<3,0,TPersonnel[[#This Row],[Ancienneté (ans) à la date théorique de sortie]]*TPersonnel[[#This Row],[Salaire Brut de référence]]*4/10),0))))) -> 0 | AI31: =IF(TPersonnel[[#This Row],[INDEM LÉGALE]]=0,"",IF(TPersonnel[[#This Row],[INDEM LÉGALE]]>TPersonnel[[#This Row],[INDEM CONV.]],"LEGAL","CONVENTIONNEL")) | AJ31: =MAX(TPersonnel[[#This Row],[INDEM LÉGALE]],TPersonnel[[#This Row],[INDEM CONV.]]) -> 0 | AK31: =TPersonnel[[#This Row],[INDEM RETENUE]]*'⚙️ Parametres'!$B$5 -> 0 | AL31: =TPersonnel[[#This Row],[INDEM RETENUE]]+TPersonnel[[#This Row],[Majoration PSE]] -> 0 | AM31: =IF(UPPER(TPersonnel[[#This Row],[Fonction à supprimer]])="NON",0,IF(OR(TPersonnel[[#This Row],[Catégorie]]="Cadre"),3,IF(TPersonnel[[#This Row],[Catégorie]]="Haute maitrise",2,IF(OR(TPersonnel[[#This Row],[Catégorie]]="Agent Maitrise",TPersonnel[[#This Row],[Catégorie]]="Agent de maitrise"),IF(TPersonnel[[#This Row],[Ancienneté (ans) à la date théorique de sortie]]<2/12,0,IF(TPersonnel[[#This Row],[Ancienneté (ans) à la date théorique de sortie]]<2,1,2)),IF(OR(TPersonnel[[#This Row],[Catégorie]]="Ouvrier",TPersonnel[[#This Row],[Catégorie]]="Employe",TPersonnel[[#This Row],[Catégorie]]="Employé"),IF(TPersonnel[[#This Row],[Ancienneté (ans) à la date théorique de sortie]]<6/12,IF(TPersonnel[[#This Row],[Catégorie]]="Ouvrier",1/4,IF(TPersonnel[[#This Row],[Ancienneté (ans) à la date théorique de sortie]]<1/12,0,1)),IF(TPersonnel[[#This Row],[Ancienneté (ans) à la date théorique de sortie]]<2,1,2)),2))))) -> 0 | AN31: =IF(UPPER(TPersonnel[[#This Row],[Fonction à supprimer]])="NON",0,TPersonnel[[#This Row],[Préavis Calc (mois)]]*TPersonnel[[#This Row],[Salaire Brut de référence]]) -> 0 | AO31: =IF(TPersonnel[[#This Row],[Fonction à supprimer]]="NON",0,TPersonnel[[#This Row],[Nb CP Acquis]]+TPersonnel[[#This Row],[Préavis Calc (mois)]]*2.08) -> 0 | AP31: =TPersonnel[[#This Row],[CP Calc (jrs)]]*TPersonnel[[#This Row],[Salaire Brut de référence]]/21.67 -> 0 | AQ31: =IF(UPPER(TPersonnel[[#This Row],[Fonction à supprimer]])="NON",0,_xlfn.LET(_xlpm.taux,IF(TPersonnel[[#This Row],[Catégorie]]="Ouvrier",'📈 Dashboard'!$B$32,IF(TPersonnel[[#This Row],[Catégorie]]="Cadre",'📈 Dashboard'!$B$34,'📈 Dashboard'!$B$33)),_xlpm.csp,UPPER(TPersonnel[[#This Row],[CSP (contrat de sécurisation professionnel)]])="OUI",IF(AND(_xlpm.csp,TPersonnel[[#This Row],[Ancienneté (ans) à la date théorique de sortie]]>=1),MIN(TPersonnel[[#This Row],[Préavis Calc (mois)]],3)*TPersonnel[[#This Row],[Salaire Brut de référence]]*(_xlpm.taux+'⚙️ Parametres'!$B$11)+IF(TPersonnel[[#This Row],[Préavis Calc (mois)]]>3,(TPersonnel[[#This Row],[Préavis Calc (mois)]]-3)*TPersonnel[[#This Row],[Salaire Brut de référence]]*_xlpm.taux,0)+TPersonnel[[#This Row],[Indem CP]]*_xlpm.taux,IF(_xlpm.csp,TPersonnel[[#This Row],[Indem CP]]*_xlpm.taux,(TPersonnel[[#This Row],[Indem Préavis Brut]]+TPersonnel[[#This Row],[Indem CP]])*_xlpm.taux)))) -> 0 | AR31: =TPersonnel[[#This Row],[TOTAL INDEM]]+TPersonnel[[#This Row],[Indem Préavis Brut]]+TPersonnel[[#This Row],[Indem CP]]+TPersonnel[[#This Row],[COÛT Charges Patronales]] -> 0
A32: 2798 | B32: Non | C32: REGUIG | D32: Boris | E32: PUSIGNAN | F32: Exploitant affréteur | G32: CDI | H32: Agent de maîtrise | I32: 150 | J32: H | K32: 45474 | L32: 45474 | M32: 30315 | N32: 3527 | P32: 14.58 | Q32: =IF(UPPER(B32)="OUI",'📈 Dashboard'!$B$37,"") | R32: =MAX(N32,O32/12) -> 3527 | S32: 2395.57 | T32: =IF(L32="",(TODAY()-K32)/365.25,MAX((TODAY()-K32)/365.25,(TODAY()-L32)/365.25)) -> 1.705681 | U32: =IF(M32="","",(TODAY()-M32)/365.25) -> 43.208761 | V32: =N32*12 -> 42324 | W32: =IF(H32="Cadre",3,IF(H32="Haute maitrise",2,IF(OR(H32="Agent Maitrise",H32="Agent de maitrise"),IF(T32<2/12,0,IF(T32<2,1,2)),IF(OR(H32="Ouvrier"),IF(T32<6/12,1/4,IF(T32<2,1,2)),IF(OR(H32="Employe",H32="Employé"),IF(T32<1/12,0,IF(T32<2,1,2)),2))))) -> 2 | X32: =IF(Q32="",T32,(Q32-K32)/365.25) -> 1.705681 | AG32: =IF(TPersonnel[[#This Row],[Fonction à supprimer]]="NON",0,IF(TPersonnel[[#This Row],[Ancienneté (ans) à la date théorique de sortie]]<0.67,0,IF(TPersonnel[[#This Row],[Ancienneté (ans) à la date théorique de sortie]]<=10,TPersonnel[[#This Row],[Ancienneté (ans) à la date théorique de sortie]]*TPersonnel[[#This Row],[Salaire Brut de référence]]/4,(10*TPersonnel[[#This Row],[Salaire Brut de référence]]/4+(TPersonnel[[#This Row],[Ancienneté (ans) à la date théorique de sortie]]-10)*TPersonnel[[#This Row],[Salaire Brut de référence]]/3)))) -> 0 | AH32: =IF(UPPER(TPersonnel[[#This Row],[Fonction à supprimer]])="NON",0,IF(TPersonnel[[#This Row],[Ancienneté (ans) à la date théorique de sortie]]<1,0,IF(OR(TPersonnel[[#This Row],[Catégorie]]="Ouvrier",TPersonnel[[#This Row],[Catégorie]]="Employe",TPersonnel[[#This Row],[Catégorie]]="Employé"),IF(TPersonnel[[#This Row],[Ancienneté (ans) à la date théorique de sortie]]<3,TPersonnel[[#This Row],[Ancienneté (ans) à la date théorique de sortie]]*TPersonnel[[#This Row],[Salaire Brut de référence]]/10,TPersonnel[[#This Row],[Ancienneté (ans) à la date théorique de sortie]]*TPersonnel[[#This Row],[Salaire Brut de référence]]*2/10),IF(OR(TPersonnel[[#This Row],[Catégorie]]="Agent Maitrise",TPersonnel[[#This Row],[Catégorie]]="Agent de maitrise",TPersonnel[[#This Row],[Catégorie]]="Haute maitrise"),IF(TPersonnel[[#This Row],[Ancienneté (ans) à la date théorique de sortie]]<3,TPersonnel[[#This Row],[Ancienneté (ans) à la date théorique de sortie]]*TPersonnel[[#This Row],[Salaire Brut de référence]]/10,TPersonnel[[#This Row],[Ancienneté (ans) à la date théorique de sortie]]*TPersonnel[[#This Row],[Salaire Brut de référence]]*3/10),IF(TPersonnel[[#This Row],[Catégorie]]="Cadre",IF(TPersonnel[[#This Row],[Ancienneté (ans) à la date théorique de sortie]]<3,0,TPersonnel[[#This Row],[Ancienneté (ans) à la date théorique de sortie]]*TPersonnel[[#This Row],[Salaire Brut de référence]]*4/10),0))))) -> 0 | AI32: =IF(TPersonnel[[#This Row],[INDEM LÉGALE]]=0,"",IF(TPersonnel[[#This Row],[INDEM LÉGALE]]>TPersonnel[[#This Row],[INDEM CONV.]],"LEGAL","CONVENTIONNEL")) | AJ32: =MAX(TPersonnel[[#This Row],[INDEM LÉGALE]],TPersonnel[[#This Row],[INDEM CONV.]]) -> 0 | AK32: =TPersonnel[[#This Row],[INDEM RETENUE]]*'⚙️ Parametres'!$B$5 -> 0 | AL32: =TPersonnel[[#This Row],[INDEM RETENUE]]+TPersonnel[[#This Row],[Majoration PSE]] -> 0 | AM32: =IF(UPPER(TPersonnel[[#This Row],[Fonction à supprimer]])="NON",0,IF(OR(TPersonnel[[#This Row],[Catégorie]]="Cadre"),3,IF(TPersonnel[[#This Row],[Catégorie]]="Haute maitrise",2,IF(OR(TPersonnel[[#This Row],[Catégorie]]="Agent Maitrise",TPersonnel[[#This Row],[Catégorie]]="Agent de maitrise"),IF(TPersonnel[[#This Row],[Ancienneté (ans) à la date théorique de sortie]]<2/12,0,IF(TPersonnel[[#This Row],[Ancienneté (ans) à la date théorique de sortie]]<2,1,2)),IF(OR(TPersonnel[[#This Row],[Catégorie]]="Ouvrier",TPersonnel[[#This Row],[Catégorie]]="Employe",TPersonnel[[#This Row],[Catégorie]]="Employé"),IF(TPersonnel[[#This Row],[Ancienneté (ans) à la date théorique de sortie]]<6/12,IF(TPersonnel[[#This Row],[Catégorie]]="Ouvrier",1/4,IF(TPersonnel[[#This Row],[Ancienneté (ans) à la date théorique de sortie]]<1/12,0,1)),IF(TPersonnel[[#This Row],[Ancienneté (ans) à la date théorique de sortie]]<2,1,2)),2))))) -> 0 | AN32: =IF(UPPER(TPersonnel[[#This Row],[Fonction à supprimer]])="NON",0,TPersonnel[[#This Row],[Préavis Calc (mois)]]*TPersonnel[[#This Row],[Salaire Brut de référence]]) -> 0 | AO32: =IF(TPersonnel[[#This Row],[Fonction à supprimer]]="NON",0,TPersonnel[[#This Row],[Nb CP Acquis]]+TPersonnel[[#This Row],[Préavis Calc (mois)]]*2.08) -> 0 | AP32: =TPersonnel[[#This Row],[CP Calc (jrs)]]*TPersonnel[[#This Row],[Salaire Brut de référence]]/21.67 -> 0 | AQ32: =IF(UPPER(TPersonnel[[#This Row],[Fonction à supprimer]])="NON",0,_xlfn.LET(_xlpm.taux,IF(TPersonnel[[#This Row],[Catégorie]]="Ouvrier",'📈 Dashboard'!$B$32,IF(TPersonnel[[#This Row],[Catégorie]]="Cadre",'📈 Dashboard'!$B$34,'📈 Dashboard'!$B$33)),_xlpm.csp,UPPER(TPersonnel[[#This Row],[CSP (contrat de sécurisation professionnel)]])="OUI",IF(AND(_xlpm.csp,TPersonnel[[#This Row],[Ancienneté (ans) à la date théorique de sortie]]>=1),MIN(TPersonnel[[#This Row],[Préavis Calc (mois)]],3)*TPersonnel[[#This Row],[Salaire Brut de référence]]*(_xlpm.taux+'⚙️ Parametres'!$B$11)+IF(TPersonnel[[#This Row],[Préavis Calc (mois)]]>3,(TPersonnel[[#This Row],[Préavis Calc (mois)]]-3)*TPersonnel[[#This Row],[Salaire Brut de référence]]*_xlpm.taux,0)+TPersonnel[[#This Row],[Indem CP]]*_xlpm.taux,IF(_xlpm.csp,TPersonnel[[#This Row],[Indem CP]]*_xlpm.taux,(TPersonnel[[#This Row],[Indem Préavis Brut]]+TPersonnel[[#This Row],[Indem CP]])*_xlpm.taux)))) -> 0 | AR32: =TPersonnel[[#This Row],[TOTAL INDEM]]+TPersonnel[[#This Row],[Indem Préavis Brut]]+TPersonnel[[#This Row],[Indem CP]]+TPersonnel[[#This Row],[COÛT Charges Patronales]] -> 0
A33: 2805 | B33: Non | C33: BOUDRAA | D33: Khalid | E33: PUSIGNAN | F33: Assistant exploitation | G33: CDI | H33: Apprenti | I33: 120 | J33: H | K33: 45890 | L33: 45890 | M33: 38020 | N33: 1010.72 | P33: 6.59 | Q33: =IF(UPPER(B33)="OUI",'📈 Dashboard'!$B$37,"") | R33: =MAX(N33,O33/12) -> 1010.72 | S33: 319.17 | T33: =IF(L33="",(TODAY()-K33)/365.25,MAX((TODAY()-K33)/365.25,(TODAY()-L33)/365.25)) -> 0.56673511 | U33: =IF(M33="","",(TODAY()-M33)/365.25) -> 22.113621 | V33: =N33*12 -> 12128.64 | W33: =IF(H33="Cadre",3,IF(H33="Haute maitrise",2,IF(OR(H33="Agent Maitrise",H33="Agent de maitrise"),IF(T33<2/12,0,IF(T33<2,1,2)),IF(OR(H33="Ouvrier"),IF(T33<6/12,1/4,IF(T33<2,1,2)),IF(OR(H33="Employe",H33="Employé"),IF(T33<1/12,0,IF(T33<2,1,2)),2))))) -> 2 | X33: =IF(Q33="",T33,(Q33-K33)/365.25) -> 0.56673511 | AG33: =IF(TPersonnel[[#This Row],[Fonction à supprimer]]="NON",0,IF(TPersonnel[[#This Row],[Ancienneté (ans) à la date théorique de sortie]]<0.67,0,IF(TPersonnel[[#This Row],[Ancienneté (ans) à la date théorique de sortie]]<=10,TPersonnel[[#This Row],[Ancienneté (ans) à la date théorique de sortie]]*TPersonnel[[#This Row],[Salaire Brut de référence]]/4,(10*TPersonnel[[#This Row],[Salaire Brut de référence]]/4+(TPersonnel[[#This Row],[Ancienneté (ans) à la date théorique de sortie]]-10)*TPersonnel[[#This Row],[Salaire Brut de référence]]/3)))) -> 0 | AH33: =IF(UPPER(TPersonnel[[#This Row],[Fonction à supprimer]])="NON",0,IF(TPersonnel[[#This Row],[Ancienneté (ans) à la date théorique de sortie]]<1,0,IF(OR(TPersonnel[[#This Row],[Catégorie]]="Ouvrier",TPersonnel[[#This Row],[Catégorie]]="Employe",TPersonnel[[#This Row],[Catégorie]]="Employé"),IF(TPersonnel[[#This Row],[Ancienneté (ans) à la date théorique de sortie]]<3,TPersonnel[[#This Row],[Ancienneté (ans) à la date théorique de sortie]]*TPersonnel[[#This Row],[Salaire Brut de référence]]/10,TPersonnel[[#This Row],[Ancienneté (ans) à la date théorique de sortie]]*TPersonnel[[#This Row],[Salaire Brut de référence]]*2/10),IF(OR(TPersonnel[[#This Row],[Catégorie]]="Agent Maitrise",TPersonnel[[#This Row],[Catégorie]]="Agent de maitrise",TPersonnel[[#This Row],[Catégorie]]="Haute maitrise"),IF(TPersonnel[[#This Row],[Ancienneté (ans) à la date théorique de sortie]]<3,TPersonnel[[#This Row],[Ancienneté (ans) à la date théorique de sortie]]*TPersonnel[[#This Row],[Salaire Brut de référence]]/10,TPersonnel[[#This Row],[Ancienneté (ans) à la date théorique de sortie]]*TPersonnel[[#This Row],[Salaire Brut de référence]]*3/10),IF(TPersonnel[[#This Row],[Catégorie]]="Cadre",IF(TPersonnel[[#This Row],[Ancienneté (ans) à la date théorique de sortie]]<3,0,TPersonnel[[#This Row],[Ancienneté (ans) à la date théorique de sortie]]*TPersonnel[[#This Row],[Salaire Brut de référence]]*4/10),0))))) -> 0 | AI33: =IF(TPersonnel[[#This Row],[INDEM LÉGALE]]=0,"",IF(TPersonnel[[#This Row],[INDEM LÉGALE]]>TPersonnel[[#This Row],[INDEM CONV.]],"LEGAL","CONVENTIONNEL")) | AJ33: =MAX(TPersonnel[[#This Row],[INDEM LÉGALE]],TPersonnel[[#This Row],[INDEM CONV.]]) -> 0 | AK33: =TPersonnel[[#This Row],[INDEM RETENUE]]*'⚙️ Parametres'!$B$5 -> 0 | AL33: =TPersonnel[[#This Row],[INDEM RETENUE]]+TPersonnel[[#This Row],[Majoration PSE]] -> 0 | AM33: =IF(UPPER(TPersonnel[[#This Row],[Fonction à supprimer]])="NON",0,IF(OR(TPersonnel[[#This Row],[Catégorie]]="Cadre"),3,IF(TPersonnel[[#This Row],[Catégorie]]="Haute maitrise",2,IF(OR(TPersonnel[[#This Row],[Catégorie]]="Agent Maitrise",TPersonnel[[#This Row],[Catégorie]]="Agent de maitrise"),IF(TPersonnel[[#This Row],[Ancienneté (ans) à la date théorique de sortie]]<2/12,0,IF(TPersonnel[[#This Row],[Ancienneté (ans) à la date théorique de sortie]]<2,1,2)),IF(OR(TPersonnel[[#This Row],[Catégorie]]="Ouvrier",TPersonnel[[#This Row],[Catégorie]]="Employe",TPersonnel[[#This Row],[Catégorie]]="Employé"),IF(TPersonnel[[#This Row],[Ancienneté (ans) à la date théorique de sortie]]<6/12,IF(TPersonnel[[#This Row],[Catégorie]]="Ouvrier",1/4,IF(TPersonnel[[#This Row],[Ancienneté (ans) à la date théorique de sortie]]<1/12,0,1)),IF(TPersonnel[[#This Row],[Ancienneté (ans) à la date théorique de sortie]]<2,1,2)),2))))) -> 0 | AN33: =IF(UPPER(TPersonnel[[#This Row],[Fonction à supprimer]])="NON",0,TPersonnel[[#This Row],[Préavis Calc (mois)]]*TPersonnel[[#This Row],[Salaire Brut de référence]]) -> 0 | AO33: =IF(TPersonnel[[#This Row],[Fonction à supprimer]]="NON",0,TPersonnel[[#This Row],[Nb CP Acquis]]+TPersonnel[[#This Row],[Préavis Calc (mois)]]*2.08) -> 0 | AP33: =TPersonnel[[#This Row],[CP Calc (jrs)]]*TPersonnel[[#This Row],[Salaire Brut de référence]]/21.67 -> 0 | AQ33: =IF(UPPER(TPersonnel[[#This Row],[Fonction à supprimer]])="NON",0,_xlfn.LET(_xlpm.taux,IF(TPersonnel[[#This Row],[Catégorie]]="Ouvrier",'📈 Dashboard'!$B$32,IF(TPersonnel[[#This Row],[Catégorie]]="Cadre",'📈 Dashboard'!$B$34,'📈 Dashboard'!$B$33)),_xlpm.csp,UPPER(TPersonnel[[#This Row],[CSP (contrat de sécurisation professionnel)]])="OUI",IF(AND(_xlpm.csp,TPersonnel[[#This Row],[Ancienneté (ans) à la date théorique de sortie]]>=1),MIN(TPersonnel[[#This Row],[Préavis Calc (mois)]],3)*TPersonnel[[#This Row],[Salaire Brut de référence]]*(_xlpm.taux+'⚙️ Parametres'!$B$11)+IF(TPersonnel[[#This Row],[Préavis Calc (mois)]]>3,(TPersonnel[[#This Row],[Préavis Calc (mois)]]-3)*TPersonnel[[#This Row],[Salaire Brut de référence]]*_xlpm.taux,0)+TPersonnel[[#This Row],[Indem CP]]*_xlpm.taux,IF(_xlpm.csp,TPersonnel[[#This Row],[Indem CP]]*_xlpm.taux,(TPersonnel[[#This Row],[Indem Préavis Brut]]+TPersonnel[[#This Row],[Indem CP]])*_xlpm.taux)))) -> 0 | AR33: =TPersonnel[[#This Row],[TOTAL INDEM]]+TPersonnel[[#This Row],[Indem Préavis Brut]]+TPersonnel[[#This Row],[Indem CP]]+TPersonnel[[#This Row],[COÛT Charges Patronales]] -> 0
A34: 2806 | B34: Non | C34: ELIBAL | D34: Rumeysa | E34: PUSIGNAN | F34: Assistante Exploitation | G34: CDI | H34: Apprenti | I34: 120 | J34: F | K34: 45901 | L34: 45901 | M34: 38216 | N34: 1010.72 | P34: 6.32 | Q34: =IF(UPPER(B34)="OUI",'📈 Dashboard'!$B$37,"") | R34: =MAX(N34,O34/12) -> 1010.72 | S34: 306.9 | T34: =IF(L34="",(TODAY()-K34)/365.25,MAX((TODAY()-K34)/365.25,(TODAY()-L34)/365.25)) -> 0.53661875 | U34: =IF(M34="","",(TODAY()-M34)/365.25) -> 21.577002 | V34: =N34*12 -> 12128.64 | W34: =IF(H34="Cadre",3,IF(H34="Haute maitrise",2,IF(OR(H34="Agent Maitrise",H34="Agent de maitrise"),IF(T34<2/12,0,IF(T34<2,1,2)),IF(OR(H34="Ouvrier"),IF(T34<6/12,1/4,IF(T34<2,1,2)),IF(OR(H34="Employe",H34="Employé"),IF(T34<1/12,0,IF(T34<2,1,2)),2))))) -> 2 | X34: =IF(Q34="",T34,(Q34-K34)/365.25) -> 0.53661875 | AG34: =IF(TPersonnel[[#This Row],[Fonction à supprimer]]="NON",0,IF(TPersonnel[[#This Row],[Ancienneté (ans) à la date théorique de sortie]]<0.67,0,IF(TPersonnel[[#This Row],[Ancienneté (ans) à la date théorique de sortie]]<=10,TPersonnel[[#This Row],[Ancienneté (ans) à la date théorique de sortie]]*TPersonnel[[#This Row],[Salaire Brut de référence]]/4,(10*TPersonnel[[#This Row],[Salaire Brut de référence]]/4+(TPersonnel[[#This Row],[Ancienneté (ans) à la date théorique de sortie]]-10)*TPersonnel[[#This Row],[Salaire Brut de référence]]/3)))) -> 0 | AH34: =IF(UPPER(TPersonnel[[#This Row],[Fonction à supprimer]])="NON",0,IF(TPersonnel[[#This Row],[Ancienneté (ans) à la date théorique de sortie]]<1,0,IF(OR(TPersonnel[[#This Row],[Catégorie]]="Ouvrier",TPersonnel[[#This Row],[Catégorie]]="Employe",TPersonnel[[#This Row],[Catégorie]]="Employé"),IF(TPersonnel[[#This Row],[Ancienneté (ans) à la date théorique de sortie]]<3,TPersonnel[[#This Row],[Ancienneté (ans) à la date théorique de sortie]]*TPersonnel[[#This Row],[Salaire Brut de référence]]/10,TPersonnel[[#This Row],[Ancienneté (ans) à la date théorique de sortie]]*TPersonnel[[#This Row],[Salaire Brut de référence]]*2/10),IF(OR(TPersonnel[[#This Row],[Catégorie]]="Agent Maitrise",TPersonnel[[#This Row],[Catégorie]]="Agent de maitrise",TPersonnel[[#This Row],[Catégorie]]="Haute maitrise"),IF(TPersonnel[[#This Row],[Ancienneté (ans) à la date théorique de sortie]]<3,TPersonnel[[#This Row],[Ancienneté (ans) à la date théorique de sortie]]*TPersonnel[[#This Row],[Salaire Brut de référence]]/10,TPersonnel[[#This Row],[Ancienneté (ans) à la date théorique de sortie]]*TPersonnel[[#This Row],[Salaire Brut de référence]]*3/10),IF(TPersonnel[[#This Row],[Catégorie]]="Cadre",IF(TPersonnel[[#This Row],[Ancienneté (ans) à la date théorique de sortie]]<3,0,TPersonnel[[#This Row],[Ancienneté (ans) à la date théorique de sortie]]*TPersonnel[[#This Row],[Salaire Brut de référence]]*4/10),0))))) -> 0 | AI34: =IF(TPersonnel[[#This Row],[INDEM LÉGALE]]=0,"",IF(TPersonnel[[#This Row],[INDEM LÉGALE]]>TPersonnel[[#This Row],[INDEM CONV.]],"LEGAL","CONVENTIONNEL")) | AJ34: =MAX(TPersonnel[[#This Row],[INDEM LÉGALE]],TPersonnel[[#This Row],[INDEM CONV.]]) -> 0 | AK34: =TPersonnel[[#This Row],[INDEM RETENUE]]*'⚙️ Parametres'!$B$5 -> 0 | AL34: =TPersonnel[[#This Row],[INDEM RETENUE]]+TPersonnel[[#This Row],[Majoration PSE]] -> 0 | AM34: =IF(UPPER(TPersonnel[[#This Row],[Fonction à supprimer]])="NON",0,IF(OR(TPersonnel[[#This Row],[Catégorie]]="Cadre"),3,IF(TPersonnel[[#This Row],[Catégorie]]="Haute maitrise",2,IF(OR(TPersonnel[[#This Row],[Catégorie]]="Agent Maitrise",TPersonnel[[#This Row],[Catégorie]]="Agent de maitrise"),IF(TPersonnel[[#This Row],[Ancienneté (ans) à la date théorique de sortie]]<2/12,0,IF(TPersonnel[[#This Row],[Ancienneté (ans) à la date théorique de sortie]]<2,1,2)),IF(OR(TPersonnel[[#This Row],[Catégorie]]="Ouvrier",TPersonnel[[#This Row],[Catégorie]]="Employe",TPersonnel[[#This Row],[Catégorie]]="Employé"),IF(TPersonnel[[#This Row],[Ancienneté (ans) à la date théorique de sortie]]<6/12,IF(TPersonnel[[#This Row],[Catégorie]]="Ouvrier",1/4,IF(TPersonnel[[#This Row],[Ancienneté (ans) à la date théorique de sortie]]<1/12,0,1)),IF(TPersonnel[[#This Row],[Ancienneté (ans) à la date théorique de sortie]]<2,1,2)),2))))) -> 0 | AN34: =IF(UPPER(TPersonnel[[#This Row],[Fonction à supprimer]])="NON",0,TPersonnel[[#This Row],[Préavis Calc (mois)]]*TPersonnel[[#This Row],[Salaire Brut de référence]]) -> 0 | AO34: =IF(TPersonnel[[#This Row],[Fonction à supprimer]]="NON",0,TPersonnel[[#This Row],[Nb CP Acquis]]+TPersonnel[[#This Row],[Préavis Calc (mois)]]*2.08) -> 0 | AP34: =TPersonnel[[#This Row],[CP Calc (jrs)]]*TPersonnel[[#This Row],[Salaire Brut de référence]]/21.67 -> 0 | AQ34: =IF(UPPER(TPersonnel[[#This Row],[Fonction à supprimer]])="NON",0,_xlfn.LET(_xlpm.taux,IF(TPersonnel[[#This Row],[Catégorie]]="Ouvrier",'📈 Dashboard'!$B$32,IF(TPersonnel[[#This Row],[Catégorie]]="Cadre",'📈 Dashboard'!$B$34,'📈 Dashboard'!$B$33)),_xlpm.csp,UPPER(TPersonnel[[#This Row],[CSP (contrat de sécurisation professionnel)]])="OUI",IF(AND(_xlpm.csp,TPersonnel[[#This Row],[Ancienneté (ans) à la date théorique de sortie]]>=1),MIN(TPersonnel[[#This Row],[Préavis Calc (mois)]],3)*TPersonnel[[#This Row],[Salaire Brut de référence]]*(_xlpm.taux+'⚙️ Parametres'!$B$11)+IF(TPersonnel[[#This Row],[Préavis Calc (mois)]]>3,(TPersonnel[[#This Row],[Préavis Calc (mois)]]-3)*TPersonnel[[#This Row],[Salaire Brut de référence]]*_xlpm.taux,0)+TPersonnel[[#This Row],[Indem CP]]*_xlpm.taux,IF(_xlpm.csp,TPersonnel[[#This Row],[Indem CP]]*_xlpm.taux,(TPersonnel[[#This Row],[Indem Préavis Brut]]+TPersonnel[[#This Row],[Indem CP]])*_xlpm.taux)))) -> 0 | AR34: =TPersonnel[[#This Row],[TOTAL INDEM]]+TPersonnel[[#This Row],[Indem Préavis Brut]]+TPersonnel[[#This Row],[Indem CP]]+TPersonnel[[#This Row],[COÛT Charges Patronales]] -> 0
A35: 2807 | B35: Non | C35: NICAISE | D35: Frédéric | E35: PUSIGNAN | F35: Conducteur PL | G35: CDI | H35: Ouvrier | I35: 138M | J35: H | K35: 44515 | L35: 44515 | M35: 27685 | N35: 3565.23 | P35: 11.09 | Q35: =IF(UPPER(B35)="OUI",'📈 Dashboard'!$B$37,"") | R35: =MAX(N35,O35/12) -> 3565.23 | S35: 1545.95 | T35: =IF(L35="",(TODAY()-K35)/365.25,MAX((TODAY()-K35)/365.25,(TODAY()-L35)/365.25)) -> 4.3312799 | U35: =IF(M35="","",(TODAY()-M35)/365.25) -> 50.409309 | V35: =N35*12 -> 42782.76 | W35: =IF(H35="Cadre",3,IF(H35="Haute maitrise",2,IF(OR(H35="Agent Maitrise",H35="Agent de maitrise"),IF(T35<2/12,0,IF(T35<2,1,2)),IF(OR(H35="Ouvrier"),IF(T35<6/12,1/4,IF(T35<2,1,2)),IF(OR(H35="Employe",H35="Employé"),IF(T35<1/12,0,IF(T35<2,1,2)),2))))) -> 2 | X35: =IF(Q35="",T35,(Q35-K35)/365.25) -> 4.3312799 | AG35: =IF(TPersonnel[[#This Row],[Fonction à supprimer]]="NON",0,IF(TPersonnel[[#This Row],[Ancienneté (ans) à la date théorique de sortie]]<0.67,0,IF(TPersonnel[[#This Row],[Ancienneté (ans) à la date théorique de sortie]]<=10,TPersonnel[[#This Row],[Ancienneté (ans) à la date théorique de sortie]]*TPersonnel[[#This Row],[Salaire Brut de référence]]/4,(10*TPersonnel[[#This Row],[Salaire Brut de référence]]/4+(TPersonnel[[#This Row],[Ancienneté (ans) à la date théorique de sortie]]-10)*TPersonnel[[#This Row],[Salaire Brut de référence]]/3)))) -> 0 | AH35: =IF(UPPER(TPersonnel[[#This Row],[Fonction à supprimer]])="NON",0,IF(TPersonnel[[#This Row],[Ancienneté (ans) à la date théorique de sortie]]<1,0,IF(OR(TPersonnel[[#This Row],[Catégorie]]="Ouvrier",TPersonnel[[#This Row],[Catégorie]]="Employe",TPersonnel[[#This Row],[Catégorie]]="Employé"),IF(TPersonnel[[#This Row],[Ancienneté (ans) à la date théorique de sortie]]<3,TPersonnel[[#This Row],[Ancienneté (ans) à la date théorique de sortie]]*TPersonnel[[#This Row],[Salaire Brut de référence]]/10,TPersonnel[[#This Row],[Ancienneté (ans) à la date théorique de sortie]]*TPersonnel[[#This Row],[Salaire Brut de référence]]*2/10),IF(OR(TPersonnel[[#This Row],[Catégorie]]="Agent Maitrise",TPersonnel[[#This Row],[Catégorie]]="Agent de maitrise",TPersonnel[[#This Row],[Catégorie]]="Haute maitrise"),IF(TPersonnel[[#This Row],[Ancienneté (ans) à la date théorique de sortie]]<3,TPersonnel[[#This Row],[Ancienneté (ans) à la date théorique de sortie]]*TPersonnel[[#This Row],[Salaire Brut de référence]]/10,TPersonnel[[#This Row],[Ancienneté (ans) à la date théorique de sortie]]*TPersonnel[[#This Row],[Salaire Brut de référence]]*3/10),IF(TPersonnel[[#This Row],[Catégorie]]="Cadre",IF(TPersonnel[[#This Row],[Ancienneté (ans) à la date théorique de sortie]]<3,0,TPersonnel[[#This Row],[Ancienneté (ans) à la date théorique de sortie]]*TPersonnel[[#This Row],[Salaire Brut de référence]]*4/10),0))))) -> 0 | AI35: =IF(TPersonnel[[#This Row],[INDEM LÉGALE]]=0,"",IF(TPersonnel[[#This Row],[INDEM LÉGALE]]>TPersonnel[[#This Row],[INDEM CONV.]],"LEGAL","CONVENTIONNEL")) | AJ35: =MAX(TPersonnel[[#This Row],[INDEM LÉGALE]],TPersonnel[[#This Row],[INDEM CONV.]]) -> 0 | AK35: =TPersonnel[[#This Row],[INDEM RETENUE]]*'⚙️ Parametres'!$B$5 -> 0 | AL35: =TPersonnel[[#This Row],[INDEM RETENUE]]+TPersonnel[[#This Row],[Majoration PSE]] -> 0 | AM35: =IF(UPPER(TPersonnel[[#This Row],[Fonction à supprimer]])="NON",0,IF(OR(TPersonnel[[#This Row],[Catégorie]]="Cadre"),3,IF(TPersonnel[[#This Row],[Catégorie]]="Haute maitrise",2,IF(OR(TPersonnel[[#This Row],[Catégorie]]="Agent Maitrise",TPersonnel[[#This Row],[Catégorie]]="Agent de maitrise"),IF(TPersonnel[[#This Row],[Ancienneté (ans) à la date théorique de sortie]]<2/12,0,IF(TPersonnel[[#This Row],[Ancienneté (ans) à la date théorique de sortie]]<2,1,2)),IF(OR(TPersonnel[[#This Row],[Catégorie]]="Ouvrier",TPersonnel[[#This Row],[Catégorie]]="Employe",TPersonnel[[#This Row],[Catégorie]]="Employé"),IF(TPersonnel[[#This Row],[Ancienneté (ans) à la date théorique de sortie]]<6/12,IF(TPersonnel[[#This Row],[Catégorie]]="Ouvrier",1/4,IF(TPersonnel[[#This Row],[Ancienneté (ans) à la date théorique de sortie]]<1/12,0,1)),IF(TPersonnel[[#This Row],[Ancienneté (ans) à la date théorique de sortie]]<2,1,2)),2))))) -> 0 | AN35: =IF(UPPER(TPersonnel[[#This Row],[Fonction à supprimer]])="NON",0,TPersonnel[[#This Row],[Préavis Calc (mois)]]*TPersonnel[[#This Row],[Salaire Brut de référence]]) -> 0 | AO35: =IF(TPersonnel[[#This Row],[Fonction à supprimer]]="NON",0,TPersonnel[[#This Row],[Nb CP Acquis]]+TPersonnel[[#This Row],[Préavis Calc (mois)]]*2.08) -> 0 | AP35: =TPersonnel[[#This Row],[CP Calc (jrs)]]*TPersonnel[[#This Row],[Salaire Brut de référence]]/21.67 -> 0 | AQ35: =IF(UPPER(TPersonnel[[#This Row],[Fonction à supprimer]])="NON",0,_xlfn.LET(_xlpm.taux,IF(TPersonnel[[#This Row],[Catégorie]]="Ouvrier",'📈 Dashboard'!$B$32,IF(TPersonnel[[#This Row],[Catégorie]]="Cadre",'📈 Dashboard'!$B$34,'📈 Dashboard'!$B$33)),_xlpm.csp,UPPER(TPersonnel[[#This Row],[CSP (contrat de sécurisation professionnel)]])="OUI",IF(AND(_xlpm.csp,TPersonnel[[#This Row],[Ancienneté (ans) à la date théorique de sortie]]>=1),MIN(TPersonnel[[#This Row],[Préavis Calc (mois)]],3)*TPersonnel[[#This Row],[Salaire Brut de référence]]*(_xlpm.taux+'⚙️ Parametres'!$B$11)+IF(TPersonnel[[#This Row],[Préavis Calc (mois)]]>3,(TPersonnel[[#This Row],[Préavis Calc (mois)]]-3)*TPersonnel[[#This Row],[Salaire Brut de référence]]*_xlpm.taux,0)+TPersonnel[[#This Row],[Indem CP]]*_xlpm.taux,IF(_xlpm.csp,TPersonnel[[#This Row],[Indem CP]]*_xlpm.taux,(TPersonnel[[#This Row],[Indem Préavis Brut]]+TPersonnel[[#This Row],[Indem CP]])*_xlpm.taux)))) -> 0 | AR35: =TPersonnel[[#This Row],[TOTAL INDEM]]+TPersonnel[[#This Row],[Indem Préavis Brut]]+TPersonnel[[#This Row],[Indem CP]]+TPersonnel[[#This Row],[COÛT Charges Patronales]] -> 0
A36: 2808 | B36: Non | C36: ROCHAS | D36: Christelle | E36: PUSIGNAN | F36: Commerciale | G36: CDI | H36: Agent de maîtrise | I36: 150 | J36: F | K36: 45901 | L36: 45901 | M36: 26424 | N36: 2852 | P36: 7.26 | Q36: =IF(UPPER(B36)="OUI",'📈 Dashboard'!$B$37,"") | R36: =MAX(N36,O36/12) -> 2852 | S36: 994.7 | T36: =IF(L36="",(TODAY()-K36)/365.25,MAX((TODAY()-K36)/365.25,(TODAY()-L36)/365.25)) -> 0.53661875 | U36: =IF(M36="","",(TODAY()-M36)/365.25) -> 53.861739 | V36: =N36*12 -> 34224 | W36: =IF(H36="Cadre",3,IF(H36="Haute maitrise",2,IF(OR(H36="Agent Maitrise",H36="Agent de maitrise"),IF(T36<2/12,0,IF(T36<2,1,2)),IF(OR(H36="Ouvrier"),IF(T36<6/12,1/4,IF(T36<2,1,2)),IF(OR(H36="Employe",H36="Employé"),IF(T36<1/12,0,IF(T36<2,1,2)),2))))) -> 2 | X36: =IF(Q36="",T36,(Q36-K36)/365.25) -> 0.53661875 | AG36: =IF(TPersonnel[[#This Row],[Fonction à supprimer]]="NON",0,IF(TPersonnel[[#This Row],[Ancienneté (ans) à la date théorique de sortie]]<0.67,0,IF(TPersonnel[[#This Row],[Ancienneté (ans) à la date théorique de sortie]]<=10,TPersonnel[[#This Row],[Ancienneté (ans) à la date théorique de sortie]]*TPersonnel[[#This Row],[Salaire Brut de référence]]/4,(10*TPersonnel[[#This Row],[Salaire Brut de référence]]/4+(TPersonnel[[#This Row],[Ancienneté (ans) à la date théorique de sortie]]-10)*TPersonnel[[#This Row],[Salaire Brut de référence]]/3)))) -> 0 | AH36: =IF(UPPER(TPersonnel[[#This Row],[Fonction à supprimer]])="NON",0,IF(TPersonnel[[#This Row],[Ancienneté (ans) à la date théorique de sortie]]<1,0,IF(OR(TPersonnel[[#This Row],[Catégorie]]="Ouvrier",TPersonnel[[#This Row],[Catégorie]]="Employe",TPersonnel[[#This Row],[Catégorie]]="Employé"),IF(TPersonnel[[#This Row],[Ancienneté (ans) à la date théorique de sortie]]<3,TPersonnel[[#This Row],[Ancienneté (ans) à la date théorique de sortie]]*TPersonnel[[#This Row],[Salaire Brut de référence]]/10,TPersonnel[[#This Row],[Ancienneté (ans) à la date théorique de sortie]]*TPersonnel[[#This Row],[Salaire Brut de référence]]*2/10),IF(OR(TPersonnel[[#This Row],[Catégorie]]="Agent Maitrise",TPersonnel[[#This Row],[Catégorie]]="Agent de maitrise",TPersonnel[[#This Row],[Catégorie]]="Haute maitrise"),IF(TPersonnel[[#This Row],[Ancienneté (ans) à la date théorique de sortie]]<3,TPersonnel[[#This Row],[Ancienneté (ans) à la date théorique de sortie]]*TPersonnel[[#This Row],[Salaire Brut de référence]]/10,TPersonnel[[#This Row],[Ancienneté (ans) à la date théorique de sortie]]*TPersonnel[[#This Row],[Salaire Brut de référence]]*3/10),IF(TPersonnel[[#This Row],[Catégorie]]="Cadre",IF(TPersonnel[[#This Row],[Ancienneté (ans) à la date théorique de sortie]]<3,0,TPersonnel[[#This Row],[Ancienneté (ans) à la date théorique de sortie]]*TPersonnel[[#This Row],[Salaire Brut de référence]]*4/10),0))))) -> 0 | AI36: =IF(TPersonnel[[#This Row],[INDEM LÉGALE]]=0,"",IF(TPersonnel[[#This Row],[INDEM LÉGALE]]>TPersonnel[[#This Row],[INDEM CONV.]],"LEGAL","CONVENTIONNEL")) | AJ36: =MAX(TPersonnel[[#This Row],[INDEM LÉGALE]],TPersonnel[[#This Row],[INDEM CONV.]]) -> 0 | AK36: =TPersonnel[[#This Row],[INDEM RETENUE]]*'⚙️ Parametres'!$B$5 -> 0 | AL36: =TPersonnel[[#This Row],[INDEM RETENUE]]+TPersonnel[[#This Row],[Majoration PSE]] -> 0 | AM36: =IF(UPPER(TPersonnel[[#This Row],[Fonction à supprimer]])="NON",0,IF(OR(TPersonnel[[#This Row],[Catégorie]]="Cadre"),3,IF(TPersonnel[[#This Row],[Catégorie]]="Haute maitrise",2,IF(OR(TPersonnel[[#This Row],[Catégorie]]="Agent Maitrise",TPersonnel[[#This Row],[Catégorie]]="Agent de maitrise"),IF(TPersonnel[[#This Row],[Ancienneté (ans) à la date théorique de sortie]]<2/12,0,IF(TPersonnel[[#This Row],[Ancienneté (ans) à la date théorique de sortie]]<2,1,2)),IF(OR(TPersonnel[[#This Row],[Catégorie]]="Ouvrier",TPersonnel[[#This Row],[Catégorie]]="Employe",TPersonnel[[#This Row],[Catégorie]]="Employé"),IF(TPersonnel[[#This Row],[Ancienneté (ans) à la date théorique de sortie]]<6/12,IF(TPersonnel[[#This Row],[Catégorie]]="Ouvrier",1/4,IF(TPersonnel[[#This Row],[Ancienneté (ans) à la date théorique de sortie]]<1/12,0,1)),IF(TPersonnel[[#This Row],[Ancienneté (ans) à la date théorique de sortie]]<2,1,2)),2))))) -> 0 | AN36: =IF(UPPER(TPersonnel[[#This Row],[Fonction à supprimer]])="NON",0,TPersonnel[[#This Row],[Préavis Calc (mois)]]*TPersonnel[[#This Row],[Salaire Brut de référence]]) -> 0 | AO36: =IF(TPersonnel[[#This Row],[Fonction à supprimer]]="NON",0,TPersonnel[[#This Row],[Nb CP Acquis]]+TPersonnel[[#This Row],[Préavis Calc (mois)]]*2.08) -> 0 | AP36: =TPersonnel[[#This Row],[CP Calc (jrs)]]*TPersonnel[[#This Row],[Salaire Brut de référence]]/21.67 -> 0 | AQ36: =IF(UPPER(TPersonnel[[#This Row],[Fonction à supprimer]])="NON",0,_xlfn.LET(_xlpm.taux,IF(TPersonnel[[#This Row],[Catégorie]]="Ouvrier",'📈 Dashboard'!$B$32,IF(TPersonnel[[#This Row],[Catégorie]]="Cadre",'📈 Dashboard'!$B$34,'📈 Dashboard'!$B$33)),_xlpm.csp,UPPER(TPersonnel[[#This Row],[CSP (contrat de sécurisation professionnel)]])="OUI",IF(AND(_xlpm.csp,TPersonnel[[#This Row],[Ancienneté (ans) à la date théorique de sortie]]>=1),MIN(TPersonnel[[#This Row],[Préavis Calc (mois)]],3)*TPersonnel[[#This Row],[Salaire Brut de référence]]*(_xlpm.taux+'⚙️ Parametres'!$B$11)+IF(TPersonnel[[#This Row],[Préavis Calc (mois)]]>3,(TPersonnel[[#This Row],[Préavis Calc (mois)]]-3)*TPersonnel[[#This Row],[Salaire Brut de référence]]*_xlpm.taux,0)+TPersonnel[[#This Row],[Indem CP]]*_xlpm.taux,IF(_xlpm.csp,TPersonnel[[#This Row],[Indem CP]]*_xlpm.taux,(TPersonnel[[#This Row],[Indem Préavis Brut]]+TPersonnel[[#This Row],[Indem CP]])*_xlpm.taux)))) -> 0 | AR36: =TPersonnel[[#This Row],[TOTAL INDEM]]+TPersonnel[[#This Row],[Indem Préavis Brut]]+TPersonnel[[#This Row],[Indem CP]]+TPersonnel[[#This Row],[COÛT Charges Patronales]] -> 0
A37: 2809 | B37: Non | C37: LELIEVRE-OUDIN | D37: Fabien | E37: PUSIGNAN | F37: Affréteur | G37: CDI | H37: Agent de maîtrise | I37: 150 | J37: H | K37: 45931 | L37: 45931 | M37: 26156 | N37: 3000 | P37: 5.25 | Q37: =IF(UPPER(B37)="OUI",'📈 Dashboard'!$B$37,"") | R37: =MAX(N37,O37/12) -> 3000 | S37: 756 | T37: =IF(L37="",(TODAY()-K37)/365.25,MAX((TODAY()-K37)/365.25,(TODAY()-L37)/365.25)) -> 0.45448323 | U37: =IF(M37="","",(TODAY()-M37)/365.25) -> 54.595483 | V37: =N37*12 -> 36000 | W37: =IF(H37="Cadre",3,IF(H37="Haute maitrise",2,IF(OR(H37="Agent Maitrise",H37="Agent de maitrise"),IF(T37<2/12,0,IF(T37<2,1,2)),IF(OR(H37="Ouvrier"),IF(T37<6/12,1/4,IF(T37<2,1,2)),IF(OR(H37="Employe",H37="Employé"),IF(T37<1/12,0,IF(T37<2,1,2)),2))))) -> 2 | X37: =IF(Q37="",T37,(Q37-K37)/365.25) -> 0.45448323 | AG37: =IF(TPersonnel[[#This Row],[Fonction à supprimer]]="NON",0,IF(TPersonnel[[#This Row],[Ancienneté (ans) à la date théorique de sortie]]<0.67,0,IF(TPersonnel[[#This Row],[Ancienneté (ans) à la date théorique de sortie]]<=10,TPersonnel[[#This Row],[Ancienneté (ans) à la date théorique de sortie]]*TPersonnel[[#This Row],[Salaire Brut de référence]]/4,(10*TPersonnel[[#This Row],[Salaire Brut de référence]]/4+(TPersonnel[[#This Row],[Ancienneté (ans) à la date théorique de sortie]]-10)*TPersonnel[[#This Row],[Salaire Brut de référence]]/3)))) -> 0 | AH37: =IF(UPPER(TPersonnel[[#This Row],[Fonction à supprimer]])="NON",0,IF(TPersonnel[[#This Row],[Ancienneté (ans) à la date théorique de sortie]]<1,0,IF(OR(TPersonnel[[#This Row],[Catégorie]]="Ouvrier",TPersonnel[[#This Row],[Catégorie]]="Employe",TPersonnel[[#This Row],[Catégorie]]="Employé"),IF(TPersonnel[[#This Row],[Ancienneté (ans) à la date théorique de sortie]]<3,TPersonnel[[#This Row],[Ancienneté (ans) à la date théorique de sortie]]*TPersonnel[[#This Row],[Salaire Brut de référence]]/10,TPersonnel[[#This Row],[Ancienneté (ans) à la date théorique de sortie]]*TPersonnel[[#This Row],[Salaire Brut de référence]]*2/10),IF(OR(TPersonnel[[#This Row],[Catégorie]]="Agent Maitrise",TPersonnel[[#This Row],[Catégorie]]="Agent de maitrise",TPersonnel[[#This Row],[Catégorie]]="Haute maitrise"),IF(TPersonnel[[#This Row],[Ancienneté (ans) à la date théorique de sortie]]<3,TPersonnel[[#This Row],[Ancienneté (ans) à la date théorique de sortie]]*TPersonnel[[#This Row],[Salaire Brut de référence]]/10,TPersonnel[[#This Row],[Ancienneté (ans) à la date théorique de sortie]]*TPersonnel[[#This Row],[Salaire Brut de référence]]*3/10),IF(TPersonnel[[#This Row],[Catégorie]]="Cadre",IF(TPersonnel[[#This Row],[Ancienneté (ans) à la date théorique de sortie]]<3,0,TPersonnel[[#This Row],[Ancienneté (ans) à la date théorique de sortie]]*TPersonnel[[#This Row],[Salaire Brut de référence]]*4/10),0))))) -> 0 | AI37: =IF(TPersonnel[[#This Row],[INDEM LÉGALE]]=0,"",IF(TPersonnel[[#This Row],[INDEM LÉGALE]]>TPersonnel[[#This Row],[INDEM CONV.]],"LEGAL","CONVENTIONNEL")) | AJ37: =MAX(TPersonnel[[#This Row],[INDEM LÉGALE]],TPersonnel[[#This Row],[INDEM CONV.]]) -> 0 | AK37: =TPersonnel[[#This Row],[INDEM RETENUE]]*'⚙️ Parametres'!$B$5 -> 0 | AL37: =TPersonnel[[#This Row],[INDEM RETENUE]]+TPersonnel[[#This Row],[Majoration PSE]] -> 0 | AM37: =IF(UPPER(TPersonnel[[#This Row],[Fonction à supprimer]])="NON",0,IF(OR(TPersonnel[[#This Row],[Catégorie]]="Cadre"),3,IF(TPersonnel[[#This Row],[Catégorie]]="Haute maitrise",2,IF(OR(TPersonnel[[#This Row],[Catégorie]]="Agent Maitrise",TPersonnel[[#This Row],[Catégorie]]="Agent de maitrise"),IF(TPersonnel[[#This Row],[Ancienneté (ans) à la date théorique de sortie]]<2/12,0,IF(TPersonnel[[#This Row],[Ancienneté (ans) à la date théorique de sortie]]<2,1,2)),IF(OR(TPersonnel[[#This Row],[Catégorie]]="Ouvrier",TPersonnel[[#This Row],[Catégorie]]="Employe",TPersonnel[[#This Row],[Catégorie]]="Employé"),IF(TPersonnel[[#This Row],[Ancienneté (ans) à la date théorique de sortie]]<6/12,IF(TPersonnel[[#This Row],[Catégorie]]="Ouvrier",1/4,IF(TPersonnel[[#This Row],[Ancienneté (ans) à la date théorique de sortie]]<1/12,0,1)),IF(TPersonnel[[#This Row],[Ancienneté (ans) à la date théorique de sortie]]<2,1,2)),2))))) -> 0 | AN37: =IF(UPPER(TPersonnel[[#This Row],[Fonction à supprimer]])="NON",0,TPersonnel[[#This Row],[Préavis Calc (mois)]]*TPersonnel[[#This Row],[Salaire Brut de référence]]) -> 0 | AO37: =IF(TPersonnel[[#This Row],[Fonction à supprimer]]="NON",0,TPersonnel[[#This Row],[Nb CP Acquis]]+TPersonnel[[#This Row],[Préavis Calc (mois)]]*2.08) -> 0 | AP37: =TPersonnel[[#This Row],[CP Calc (jrs)]]*TPersonnel[[#This Row],[Salaire Brut de référence]]/21.67 -> 0 | AQ37: =IF(UPPER(TPersonnel[[#This Row],[Fonction à supprimer]])="NON",0,_xlfn.LET(_xlpm.taux,IF(TPersonnel[[#This Row],[Catégorie]]="Ouvrier",'📈 Dashboard'!$B$32,IF(TPersonnel[[#This Row],[Catégorie]]="Cadre",'📈 Dashboard'!$B$34,'📈 Dashboard'!$B$33)),_xlpm.csp,UPPER(TPersonnel[[#This Row],[CSP (contrat de sécurisation professionnel)]])="OUI",IF(AND(_xlpm.csp,TPersonnel[[#This Row],[Ancienneté (ans) à la date théorique de sortie]]>=1),MIN(TPersonnel[[#This Row],[Préavis Calc (mois)]],3)*TPersonnel[[#This Row],[Salaire Brut de référence]]*(_xlpm.taux+'⚙️ Parametres'!$B$11)+IF(TPersonnel[[#This Row],[Préavis Calc (mois)]]>3,(TPersonnel[[#This Row],[Préavis Calc (mois)]]-3)*TPersonnel[[#This Row],[Salaire Brut de référence]]*_xlpm.taux,0)+TPersonnel[[#This Row],[Indem CP]]*_xlpm.taux,IF(_xlpm.csp,TPersonnel[[#This Row],[Indem CP]]*_xlpm.taux,(TPersonnel[[#This Row],[Indem Préavis Brut]]+TPersonnel[[#This Row],[Indem CP]])*_xlpm.taux)))) -> 0 | AR37: =TPersonnel[[#This Row],[TOTAL INDEM]]+TPersonnel[[#This Row],[Indem Préavis Brut]]+TPersonnel[[#This Row],[Indem CP]]+TPersonnel[[#This Row],[COÛT Charges Patronales]] -> 0
N40: 90271.17

Sheet 📈 Dashboard
A1: 🎯 DASHBOARD PSE — ANALYSE AVANT / APRÈS RESTRUCTURATION | V1: Site | W1: Effectif Avant | X1: Postes Supprimés | AA1: Catégorie | AB1: Effectif Avant | AC1: Postes Supprimés | AE1: Contrat | AF1: Avant | AG1: Suppressions
V2: =A9 -> PUSIGNAN | W2: =B9 -> 13 | X2: =C9 -> 0 | AA2: =IFERROR(INDEX(_xlfn.ANCHORARRAY('⚙️ Parametres'!$K$3),1),"") -> Agent de maîtrise | AB2: =IF(AA2="","",COUNTIF(TPersonnel[Catégorie],AA2)) -> 6 | AC2: {=IF(AA2="","",SUMPRODUCT((UPPER(TPersonnel[Fonction à supprimer])="OUI")*(TPersonnel[Catégorie]=AA2)))} -> 0 | AE2: CDI | AF2: =B17 -> 34 | AG2: =C17 -> 0
A3: Effectif Avant | B3: Suppressions | C3: Effectif Après | D3: % Réduction | F3: Coût Employeur Avant (€/an) | G3: Coût Employeur Après (€/an) | H3: Économie Employeur (€/an) | J3: Coût IL (exonéré) | K3: Coût Préavis (chargé) | L3: Coût CP (chargé) | M3: COÛT TOTAL PSE | N3: ROI (années) | Q3: CDI supprimés | R3: CDD supprimés | S3: H supprimés | T3: F supprimées | V3: =A10 -> ROGNAC | W3: =B10 -> 6 | X3: =C10 -> 0 | AA3: =IFERROR(INDEX(_xlfn.ANCHORARRAY('⚙️ Parametres'!$K$3),2),"") -> Apprenti | AB3: =IF(AA3="","",COUNTIF(TPersonnel[Catégorie],AA3)) -> 2 | AC3: {=IF(AA3="","",SUMPRODUCT((UPPER(TPersonnel[Fonction à supprimer])="OUI")*(TPersonnel[Catégorie]=AA3)))} -> 0 | AE3: CDD | AF3: =B18 -> 0 | AG3: =C18 -> 0
A4: =ROWS(TPersonnel[]) -> 34 | B4: {=SUMPRODUCT((UPPER(TPersonnel[Fonction à supprimer])="OUI")*1)} -> 0 | C4: =A4-B4 -> 34 | D4: =B4/A4 -> 0 | F4: {=SUMPRODUCT(TPersonnel[Salaire Annuel Total]*(1+IF(TPersonnel[Catégorie]="Ouvrier",$B$32,IF(TPersonnel[Catégorie]="Cadre",$B$34,$B$33))))} -> 1575573 | G4: {=SUMPRODUCT((UPPER(TPersonnel[Fonction à supprimer])<>"OUI")*TPersonnel[Salaire Annuel Total]*(1+IF(TPersonnel[Catégorie]="Ouvrier",$B$32,IF(TPersonnel[Catégorie]="Cadre",$B$34,$B$33))))} -> 1575573 | H4: =F4-G4 -> 0 | J4: =SUM(TPersonnel[TOTAL INDEM]) -> 0 | K4: {=SUMPRODUCT((UPPER(TPersonnel[Fonction à supprimer])="OUI")*(UPPER(TPersonnel[CSP (contrat de sécurisation professionnel)])<>"OUI")*TPersonnel[Indem Préavis Brut]*(1+IF(TPersonnel[Catégorie]="Ouvrier",$B$32,IF(TPersonnel[Catégorie]="Cadre",$B$34,$B$33))))+SUMPRODUCT((UPPER(TPersonnel[Fonction à supprimer])="OUI")*(UPPER(TPersonnel[CSP (contrat de sécurisation professionnel)])="OUI")*TPersonnel[Indem Préavis Brut])} -> 0 | L4: {=SUMPRODUCT((UPPER(TPersonnel[Fonction à supprimer])="OUI")*TPersonnel[Indem CP]*(1+IF(TPersonnel[Catégorie]="Ouvrier",$B$32,IF(TPersonnel[Catégorie]="Cadre",$B$34,$B$33))))} -> 0 | M4: =J4+K4+L4 -> 0 | N4: =IFERROR(M4/H4,0) -> 0 | Q4: {=SUMPRODUCT((UPPER(TPersonnel[Fonction à supprimer])="OUI")*(TPersonnel[Type de contrat]="CDI"))} -> 0 | R4: {=SUMPRODUCT((UPPER(TPersonnel[Fonction à supprimer])="OUI")*(TPersonnel[Type de contrat]="CDD"))} -> 0 | S4: {=SUMPRODUCT((UPPER(TPersonnel[Fonction à supprimer])="OUI")*(TPersonnel[Sexe]="H"))} -> 0 | T4: {=SUMPRODUCT((UPPER(TPersonnel[Fonction à supprimer])="OUI")*(TPersonnel[Sexe]="F"))} -> 0 | V4: =A11 -> VALENCE | W4: =B11 -> 15 | X4: =C11 -> 0 | AA4: =IFERROR(INDEX(_xlfn.ANCHORARRAY('⚙️ Parametres'!$K$3),3),"") -> Employé | AB4: =IF(AA4="","",COUNTIF(TPersonnel[Catégorie],AA4)) -> 2 | AC4: {=IF(AA4="","",SUMPRODUCT((UPPER(TPersonnel[Fonction à supprimer])="OUI")*(TPersonnel[Catégorie]=AA4)))} -> 0
V5: =A12 | W5: =IF(A12="","",B12) | X5: =IF(A12="","",C12) | AA5: =IFERROR(INDEX(_xlfn.ANCHORARRAY('⚙️ Parametres'!$K$3),4),"") -> Ouvrier | AB5: =IF(AA5="","",COUNTIF(TPersonnel[Catégorie],AA5)) -> 24 | AC5: {=IF(AA5="","",SUMPRODUCT((UPPER(TPersonnel[Fonction à supprimer])="OUI")*(TPersonnel[Catégorie]=AA5)))} -> 0
V6: =A13 | W6: =IF(A13="","",B13) | X6: =IF(A13="","",C13) | AA6: =IFERROR(INDEX(_xlfn.ANCHORARRAY('⚙️ Parametres'!$K$3),5),"") | AB6: =IF(AA6="","",COUNTIF(TPersonnel[Catégorie],AA6)) | AC6: {=IF(AA6="","",SUMPRODUCT((UPPER(TPersonnel[Fonction à supprimer])="OUI")*(TPersonnel[Catégorie]=AA6)))} | AE6: Sexe | AF6: Avant | AG6: Suppressions
A7: 📍 VENTILATION PAR SITE | I7: 💼 VENTILATION PAR CATÉGORIE (CSP) | V7: =A14 | W7: =IF(A14="","",B14) | X7: =IF(A14="","",C14) | AA7: =IFERROR(INDEX(_xlfn.ANCHORARRAY('⚙️ Parametres'!$K$3),6),"") | AB7: =IF(AA7="","",COUNTIF(TPersonnel[Catégorie],AA7)) | AC7: {=IF(AA7="","",SUMPRODUCT((UPPER(TPersonnel[Fonction à supprimer])="OUI")*(TPersonnel[Catégorie]=AA7)))} | AE7: Hommes | AF7: =J18 -> 28 | AG7: =K18 -> 0
A8: Site | B8: Avant | C8: Suppr. | D8: Après | E8: % Suppr. | F8: Coût Empl. Avant (€) | G8: Coût Empl. Après (€) | I8: Catégorie | J8: Avant | K8: Suppr. | L8: Après | M8: % Suppr. | N8: Coût Empl. Avant (€) | O8: Coût Empl. Après (€) | AA8: =IFERROR(INDEX(_xlfn.ANCHORARRAY('⚙️ Parametres'!$K$3),7),"") | AB8: =IF(AA8="","",COUNTIF(TPersonnel[Catégorie],AA8)) | AC8: {=IF(AA8="","",SUMPRODUCT((UPPER(TPersonnel[Fonction à supprimer])="OUI")*(TPersonnel[Catégorie]=AA8)))} | AE8: Femmes | AF8: =J19 -> 6 | AG8: =K19 -> 0
